Workbook

Sheet Leia primeiro
A1: Topologic — modelo financeiro gerencial, 24 meses
A2: Data de referência | B2: 2026-10-01
A3: Status | B3: Todas as receitas, custos, conversões e preços são hipóteses; não há clientes pagantes comprovados.
A4: Como editar | B4: Premissas, Capex e Agenda contêm entradas; cenários e Resumo usam fórmulas. Abra no Excel/LibreOffice para recalcular.
A5: Valores verificados | B5: Aba Verificado contém snapshot calculado independentemente em Python; não muda quando entradas forem editadas.
A6: Mês zero | B6: Aquisição de hardware e despesas pré-operacionais. M1 começa após autorização do plano, sem data-calendário assumida.
A7: Implantação | B7: 36 mil em dois marcos mensais de 50%; 120h distribuídas nos mesmos dois meses. Sem atraso/inadimplência nos marcos, hipótese forte.
A8: Assinatura | B8: Começa dois meses após início do projeto apenas para projetos que convertem; recebimento padrão 1 mês depois.
A9: Tributação | B9: Provisão gerencial sobre faturamento no próprio mês; não é enquadramento ou calendário fiscal validado.
A10: Comissão | B10: Reserva média de 5% sobre recebimentos, não promessa de comissão a parceiros.
A11: Pessoal | B11: Equipe interna no fixo; implantação e curadoria executadas por prestadores de entrega nos custos diretos. Não duplicar as mesmas horas.
A12: Caixa | B12: Acumulado sem aporte; capital indicado cobre maior déficit mais maior entre 15% do déficit e três meses do fixo máximo.
A13: Resultado recorrente | B13: MRR menos provisão tributária/comercial, custo direto recorrente e fixo. Não depende de novas implantações e não inclui depreciação.
... A18: Canais externos | B18: MCP não transfere a inferência do Claude/ChatGPT para a DGX. Licenças clientes/ERP/ITSM não incluídas.

Sheet Premissas
A1: Parâmetro | B1: Valor | C1: Unidade/observação
A2: setup_price | B2: 36000 | C2: R$/implantação; hipótese
A3: strategic_price | B3: 7500 | C3: R$/cliente/mês; hipótese
A4: live_uplift | B4: 4500 | C4: R$/cliente vivo/mês adicional; hipótese
A5: setup_hours | B5: 120 | C5: horas/implantação em dois meses
A6: hourly_cost | B6: 150 | C6: R$/hora prestador de entrega
A7: client_cost | B7: 1500 | C7: R$/cliente/mês: 6h x150 +600 infraestrutura
A8: live_cost | B8: 1000 | C8: R$/cliente vivo/mês: 4h x150 +400 infraestrutura
A9: tax_rate | B9: 0.08 | C9: Provisão/faturamento; validar contador
A10: commission_rate | B10: 0.05 | C10: Reserva comercial/recebimento
A11: conversion_delay | B11: 2 | C11: Meses do início até assinatura; fórmula usa esta entrada
A12: receipt_lag | B12: 1 | C12: Meses do faturamento recorrente até recebimento; >=1
A13: attach_conservative | B13: 0 | C13: Percentual alvo vivo; arredondado para baixo
... A22: depreciation_months | B22: 36 | C22: Vida econômica gerencial; sem valor residual

Sheet Capex
A1: Item | B1: Quantidade | C1: Unitário R$ | D1: Total R$ | E1: Classificação / status
A2: DGX Spark 128GB/4TB | B2: 2 | C2: 65000 | D2: =B2*C2 | E2: CAPEX; reserva sem cotação brasileira confirmada
A3: Nobreak e proteção elétrica | B3: 1 | C3: 6000 | D3: =B3*C3 | E3: CAPEX; hipótese
A4: Rede e segurança de perímetro | B4: 1 | C4: 4000 | D4: =B4*C4 | E4: CAPEX; hipótese
A5: Backup local complementar | B5: 1 | C5: 4000 | D5: =B5*C5 | E5: CAPEX; hipótese; cópia externa no OPEX
A6: Estação/periféricos complementares | B6: 1 | C6: 6000 | D6: =B6*C6 | E6: CAPEX; hipótese
A7: Jurídico, contratos e constituição | B7: 1 | C7: 12000 | D7: =B7*C7 | E7: Pré-operação; hipótese
A8: Revisão inicial de segurança | B8: 1 | C8: 12000 | D8: =B8*C8 | E8: Pré-operação; hipótese
A9: Total hardware | D9: =SUM(D2:D6)
A10: Total pré-operação | D10: =SUM(D7:D8)
A11: Desembolso M0 | D11: =D9+D10
A12: Depreciação mensal referência | D12: =D9/Premissas!$B$22

Sheet Agenda
A1: Cenário | B1: Mês | C1: Novos projetos pagos | D1: Destes, convertem em assinatura | E1: Saídas de assinatura no mês
A2: Conservador | B2: 1 | C2: 0 | D2: 0 | E2: 0
A3: Conservador | B3: 2 | C3: 0 | D3: 0 | E3: 0
A4: Conservador | B4: 3 | C4: 0 | D4: 0 | E4: 0
A5: Conservador | B5: 4 | C5: 0 | D5: 0 | E5: 0
A6: Conservador | B6: 5 | C6: 0 | D6: 0 | E6: 0
A7: Conservador | B7: 6 | C7: 1 | D7: 1 | E7: 0
A8: Conservador | B8: 7 | C8: 0 | D8: 0 | E8: 0
A9: Conservador | B9: 8 | C9: 0 | D9: 0 | E9: 0
A10: Conservador | B10: 9 | C10: 0 | D10: 0 | E10: 0
A11: Conservador | B11: 10 | C11: 1 | D11: 0 | E11: 0
A12: Conservador | B12: 11 | C12: 0 | D12: 0 | E12: 0
A13: Conservador | B13: 12 | C13: 0 | D13: 0 | E13: 0
... A73: Expansao | B73: 24 | C73: 1 | D73: 1 | E73: 0

Sheet Conservador
A1: Mês | B1: Projetos novos | C1: Assinaturas novas | D1: Saídas | E1: Clientes ativos | F1: Clientes vivos | G1: Projetos em entrega | H1: Fat. implantação | I1: Fat. recorrente/MRR | J1: Faturamento total | K1: Receb. recorrente | L1: Recebimentos totais | M1: Fixo | N1: Custo implantação | O1: Custo recorrente | P1: Provisão tributos | Q1: Reserva comercial | R1: Saídas totais | S1: Caixa do mês | T1: Acumulado sem aporte | U1: Resultado recorrente | V1: Horas implantação | W1: Horas curadoria | X1: Contas a receber recorrente
A2: 0 | B2: 0 | C2: 0 | D2: 0 | E2: 0 | F2: 0 | G2: 0 | H2: 0 | I2: 0 | J2: 0 | K2: 0 | L2: 0 | M2: 0 | N2: 0 | O2: 0 | P2: 0 | Q2: 0 | R2: =Capex!D11 | S2: =-R2 | T2: =S2 | U2: 0 | V2: 0 | W2: 0 | X2: 0
A3: 1 | B3: =Agenda!C2 | C3: =IF(A3>Premissas!$B$11,INDEX(Agenda!$D$2:$D$25,A3-Premissas!$B$11),0) | D3: =Agenda!E2 | E3: =E2+C3-D3 | F3: =IF(A3>=Premissas!$B$16,ROUNDDOWN(E3*Premissas!$B$13,0),0) | G3: =B3+B2 | H3: =G3*Premissas!$B$2/2 | I3: =E3*Premissas!$B$3+F3*Premissas!$B$4 | J3: =H3+I3 | K3: =IF(A3>Premissas!$B$12,INDEX($I$3:$I$26,A3-Premissas!$B$12),0) | L3: =H3+K3 | M3: =IF(A3<=6,Premissas!$B$17,IF(A3<=12,Premissas!$B$18,Premissas!$B$19)) | N3: =G3*Premissas!$B$5/2*Premissas!$B$6 | O3: =E3*Premissas!$B$7+F3*Premissas!$B$8 | P3: =J3*Premissas!$B$9 | Q3: =L3*Premissas!$B$10 | R3: =SUM(M3:Q3) | S3: =L3-R3 | T3: =T2+S3 | U3: =I3*(1-Premissas!$B$9-Premissas!$B$10)-O3-M3 | V3: =G3*Premissas!$B$5/2 | W3: =E3*6+F3*4 | X3: =X2+I3-K3
A4: 2 | B4: =Agenda!C3 | C4: =IF(A4>Premissas!$B$11,INDEX(Agenda!$D$2:$D$25,A4-Premissas!$B$11),0) | D4: =Agenda!E3 | E4: =E3+C4-D4 | F4: =IF(A4>=Premissas!$B$16,ROUNDDOWN(E4*Premissas!$B$13,0),0) | G4: =B4+B3 | H4: =G4*Premissas!$B$2/2 | I4: =E4*Premissas!$B$3+F4*Premissas!$B$4 | J4: =H4+I4 | K4: =IF(A4>Premissas!$B$12,INDEX($I$3:$I$26,A4-Premissas!$B$12),0) | L4: =H4+K4 | M4: =IF(A4<=6,Premissas!$B$17,IF(A4<=12,Premissas!$B$18,Premissas!$B$19)) | N4: =G4*Premissas!$B$5/2*Premissas!$B$6 | O4: =E4*Premissas!$B$7+F4*Premissas!$B$8 | P4: =J4*Premissas!$B$9 | Q4: =L4*Premissas!$B$10 | R4: =SUM(M4:Q4) | S4: =L4-R4 | T4: =T3+S4 | U4: =I4*(1-Premissas!$B$9-Premissas!$B$10)-O4-M4 | V4: =G4*Premissas!$B$5/2 | W4: =E4*6+F4*4 | X4: =X3+I4-K4
A5: 3 | B5: =Agenda!C4 | C5: =IF(A5>Premissas!$B$11,INDEX(Agenda!$D$2:$D$25,A5-Premissas!$B$11),0) | D5: =Agenda!E4 | E5: =E4+C5-D5 | F5: =IF(A5>=Premissas!$B$16,ROUNDDOWN(E5*Premissas!$B$13,0),0) | G5: =B5+B4 | H5: =G5*Premissas!$B$2/2 | I5: =E5*Premissas!$B$3+F5*Premissas!$B$4 | J5: =H5+I5 | K5: =IF(A5>Premissas!$B$12,INDEX($I$3:$I$26,A5-Premissas!$B$12),0) | L5: =H5+K5 | M5: =IF(A5<=6,Premissas!$B$17,IF(A5<=12,Premissas!$B$18,Premissas!$B$19)) | N5: =G5*Premissas!$B$5/2*Premissas!$B$6 | O5: =E5*Premissas!$B$7+F5*Premissas!$B$8 | P5: =J5*Premissas!$B$9 | Q5: =L5*Premissas!$B$10 | R5: =SUM(M5:Q5) | S5: =L5-R5 | T5: =T4+S5 | U5: =I5*(1-Premissas!$B$9-Premissas!$B$10)-O5-M5 | V5: =G5*Premissas!$B$5/2 | W5: =E5*6+F5*4 | X5: =X4+I5-K5
A6: 4 | B6: =Agenda!C5 | C6: =IF(A6>Premissas!$B$11,INDEX(Agenda!$D$2:$D$25,A6-Premissas!$B$11),0) | D6: =Agenda!E5 | E6: =E5+C6-D6 | F6: =IF(A6>=Premissas!$B$16,ROUNDDOWN(E6*Premissas!$B$13,0),0) | G6: =B6+B5 | H6: =G6*Premissas!$B$2/2 | I6: =E6*Premissas!$B$3+F6*Premissas!$B$4 | J6: =H6+I6 | K6: =IF(A6>Premissas!$B$12,INDEX($I$3:$I$26,A6-Premissas!$B$12),0) | L6: =H6+K6 | M6: =IF(A6<=6,Premissas!$B$17,IF(A6<=12,Premissas!$B$18,Premissas!$B$19)) | N6: =G6*Premissas!$B$5/2*Premissas!$B$6 | O6: =E6*Premissas!$B$7+F6*Premissas!$B$8 | P6: =J6*Premissas!$B$9 | Q6: =L6*Premissas!$B$10 | R6: =SUM(M6:Q6) | S6: =L6-R6 | T6: =T5+S6 | U6: =I6*(1-Premissas!$B$9-Premissas!$B$10)-O6-M6 | V6: =G6*Premissas!$B$5/2 | W6: =E6*6+F6*4 | X6: =X5+I6-K6
A7: 5 | B7: =Agenda!C6 | C7: =IF(A7>Premissas!$B$11,INDEX(Agenda!$D$2:$D$25,A7-Premissas!$B$11),0) | D7: =Agenda!E6 | E7: =E6+C7-D7 | F7: =IF(A7>=Premissas!$B$16,ROUNDDOWN(E7*Premissas!$B$13,0),0) | G7: =B7+B6 | H7: =G7*Premissas!$B$2/2 | I7: =E7*Premissas!$B$3+F7*Premissas!$B$4 | J7: =H7+I7 | K7: =IF(A7>Premissas!$B$12,INDEX($I$3:$I$26,A7-Premissas!$B$12),0) | L7: =H7+K7 | M7: =IF(A7<=6,Premissas!$B$17,IF(A7<=12,Premissas!$B$18,Premissas!$B$19)) | N7: =G7*Premissas!$B$5/2*Premissas!$B$6 | O7: =E7*Premissas!$B$7+F7*Premissas!$B$8 | P7: =J7*Premissas!$B$9 | Q7: =L7*Premissas!$B$10 | R7: =SUM(M7:Q7) | S7: =L7-R7 | T7: =T6+S7 | U7: =I7*(1-Premissas!$B$9-Premissas!$B$10)-O7-M7 | V7: =G7*Premissas!$B$5/2 | W7: =E7*6+F7*4 | X7: =X6+I7-K7
A8: 6 | B8: =Agenda!C7 | C8: =IF(A8>Premissas!$B$11,INDEX(Agenda!$D$2:$D$25,A8-Premissas!$B$11),0) | D8: =Agenda!E7 | E8: =E7+C8-D8 | F8: =IF(A8>=Premissas!$B$16,ROUNDDOWN(E8*Premissas!$B$13,0),0) | G8: =B8+B7 | H8: =G8*Premissas!$B$2/2 | I8: =E8*Premissas!$B$3+F8*Premissas!$B$4 | J8: =H8+I8 | K8: =IF(A8>Premissas!$B$12,INDEX($I$3:$I$26,A8-Premissas!$B$12),0) | L8: =H8+K8 | M8: =IF(A8<=6,Premissas!$B$17,IF(A8<=12,Premissas!$B$18,Premissas!$B$19)) | N8: =G8*Premissas!$B$5/2*Premissas!$B$6 | O8: =E8*Premissas!$B$7+F8*Premissas!$B$8 | P8: =J8*Premissas!$B$9 | Q8: =L8*Premissas!$B$10 | R8: =SUM(M8:Q8) | S8: =L8-R8 | T8: =T7+S8 | U8: =I8*(1-Premissas!$B$9-Premissas!$B$10)-O8-M8 | V8: =G8*Premissas!$B$5/2 | W8: =E8*6+F8*4 | X8: =X7+I8-K8
A9: 7 | B9: =Agenda!C8 | C9: =IF(A9>Premissas!$B$11,INDEX(Agenda!$D$2:$D$25,A9-Premissas!$B$11),0) | D9: =Agenda!E8 | E9: =E8+C9-D9 | F9: =IF(A9>=Premissas!$B$16,ROUNDDOWN(E9*Premissas!$B$13,0),0) | G9: =B9+B8 | H9: =G9*Premissas!$B$2/2 | I9: =E9*Premissas!$B$3+F9*Premissas!$B$4 | J9: =H9+I9 | K9: =IF(A9>Premissas!$B$12,INDEX($I$3:$I$26,A9-Premissas!$B$12),0) | L9: =H9+K9 | M9: =IF(A9<=6,Premissas!$B$17,IF(A9<=12,Premissas!$B$18,Premissas!$B$19)) | N9: =G9*Premissas!$B$5/2*Premissas!$B$6 | O9: =E9*Premissas!$B$7+F9*Premissas!$B$8 | P9: =J9*Premissas!$B$9 | Q9: =L9*Premissas!$B$10 | R9: =SUM(M9:Q9) | S9: =L9-R9 | T9: =T8+S9 | U9: =I9*(1-Premissas!$B$9-Premissas!$B$10)-O9-M9 | V9: =G9*Premissas!$B$5/2 | W9: =E9*6+F9*4 | X9: =X8+I9-K9
A10: 8 | B10: =Agenda!C9 | C10: =IF(A10>Premissas!$B$11,INDEX(Agenda!$D$2:$D$25,A10-Premissas!$B$11),0) | D10: =Agenda!E9 | E10: =E9+C10-D10 | F10: =IF(A10>=Premissas!$B$16,ROUNDDOWN(E10*Premissas!$B$13,0),0) | G10: =B10+B9 | H10: =G10*Premissas!$B$2/2 | I10: =E10*Premissas!$B$3+F10*Premissas!$B$4 | J10: =H10+I10 | K10: =IF(A10>Premissas!$B$12,INDEX($I$3:$I$26,A10-Premissas!$B$12),0) | L10: =H10+K10 | M10: =IF(A10<=6,Premissas!$B$17,IF(A10<=12,Premissas!$B$18,Premissas!$B$19)) | N10: =G10*Premissas!$B$5/2*Premissas!$B$6 | O10: =E10*Premissas!$B$7+F10*Premissas!$B$8 | P10: =J10*Premissas!$B$9 | Q10: =L10*Premissas!$B$10 | R10: =SUM(M10:Q10) | S10: =L10-R10 | T10: =T9+S10 | U10: =I10*(1-Premissas!$B$9-Premissas!$B$10)-O10-M10 | V10: =G10*Premissas!$B$5/2 | W10: =E10*6+F10*4 | X10: =X9+I10-K10
A11: 9 | B11: =Agenda!C10 | C11: =IF(A11>Premissas!$B$11,INDEX(Agenda!$D$2:$D$25,A11-Premissas!$B$11),0) | D11: =Agenda!E10 | E11: =E10+C11-D11 | F11: =IF(A11>=Premissas!$B$16,ROUNDDOWN(E11*Premissas!$B$13,0),0) | G11: =B11+B10 | H11: =G11*Premissas!$B$2/2 | I11: =E11*Premissas!$B$3+F11*Premissas!$B$4 | J11: =H11+I11 | K11: =IF(A11>Premissas!$B$12,INDEX($I$3:$I$26,A11-Premissas!$B$12),0) | L11: =H11+K11 | M11: =IF(A11<=6,Premissas!$B$17,IF(A11<=12,Premissas!$B$18,Premissas!$B$19)) | N11: =G11*Premissas!$B$5/2*Premissas!$B$6 | O11: =E11*Premissas!$B$7+F11*Premissas!$B$8 | P11: =J11*Premissas!$B$9 | Q11: =L11*Premissas!$B$10 | R11: =SUM(M11:Q11) | S11: =L11-R11 | T11: =T10+S11 | U11: =I11*(1-Premissas!$B$9-Premissas!$B$10)-O11-M11 | V11: =G11*Premissas!$B$5/2 | W11: =E11*6+F11*4 | X11: =X10+I11-K11
A12: 10 | B12: =Agenda!C11 | C12: =IF(A12>Premissas!$B$11,INDEX(Agenda!$D$2:$D$25,A12-Premissas!$B$11),0) | D12: =Agenda!E11 | E12: =E11+C12-D12 | F12: =IF(A12>=Premissas!$B$16,ROUNDDOWN(E12*Premissas!$B$13,0),0) | G12: =B12+B11 | H12: =G12*Premissas!$B$2/2 | I12: =E12*Premissas!$B$3+F12*Premissas!$B$4 | J12: =H12+I12 | K12: =IF(A12>Premissas!$B$12,INDEX($I$3:$I$26,A12-Premissas!$B$12),0) | L12: =H12+K12 | M12: =IF(A12<=6,Premissas!$B$17,IF(A12<=12,Premissas!$B$18,Premissas!$B$19)) | N12: =G12*Premissas!$B$5/2*Premissas!$B$6 | O12: =E12*Premissas!$B$7+F12*Premissas!$B$8 | P12: =J12*Premissas!$B$9 | Q12: =L12*Premissas!$B$10 | R12: =SUM(M12:Q12) | S12: =L12-R12 | T12: =T11+S12 | U12: =I12*(1-Premissas!$B$9-Premissas!$B$10)-O12-M12 | V12: =G12*Premissas!$B$5/2 | W12: =E12*6+F12*4 | X12: =X11+I12-K12
A13: 11 | B13: =Agenda!C12 | C13: =IF(A13>Premissas!$B$11,INDEX(Agenda!$D$2:$D$25,A13-Premissas!$B$11),0) | D13: =Agenda!E12 | E13: =E12+C13-D13 | F13: =IF(A13>=Premissas!$B$16,ROUNDDOWN(E13*Premissas!$B$13,0),0) | G13: =B13+B12 | H13: =G13*Premissas!$B$2/2 | I13: =E13*Premissas!$B$3+F13*Premissas!$B$4 | J13: =H13+I13 | K13: =IF(A13>Premissas!$B$12,INDEX($I$3:$I$26,A13-Premissas!$B$12),0) | L13: =H13+K13 | M13: =IF(A13<=6,Premissas!$B$17,IF(A13<=12,Premissas!$B$18,Premissas!$B$19)) | N13: =G13*Premissas!$B$5/2*Premissas!$B$6 | O13: =E13*Premissas!$B$7+F13*Premissas!$B$8 | P13: =J13*Premissas!$B$9 | Q13: =L13*Premissas!$B$10 | R13: =SUM(M13:Q13) | S13: =L13-R13 | T13: =T12+S13 | U13: =I13*(1-Premissas!$B$9-Premissas!$B$10)-O13-M13 | V13: =G13*Premissas!$B$5/2 | W13: =E13*6+F13*4 | X13: =X12+I13-K13
A14: 12 | B14: =Agenda!C13 | C14: =IF(A14>Premissas!$B$11,INDEX(Agenda!$D$2:$D$25,A14-Premissas!$B$11),0) | D14: =Agenda!E13 | E14: =E13+C14-D14 | F14: =IF(A14>=Premissas!$B$16,ROUNDDOWN(E14*Premissas!$B$13,0),0) | G14: =B14+B13 | H14: =G14*Premissas!$B$2/2 | I14: =E14*Premissas!$B$3+F14*Premissas!$B$4 | J14: =H14+I14 | K14: =IF(A14>Premissas!$B$12,INDEX($I$3:$I$26,A14-Premissas!$B$12),0) | L14: =H14+K14 | M14: =IF(A14<=6,Premissas!$B$17,IF(A14<=12,Premissas!$B$18,Premissas!$B$19)) | N14: =G14*Premissas!$B$5/2*Premissas!$B$6 | O14: =E14*Premissas!$B$7+F14*Premissas!$B$8 | P14: =J14*Premissas!$B$9 | Q14: =L14*Premissas!$B$10 | R14: =SUM(M14:Q14) | S14: =L14-R14 | T14: =T13+S14 | U14: =I14*(1-Premissas!$B$9-Premissas!$B$10)-O14-M14 | V14: =G14*Premissas!$B$5/2 | W14: =E14*6+F14*4 | X14: =X13+I14-K14
... A26: 24 | B26: =Agenda!C25 | C26: =IF(A26>Premissas!$B$11,INDEX(Agenda!$D$2:$D$25,A26-Premissas!$B$11),0) | D26: =Agenda!E25 | E26: =E25+C26-D26 | F26: =IF(A26>=Premissas!$B$16,ROUNDDOWN(E26*Premissas!$B$13,0),0) | G26: =B26+B25 | H26: =G26*Premissas!$B$2/2 | I26: =E26*Premissas!$B$3+F26*Premissas!$B$4 | J26: =H26+I26 | K26: =IF(A26>Premissas!$B$12,INDEX($I$3:$I$26,A26-Premissas!$B$12),0) | L26: =H26+K26 | M26: =IF(A26<=6,Premissas!$B$17,IF(A26<=12,Premissas!$B$18,Premissas!$B$19)) | N26: =G26*Premissas!$B$5/2*Premissas!$B$6 | O26: =E26*Premissas!$B$7+F26*Premissas!$B$8 | P26: =J26*Premissas!$B$9 | Q26: =L26*Premissas!$B$10 | R26: =SUM(M26:Q26) | S26: =L26-R26 | T26: =T25+S26 | U26: =I26*(1-Premissas!$B$9-Premissas!$B$10)-O26-M26 | V26: =G26*Premissas!$B$5/2 | W26: =E26*6+F26*4 | X26: =X25+I26-K26

Sheet Base
A1: Mês | B1: Projetos novos | C1: Assinaturas novas | D1: Saídas | E1: Clientes ativos | F1: Clientes vivos | G1: Projetos em entrega | H1: Fat. implantação | I1: Fat. recorrente/MRR | J1: Faturamento total | K1: Receb. recorrente | L1: Recebimentos totais | M1: Fixo | N1: Custo implantação | O1: Custo recorrente | P1: Provisão tributos | Q1: Reserva comercial | R1: Saídas totais | S1: Caixa do mês | T1: Acumulado sem aporte | U1: Resultado recorrente | V1: Horas implantação | W1: Horas curadoria | X1: Contas a receber recorrente
A2: 0 | B2: 0 | C2: 0 | D2: 0 | E2: 0 | F2: 0 | G2: 0 | H2: 0 | I2: 0 | J2: 0 | K2: 0 | L2: 0 | M2: 0 | N2: 0 | O2: 0 | P2: 0 | Q2: 0 | R2: =Capex!D11 | S2: =-R2 | T2: =S2 | U2: 0 | V2: 0 | W2: 0 | X2: 0
A3: 1 | B3: =Agenda!C26 | C3: =IF(A3>Premissas!$B$11,INDEX(Agenda!$D$26:$D$49,A3-Premissas!$B$11),0) | D3: =Agenda!E26 | E3: =E2+C3-D3 | F3: =IF(A3>=Premissas!$B$16,ROUNDDOWN(E3*Premissas!$B$14,0),0) | G3: =B3+B2 | H3: =G3*Premissas!$B$2/2 | I3: =E3*Premissas!$B$3+F3*Premissas!$B$4 | J3: =H3+I3 | K3: =IF(A3>Premissas!$B$12,INDEX($I$3:$I$26,A3-Premissas!$B$12),0) | L3: =H3+K3 | M3: =IF(A3<=6,Premissas!$B$17,IF(A3<=12,Premissas!$B$18,Premissas!$B$19)) | N3: =G3*Premissas!$B$5/2*Premissas!$B$6 | O3: =E3*Premissas!$B$7+F3*Premissas!$B$8 | P3: =J3*Premissas!$B$9 | Q3: =L3*Premissas!$B$10 | R3: =SUM(M3:Q3) | S3: =L3-R3 | T3: =T2+S3 | U3: =I3*(1-Premissas!$B$9-Premissas!$B$10)-O3-M3 | V3: =G3*Premissas!$B$5/2 | W3: =E3*6+F3*4 | X3: =X2+I3-K3
A4: 2 | B4: =Agenda!C27 | C4: =IF(A4>Premissas!$B$11,INDEX(Agenda!$D$26:$D$49,A4-Premissas!$B$11),0) | D4: =Agenda!E27 | E4: =E3+C4-D4 | F4: =IF(A4>=Premissas!$B$16,ROUNDDOWN(E4*Premissas!$B$14,0),0) | G4: =B4+B3 | H4: =G4*Premissas!$B$2/2 | I4: =E4*Premissas!$B$3+F4*Premissas!$B$4 | J4: =H4+I4 | K4: =IF(A4>Premissas!$B$12,INDEX($I$3:$I$26,A4-Premissas!$B$12),0) | L4: =H4+K4 | M4: =IF(A4<=6,Premissas!$B$17,IF(A4<=12,Premissas!$B$18,Premissas!$B$19)) | N4: =G4*Premissas!$B$5/2*Premissas!$B$6 | O4: =E4*Premissas!$B$7+F4*Premissas!$B$8 | P4: =J4*Premissas!$B$9 | Q4: =L4*Premissas!$B$10 | R4: =SUM(M4:Q4) | S4: =L4-R4 | T4: =T3+S4 | U4: =I4*(1-Premissas!$B$9-Premissas!$B$10)-O4-M4 | V4: =G4*Premissas!$B$5/2 | W4: =E4*6+F4*4 | X4: =X3+I4-K4
A5: 3 | B5: =Agenda!C28 | C5: =IF(A5>Premissas!$B$11,INDEX(Agenda!$D$26:$D$49,A5-Premissas!$B$11),0) | D5: =Agenda!E28 | E5: =E4+C5-D5 | F5: =IF(A5>=Premissas!$B$16,ROUNDDOWN(E5*Premissas!$B$14,0),0) | G5: =B5+B4 | H5: =G5*Premissas!$B$2/2 | I5: =E5*Premissas!$B$3+F5*Premissas!$B$4 | J5: =H5+I5 | K5: =IF(A5>Premissas!$B$12,INDEX($I$3:$I$26,A5-Premissas!$B$12),0) | L5: =H5+K5 | M5: =IF(A5<=6,Premissas!$B$17,IF(A5<=12,Premissas!$B$18,Premissas!$B$19)) | N5: =G5*Premissas!$B$5/2*Premissas!$B$6 | O5: =E5*Premissas!$B$7+F5*Premissas!$B$8 | P5: =J5*Premissas!$B$9 | Q5: =L5*Premissas!$B$10 | R5: =SUM(M5:Q5) | S5: =L5-R5 | T5: =T4+S5 | U5: =I5*(1-Premissas!$B$9-Premissas!$B$10)-O5-M5 | V5: =G5*Premissas!$B$5/2 | W5: =E5*6+F5*4 | X5: =X4+I5-K5
A6: 4 | B6: =Agenda!C29 | C6: =IF(A6>Premissas!$B$11,INDEX(Agenda!$D$26:$D$49,A6-Premissas!$B$11),0) | D6: =Agenda!E29 | E6: =E5+C6-D6 | F6: =IF(A6>=Premissas!$B$16,ROUNDDOWN(E6*Premissas!$B$14,0),0) | G6: =B6+B5 | H6: =G6*Premissas!$B$2/2 | I6: =E6*Premissas!$B$3+F6*Premissas!$B$4 | J6: =H6+I6 | K6: =IF(A6>Premissas!$B$12,INDEX($I$3:$I$26,A6-Premissas!$B$12),0) | L6: =H6+K6 | M6: =IF(A6<=6,Premissas!$B$17,IF(A6<=12,Premissas!$B$18,Premissas!$B$19)) | N6: =G6*Premissas!$B$5/2*Premissas!$B$6 | O6: =E6*Premissas!$B$7+F6*Premissas!$B$8 | P6: =J6*Premissas!$B$9 | Q6: =L6*Premissas!$B$10 | R6: =SUM(M6:Q6) | S6: =L6-R6 | T6: =T5+S6 | U6: =I6*(1-Premissas!$B$9-Premissas!$B$10)-O6-M6 | V6: =G6*Premissas!$B$5/2 | W6: =E6*6+F6*4 | X6: =X5+I6-K6
A7: 5 | B7: =Agenda!C30 | C7: =IF(A7>Premissas!$B$11,INDEX(Agenda!$D$26:$D$49,A7-Premissas!$B$11),0) | D7: =Agenda!E30 | E7: =E6+C7-D7 | F7: =IF(A7>=Premissas!$B$16,ROUNDDOWN(E7*Premissas!$B$14,0),0) | G7: =B7+B6 | H7: =G7*Premissas!$B$2/2 | I7: =E7*Premissas!$B$3+F7*Premissas!$B$4 | J7: =H7+I7 | K7: =IF(A7>Premissas!$B$12,INDEX($I$3:$I$26,A7-Premissas!$B$12),0) | L7: =H7+K7 | M7: =IF(A7<=6,Premissas!$B$17,IF(A7<=12,Premissas!$B$18,Premissas!$B$19)) | N7: =G7*Premissas!$B$5/2*Premissas!$B$6 | O7: =E7*Premissas!$B$7+F7*Premissas!$B$8 | P7: =J7*Premissas!$B$9 | Q7: =L7*Premissas!$B$10 | R7: =SUM(M7:Q7) | S7: =L7-R7 | T7: =T6+S7 | U7: =I7*(1-Premissas!$B$9-Premissas!$B$10)-O7-M7 | V7: =G7*Premissas!$B$5/2 | W7: =E7*6+F7*4 | X7: =X6+I7-K7
A8: 6 | B8: =Agenda!C31 | C8: =IF(A8>Premissas!$B$11,INDEX(Agenda!$D$26:$D$49,A8-Premissas!$B$11),0) | D8: =Agenda!E31 | E8: =E7+C8-D8 | F8: =IF(A8>=Premissas!$B$16,ROUNDDOWN(E8*Premissas!$B$14,0),0) | G8: =B8+B7 | H8: =G8*Premissas!$B$2/2 | I8: =E8*Premissas!$B$3+F8*Premissas!$B$4 | J8: =H8+I8 | K8: =IF(A8>Premissas!$B$12,INDEX($I$3:$I$26,A8-Premissas!$B$12),0) | L8: =H8+K8 | M8: =IF(A8<=6,Premissas!$B$17,IF(A8<=12,Premissas!$B$18,Premissas!$B$19)) | N8: =G8*Premissas!$B$5/2*Premissas!$B$6 | O8: =E8*Premissas!$B$7+F8*Premissas!$B$8 | P8: =J8*Premissas!$B$9 | Q8: =L8*Premissas!$B$10 | R8: =SUM(M8:Q8) | S8: =L8-R8 | T8: =T7+S8 | U8: =I8*(1-Premissas!$B$9-Premissas!$B$10)-O8-M8 | V8: =G8*Premissas!$B$5/2 | W8: =E8*6+F8*4 | X8: =X7+I8-K8
A9: 7 | B9: =Agenda!C32 | C9: =IF(A9>Premissas!$B$11,INDEX(Agenda!$D$26:$D$49,A9-Premissas!$B$11),0) | D9: =Agenda!E32 | E9: =E8+C9-D9 | F9: =IF(A9>=Premissas!$B$16,ROUNDDOWN(E9*Premissas!$B$14,0),0) | G9: =B9+B8 | H9: =G9*Premissas!$B$2/2 | I9: =E9*Premissas!$B$3+F9*Premissas!$B$4 | J9: =H9+I9 | K9: =IF(A9>Premissas!$B$12,INDEX($I$3:$I$26,A9-Premissas!$B$12),0) | L9: =H9+K9 | M9: =IF(A9<=6,Premissas!$B$17,IF(A9<=12,Premissas!$B$18,Premissas!$B$19)) | N9: =G9*Premissas!$B$5/2*Premissas!$B$6 | O9: =E9*Premissas!$B$7+F9*Premissas!$B$8 | P9: =J9*Premissas!$B$9 | Q9: =L9*Premissas!$B$10 | R9: =SUM(M9:Q9) | S9: =L9-R9 | T9: =T8+S9 | U9: =I9*(1-Premissas!$B$9-Premissas!$B$10)-O9-M9 | V9: =G9*Premissas!$B$5/2 | W9: =E9*6+F9*4 | X9: =X8+I9-K9
A10: 8 | B10: =Agenda!C33 | C10: =IF(A10>Premissas!$B$11,INDEX(Agenda!$D$26:$D$49,A10-Premissas!$B$11),0) | D10: =Agenda!E33 | E10: =E9+C10-D10 | F10: =IF(A10>=Premissas!$B$16,ROUNDDOWN(E10*Premissas!$B$14,0),0) | G10: =B10+B9 | H10: =G10*Premissas!$B$2/2 | I10: =E10*Premissas!$B$3+F10*Premissas!$B$4 | J10: =H10+I10 | K10: =IF(A10>Premissas!$B$12,INDEX($I$3:$I$26,A10-Premissas!$B$12),0) | L10: =H10+K10 | M10: =IF(A10<=6,Premissas!$B$17,IF(A10<=12,Premissas!$B$18,Premissas!$B$19)) | N10: =G10*Premissas!$B$5/2*Premissas!$B$6 | O10: =E10*Premissas!$B$7+F10*Premissas!$B$8 | P10: =J10*Premissas!$B$9 | Q10: =L10*Premissas!$B$10 | R10: =SUM(M10:Q10) | S10: =L10-R10 | T10: =T9+S10 | U10: =I10*(1-Premissas!$B$9-Premissas!$B$10)-O10-M10 | V10: =G10*Premissas!$B$5/2 | W10: =E10*6+F10*4 | X10: =X9+I10-K10
A11: 9 | B11: =Agenda!C34 | C11: =IF(A11>Premissas!$B$11,INDEX(Agenda!$D$26:$D$49,A11-Premissas!$B$11),0) | D11: =Agenda!E34 | E11: =E10+C11-D11 | F11: =IF(A11>=Premissas!$B$16,ROUNDDOWN(E11*Premissas!$B$14,0),0) | G11: =B11+B10 | H11: =G11*Premissas!$B$2/2 | I11: =E11*Premissas!$B$3+F11*Premissas!$B$4 | J11: =H11+I11 | K11: =IF(A11>Premissas!$B$12,INDEX($I$3:$I$26,A11-Premissas!$B$12),0) | L11: =H11+K11 | M11: =IF(A11<=6,Premissas!$B$17,IF(A11<=12,Premissas!$B$18,Premissas!$B$19)) | N11: =G11*Premissas!$B$5/2*Premissas!$B$6 | O11: =E11*Premissas!$B$7+F11*Premissas!$B$8 | P11: =J11*Premissas!$B$9 | Q11: =L11*Premissas!$B$10 | R11: =SUM(M11:Q11) | S11: =L11-R11 | T11: =T10+S11 | U11: =I11*(1-Premissas!$B$9-Premissas!$B$10)-O11-M11 | V11: =G11*Premissas!$B$5/2 | W11: =E11*6+F11*4 | X11: =X10+I11-K11
A12: 10 | B12: =Agenda!C35 | C12: =IF(A12>Premissas!$B$11,INDEX(Agenda!$D$26:$D$49,A12-Premissas!$B$11),0) | D12: =Agenda!E35 | E12: =E11+C12-D12 | F12: =IF(A12>=Premissas!$B$16,ROUNDDOWN(E12*Premissas!$B$14,0),0) | G12: =B12+B11 | H12: =G12*Premissas!$B$2/2 | I12: =E12*Premissas!$B$3+F12*Premissas!$B$4 | J12: =H12+I12 | K12: =IF(A12>Premissas!$B$12,INDEX($I$3:$I$26,A12-Premissas!$B$12),0) | L12: =H12+K12 | M12: =IF(A12<=6,Premissas!$B$17,IF(A12<=12,Premissas!$B$18,Premissas!$B$19)) | N12: =G12*Premissas!$B$5/2*Premissas!$B$6 | O12: =E12*Premissas!$B$7+F12*Premissas!$B$8 | P12: =J12*Premissas!$B$9 | Q12: =L12*Premissas!$B$10 | R12: =SUM(M12:Q12) | S12: =L12-R12 | T12: =T11+S12 | U12: =I12*(1-Premissas!$B$9-Premissas!$B$10)-O12-M12 | V12: =G12*Premissas!$B$5/2 | W12: =E12*6+F12*4 | X12: =X11+I12-K12
A13: 11 | B13: =Agenda!C36 | C13: =IF(A13>Premissas!$B$11,INDEX(Agenda!$D$26:$D$49,A13-Premissas!$B$11),0) | D13: =Agenda!E36 | E13: =E12+C13-D13 | F13: =IF(A13>=Premissas!$B$16,ROUNDDOWN(E13*Premissas!$B$14,0),0) | G13: =B13+B12 | H13: =G13*Premissas!$B$2/2 | I13: =E13*Premissas!$B$3+F13*Premissas!$B$4 | J13: =H13+I13 | K13: =IF(A13>Premissas!$B$12,INDEX($I$3:$I$26,A13-Premissas!$B$12),0) | L13: =H13+K13 | M13: =IF(A13<=6,Premissas!$B$17,IF(A13<=12,Premissas!$B$18,Premissas!$B$19)) | N13: =G13*Premissas!$B$5/2*Premissas!$B$6 | O13: =E13*Premissas!$B$7+F13*Premissas!$B$8 | P13: =J13*Premissas!$B$9 | Q13: =L13*Premissas!$B$10 | R13: =SUM(M13:Q13) | S13: =L13-R13 | T13: =T12+S13 | U13: =I13*(1-Premissas!$B$9-Premissas!$B$10)-O13-M13 | V13: =G13*Premissas!$B$5/2 | W13: =E13*6+F13*4 | X13: =X12+I13-K13
A14: 12 | B14: =Agenda!C37 | C14: =IF(A14>Premissas!$B$11,INDEX(Agenda!$D$26:$D$49,A14-Premissas!$B$11),0) | D14: =Agenda!E37 | E14: =E13+C14-D14 | F14: =IF(A14>=Premissas!$B$16,ROUNDDOWN(E14*Premissas!$B$14,0),0) | G14: =B14+B13 | H14: =G14*Premissas!$B$2/2 | I14: =E14*Premissas!$B$3+F14*Premissas!$B$4 | J14: =H14+I14 | K14: =IF(A14>Premissas!$B$12,INDEX($I$3:$I$26,A14-Premissas!$B$12),0) | L14: =H14+K14 | M14: =IF(A14<=6,Premissas!$B$17,IF(A14<=12,Premissas!$B$18,Premissas!$B$19)) | N14: =G14*Premissas!$B$5/2*Premissas!$B$6 | O14: =E14*Premissas!$B$7+F14*Premissas!$B$8 | P14: =J14*Premissas!$B$9 | Q14: =L14*Premissas!$B$10 | R14: =SUM(M14:Q14) | S14: =L14-R14 | T14: =T13+S14 | U14: =I14*(1-Premissas!$B$9-Premissas!$B$10)-O14-M14 | V14: =G14*Premissas!$B$5/2 | W14: =E14*6+F14*4 | X14: =X13+I14-K14
... A26: 24 | B26: =Agenda!C49 | C26: =IF(A26>Premissas!$B$11,INDEX(Agenda!$D$26:$D$49,A26-Premissas!$B$11),0) | D26: =Agenda!E49 | E26: =E25+C26-D26 | F26: =IF(A26>=Premissas!$B$16,ROUNDDOWN(E26*Premissas!$B$14,0),0) | G26: =B26+B25 | H26: =G26*Premissas!$B$2/2 | I26: =E26*Premissas!$B$3+F26*Premissas!$B$4 | J26: =H26+I26 | K26: =IF(A26>Premissas!$B$12,INDEX($I$3:$I$26,A26-Premissas!$B$12),0) | L26: =H26+K26 | M26: =IF(A26<=6,Premissas!$B$17,IF(A26<=12,Premissas!$B$18,Premissas!$B$19)) | N26: =G26*Premissas!$B$5/2*Premissas!$B$6 | O26: =E26*Premissas!$B$7+F26*Premissas!$B$8 | P26: =J26*Premissas!$B$9 | Q26: =L26*Premissas!$B$10 | R26: =SUM(M26:Q26) | S26: =L26-R26 | T26: =T25+S26 | U26: =I26*(1-Premissas!$B$9-Premissas!$B$10)-O26-M26 | V26: =G26*Premissas!$B$5/2 | W26: =E26*6+F26*4 | X26: =X25+I26-K26

Sheet Expansao
A1: Mês | B1: Projetos novos | C1: Assinaturas novas | D1: Saídas | E1: Clientes ativos | F1: Clientes vivos | G1: Projetos em entrega | H1: Fat. implantação | I1: Fat. recorrente/MRR | J1: Faturamento total | K1: Receb. recorrente | L1: Recebimentos totais | M1: Fixo | N1: Custo implantação | O1: Custo recorrente | P1: Provisão tributos | Q1: Reserva comercial | R1: Saídas totais | S1: Caixa do mês | T1: Acumulado sem aporte | U1: Resultado recorrente | V1: Horas implantação | W1: Horas curadoria | X1: Contas a receber recorrente
A2: 0 | B2: 0 | C2: 0 | D2: 0 | E2: 0 | F2: 0 | G2: 0 | H2: 0 | I2: 0 | J2: 0 | K2: 0 | L2: 0 | M2: 0 | N2: 0 | O2: 0 | P2: 0 | Q2: 0 | R2: =Capex!D11 | S2: =-R2 | T2: =S2 | U2: 0 | V2: 0 | W2: 0 | X2: 0
A3: 1 | B3: =Agenda!C50 | C3: =IF(A3>Premissas!$B$11,INDEX(Agenda!$D$50:$D$73,A3-Premissas!$B$11),0) | D3: =Agenda!E50 | E3: =E2+C3-D3 | F3: =IF(A3>=Premissas!$B$16,ROUNDDOWN(E3*Premissas!$B$15,0),0) | G3: =B3+B2 | H3: =G3*Premissas!$B$2/2 | I3: =E3*Premissas!$B$3+F3*Premissas!$B$4 | J3: =H3+I3 | K3: =IF(A3>Premissas!$B$12,INDEX($I$3:$I$26,A3-Premissas!$B$12),0) | L3: =H3+K3 | M3: =IF(A3<=6,Premissas!$B$17,IF(A3<=12,Premissas!$B$18,Premissas!$B$19)) | N3: =G3*Premissas!$B$5/2*Premissas!$B$6 | O3: =E3*Premissas!$B$7+F3*Premissas!$B$8 | P3: =J3*Premissas!$B$9 | Q3: =L3*Premissas!$B$10 | R3: =SUM(M3:Q3) | S3: =L3-R3 | T3: =T2+S3 | U3: =I3*(1-Premissas!$B$9-Premissas!$B$10)-O3-M3 | V3: =G3*Premissas!$B$5/2 | W3: =E3*6+F3*4 | X3: =X2+I3-K3
A4: 2 | B4: =Agenda!C51 | C4: =IF(A4>Premissas!$B$11,INDEX(Agenda!$D$50:$D$73,A4-Premissas!$B$11),0) | D4: =Agenda!E51 | E4: =E3+C4-D4 | F4: =IF(A4>=Premissas!$B$16,ROUNDDOWN(E4*Premissas!$B$15,0),0) | G4: =B4+B3 | H4: =G4*Premissas!$B$2/2 | I4: =E4*Premissas!$B$3+F4*Premissas!$B$4 | J4: =H4+I4 | K4: =IF(A4>Premissas!$B$12,INDEX($I$3:$I$26,A4-Premissas!$B$12),0) | L4: =H4+K4 | M4: =IF(A4<=6,Premissas!$B$17,IF(A4<=12,Premissas!$B$18,Premissas!$B$19)) | N4: =G4*Premissas!$B$5/2*Premissas!$B$6 | O4: =E4*Premissas!$B$7+F4*Premissas!$B$8 | P4: =J4*Premissas!$B$9 | Q4: =L4*Premissas!$B$10 | R4: =SUM(M4:Q4) | S4: =L4-R4 | T4: =T3+S4 | U4: =I4*(1-Premissas!$B$9-Premissas!$B$10)-O4-M4 | V4: =G4*Premissas!$B$5/2 | W4: =E4*6+F4*4 | X4: =X3+I4-K4
A5: 3 | B5: =Agenda!C52 | C5: =IF(A5>Premissas!$B$11,INDEX(Agenda!$D$50:$D$73,A5-Premissas!$B$11),0) | D5: =Agenda!E52 | E5: =E4+C5-D5 | F5: =IF(A5>=Premissas!$B$16,ROUNDDOWN(E5*Premissas!$B$15,0),0) | G5: =B5+B4 | H5: =G5*Premissas!$B$2/2 | I5: =E5*Premissas!$B$3+F5*Premissas!$B$4 | J5: =H5+I5 | K5: =IF(A5>Premissas!$B$12,INDEX($I$3:$I$26,A5-Premissas!$B$12),0) | L5: =H5+K5 | M5: =IF(A5<=6,Premissas!$B$17,IF(A5<=12,Premissas!$B$18,Premissas!$B$19)) | N5: =G5*Premissas!$B$5/2*Premissas!$B$6 | O5: =E5*Premissas!$B$7+F5*Premissas!$B$8 | P5: =J5*Premissas!$B$9 | Q5: =L5*Premissas!$B$10 | R5: =SUM(M5:Q5) | S5: =L5-R5 | T5: =T4+S5 | U5: =I5*(1-Premissas!$B$9-Premissas!$B$10)-O5-M5 | V5: =G5*Premissas!$B$5/2 | W5: =E5*6+F5*4 | X5: =X4+I5-K5
A6: 4 | B6: =Agenda!C53 | C6: =IF(A6>Premissas!$B$11,INDEX(Agenda!$D$50:$D$73,A6-Premissas!$B$11),0) | D6: =Agenda!E53 | E6: =E5+C6-D6 | F6: =IF(A6>=Premissas!$B$16,ROUNDDOWN(E6*Premissas!$B$15,0),0) | G6: =B6+B5 | H6: =G6*Premissas!$B$2/2 | I6: =E6*Premissas!$B$3+F6*Premissas!$B$4 | J6: =H6+I6 | K6: =IF(A6>Premissas!$B$12,INDEX($I$3:$I$26,A6-Premissas!$B$12),0) | L6: =H6+K6 | M6: =IF(A6<=6,Premissas!$B$17,IF(A6<=12,Premissas!$B$18,Premissas!$B$19)) | N6: =G6*Premissas!$B$5/2*Premissas!$B$6 | O6: =E6*Premissas!$B$7+F6*Premissas!$B$8 | P6: =J6*Premissas!$B$9 | Q6: =L6*Premissas!$B$10 | R6: =SUM(M6:Q6) | S6: =L6-R6 | T6: =T5+S6 | U6: =I6*(1-Premissas!$B$9-Premissas!$B$10)-O6-M6 | V6: =G6*Premissas!$B$5/2 | W6: =E6*6+F6*4 | X6: =X5+I6-K6
A7: 5 | B7: =Agenda!C54 | C7: =IF(A7>Premissas!$B$11,INDEX(Agenda!$D$50:$D$73,A7-Premissas!$B$11),0) | D7: =Agenda!E54 | E7: =E6+C7-D7 | F7: =IF(A7>=Premissas!$B$16,ROUNDDOWN(E7*Premissas!$B$15,0),0) | G7: =B7+B6 | H7: =G7*Premissas!$B$2/2 | I7: =E7*Premissas!$B$3+F7*Premissas!$B$4 | J7: =H7+I7 | K7: =IF(A7>Premissas!$B$12,INDEX($I$3:$I$26,A7-Premissas!$B$12),0) | L7: =H7+K7 | M7: =IF(A7<=6,Premissas!$B$17,IF(A7<=12,Premissas!$B$18,Premissas!$B$19)) | N7: =G7*Premissas!$B$5/2*Premissas!$B$6 | O7: =E7*Premissas!$B$7+F7*Premissas!$B$8 | P7: =J7*Premissas!$B$9 | Q7: =L7*Premissas!$B$10 | R7: =SUM(M7:Q7) | S7: =L7-R7 | T7: =T6+S7 | U7: =I7*(1-Premissas!$B$9-Premissas!$B$10)-O7-M7 | V7: =G7*Premissas!$B$5/2 | W7: =E7*6+F7*4 | X7: =X6+I7-K7
A8: 6 | B8: =Agenda!C55 | C8: =IF(A8>Premissas!$B$11,INDEX(Agenda!$D$50:$D$73,A8-Premissas!$B$11),0) | D8: =Agenda!E55 | E8: =E7+C8-D8 | F8: =IF(A8>=Premissas!$B$16,ROUNDDOWN(E8*Premissas!$B$15,0),0) | G8: =B8+B7 | H8: =G8*Premissas!$B$2/2 | I8: =E8*Premissas!$B$3+F8*Premissas!$B$4 | J8: =H8+I8 | K8: =IF(A8>Premissas!$B$12,INDEX($I$3:$I$26,A8-Premissas!$B$12),0) | L8: =H8+K8 | M8: =IF(A8<=6,Premissas!$B$17,IF(A8<=12,Premissas!$B$18,Premissas!$B$19)) | N8: =G8*Premissas!$B$5/2*Premissas!$B$6 | O8: =E8*Premissas!$B$7+F8*Premissas!$B$8 | P8: =J8*Premissas!$B$9 | Q8: =L8*Premissas!$B$10 | R8: =SUM(M8:Q8) | S8: =L8-R8 | T8: =T7+S8 | U8: =I8*(1-Premissas!$B$9-Premissas!$B$10)-O8-M8 | V8: =G8*Premissas!$B$5/2 | W8: =E8*6+F8*4 | X8: =X7+I8-K8
A9: 7 | B9: =Agenda!C56 | C9: =IF(A9>Premissas!$B$11,INDEX(Agenda!$D$50:$D$73,A9-Premissas!$B$11),0) | D9: =Agenda!E56 | E9: =E8+C9-D9 | F9: =IF(A9>=Premissas!$B$16,ROUNDDOWN(E9*Premissas!$B$15,0),0) | G9: =B9+B8 | H9: =G9*Premissas!$B$2/2 | I9: =E9*Premissas!$B$3+F9*Premissas!$B$4 | J9: =H9+I9 | K9: =IF(A9>Premissas!$B$12,INDEX($I$3:$I$26,A9-Premissas!$B$12),0) | L9: =H9+K9 | M9: =IF(A9<=6,Premissas!$B$17,IF(A9<=12,Premissas!$B$18,Premissas!$B$19)) | N9: =G9*Premissas!$B$5/2*Premissas!$B$6 | O9: =E9*Premissas!$B$7+F9*Premissas!$B$8 | P9: =J9*Premissas!$B$9 | Q9: =L9*Premissas!$B$10 | R9: =SUM(M9:Q9) | S9: =L9-R9 | T9: =T8+S9 | U9: =I9*(1-Premissas!$B$9-Premissas!$B$10)-O9-M9 | V9: =G9*Premissas!$B$5/2 | W9: =E9*6+F9*4 | X9: =X8+I9-K9
A10: 8 | B10: =Agenda!C57 | C10: =IF(A10>Premissas!$B$11,INDEX(Agenda!$D$50:$D$73,A10-Premissas!$B$11),0) | D10: =Agenda!E57 | E10: =E9+C10-D10 | F10: =IF(A10>=Premissas!$B$16,ROUNDDOWN(E10*Premissas!$B$15,0),0) | G10: =B10+B9 | H10: =G10*Premissas!$B$2/2 | I10: =E10*Premissas!$B$3+F10*Premissas!$B$4 | J10: =H10+I10 | K10: =IF(A10>Premissas!$B$12,INDEX($I$3:$I$26,A10-Premissas!$B$12),0) | L10: =H10+K10 | M10: =IF(A10<=6,Premissas!$B$17,IF(A10<=12,Premissas!$B$18,Premissas!$B$19)) | N10: =G10*Premissas!$B$5/2*Premissas!$B$6 | O10: =E10*Premissas!$B$7+F10*Premissas!$B$8 | P10: =J10*Premissas!$B$9 | Q10: =L10*Premissas!$B$10 | R10: =SUM(M10:Q10) | S10: =L10-R10 | T10: =T9+S10 | U10: =I10*(1-Premissas!$B$9-Premissas!$B$10)-O10-M10 | V10: =G10*Premissas!$B$5/2 | W10: =E10*6+F10*4 | X10: =X9+I10-K10
A11: 9 | B11: =Agenda!C58 | C11: =IF(A11>Premissas!$B$11,INDEX(Agenda!$D$50:$D$73,A11-Premissas!$B$11),0) | D11: =Agenda!E58 | E11: =E10+C11-D11 | F11: =IF(A11>=Premissas!$B$16,ROUNDDOWN(E11*Premissas!$B$15,0),0) | G11: =B11+B10 | H11: =G11*Premissas!$B$2/2 | I11: =E11*Premissas!$B$3+F11*Premissas!$B$4 | J11: =H11+I11 | K11: =IF(A11>Premissas!$B$12,INDEX($I$3:$I$26,A11-Premissas!$B$12),0) | L11: =H11+K11 | M11: =IF(A11<=6,Premissas!$B$17,IF(A11<=12,Premissas!$B$18,Premissas!$B$19)) | N11: =G11*Premissas!$B$5/2*Premissas!$B$6 | O11: =E11*Premissas!$B$7+F11*Premissas!$B$8 | P11: =J11*Premissas!$B$9 | Q11: =L11*Premissas!$B$10 | R11: =SUM(M11:Q11) | S11: =L11-R11 | T11: =T10+S11 | U11: =I11*(1-Premissas!$B$9-Premissas!$B$10)-O11-M11 | V11: =G11*Premissas!$B$5/2 | W11: =E11*6+F11*4 | X11: =X10+I11-K11
A12: 10 | B12: =Agenda!C59 | C12: =IF(A12>Premissas!$B$11,INDEX(Agenda!$D$50:$D$73,A12-Premissas!$B$11),0) | D12: =Agenda!E59 | E12: =E11+C12-D12 | F12: =IF(A12>=Premissas!$B$16,ROUNDDOWN(E12*Premissas!$B$15,0),0) | G12: =B12+B11 | H12: =G12*Premissas!$B$2/2 | I12: =E12*Premissas!$B$3+F12*Premissas!$B$4 | J12: =H12+I12 | K12: =IF(A12>Premissas!$B$12,INDEX($I$3:$I$26,A12-Premissas!$B$12),0) | L12: =H12+K12 | M12: =IF(A12<=6,Premissas!$B$17,IF(A12<=12,Premissas!$B$18,Premissas!$B$19)) | N12: =G12*Premissas!$B$5/2*Premissas!$B$6 | O12: =E12*Premissas!$B$7+F12*Premissas!$B$8 | P12: =J12*Premissas!$B$9 | Q12: =L12*Premissas!$B$10 | R12: =SUM(M12:Q12) | S12: =L12-R12 | T12: =T11+S12 | U12: =I12*(1-Premissas!$B$9-Premissas!$B$10)-O12-M12 | V12: =G12*Premissas!$B$5/2 | W12: =E12*6+F12*4 | X12: =X11+I12-K12
A13: 11 | B13: =Agenda!C60 | C13: =IF(A13>Premissas!$B$11,INDEX(Agenda!$D$50:$D$73,A13-Premissas!$B$11),0) | D13: =Agenda!E60 | E13: =E12+C13-D13 | F13: =IF(A13>=Premissas!$B$16,ROUNDDOWN(E13*Premissas!$B$15,0),0) | G13: =B13+B12 | H13: =G13*Premissas!$B$2/2 | I13: =E13*Premissas!$B$3+F13*Premissas!$B$4 | J13: =H13+I13 | K13: =IF(A13>Premissas!$B$12,INDEX($I$3:$I$26,A13-Premissas!$B$12),0) | L13: =H13+K13 | M13: =IF(A13<=6,Premissas!$B$17,IF(A13<=12,Premissas!$B$18,Premissas!$B$19)) | N13: =G13*Premissas!$B$5/2*Premissas!$B$6 | O13: =E13*Premissas!$B$7+F13*Premissas!$B$8 | P13: =J13*Premissas!$B$9 | Q13: =L13*Premissas!$B$10 | R13: =SUM(M13:Q13) | S13: =L13-R13 | T13: =T12+S13 | U13: =I13*(1-Premissas!$B$9-Premissas!$B$10)-O13-M13 | V13: =G13*Premissas!$B$5/2 | W13: =E13*6+F13*4 | X13: =X12+I13-K13
A14: 12 | B14: =Agenda!C61 | C14: =IF(A14>Premissas!$B$11,INDEX(Agenda!$D$50:$D$73,A14-Premissas!$B$11),0) | D14: =Agenda!E61 | E14: =E13+C14-D14 | F14: =IF(A14>=Premissas!$B$16,ROUNDDOWN(E14*Premissas!$B$15,0),0) | G14: =B14+B13 | H14: =G14*Premissas!$B$2/2 | I14: =E14*Premissas!$B$3+F14*Premissas!$B$4 | J14: =H14+I14 | K14: =IF(A14>Premissas!$B$12,INDEX($I$3:$I$26,A14-Premissas!$B$12),0) | L14: =H14+K14 | M14: =IF(A14<=6,Premissas!$B$17,IF(A14<=12,Premissas!$B$18,Premissas!$B$19)) | N14: =G14*Premissas!$B$5/2*Premissas!$B$6 | O14: =E14*Premissas!$B$7+F14*Premissas!$B$8 | P14: =J14*Premissas!$B$9 | Q14: =L14*Premissas!$B$10 | R14: =SUM(M14:Q14) | S14: =L14-R14 | T14: =T13+S14 | U14: =I14*(1-Premissas!$B$9-Premissas!$B$10)-O14-M14 | V14: =G14*Premissas!$B$5/2 | W14: =E14*6+F14*4 | X14: =X13+I14-K14
... A26: 24 | B26: =Agenda!C73 | C26: =IF(A26>Premissas!$B$11,INDEX(Agenda!$D$50:$D$73,A26-Premissas!$B$11),0) | D26: =Agenda!E73 | E26: =E25+C26-D26 | F26: =IF(A26>=Premissas!$B$16,ROUNDDOWN(E26*Premissas!$B$15,0),0) | G26: =B26+B25 | H26: =G26*Premissas!$B$2/2 | I26: =E26*Premissas!$B$3+F26*Premissas!$B$4 | J26: =H26+I26 | K26: =IF(A26>Premissas!$B$12,INDEX($I$3:$I$26,A26-Premissas!$B$12),0) | L26: =H26+K26 | M26: =IF(A26<=6,Premissas!$B$17,IF(A26<=12,Premissas!$B$18,Premissas!$B$19)) | N26: =G26*Premissas!$B$5/2*Premissas!$B$6 | O26: =E26*Premissas!$B$7+F26*Premissas!$B$8 | P26: =J26*Premissas!$B$9 | Q26: =L26*Premissas!$B$10 | R26: =SUM(M26:Q26) | S26: =L26-R26 | T26: =T25+S26 | U26: =I26*(1-Premissas!$B$9-Premissas!$B$10)-O26-M26 | V26: =G26*Premissas!$B$5/2 | W26: =E26*6+F26*4 | X26: =X25+I26-K26

Sheet Resumo
A1: Cenário | B1: Projetos iniciados | C1: Clientes M12 | D1: Clientes M24 | E1: MRR M12 | F1: MRR M24 | G1: Faturamento ano 1 | H1: Faturamento ano 2 | I1: Pico déficit | J1: Reserva | K1: Capital arredondado | L1: Caixa acumulado M24 | M1: Resultado recorrente M24 | N1: ARR saída M24
A2: Conservador | B2: =SUM('Conservador'!B3:B26) | C2: ='Conservador'!E14 | D2: ='Conservador'!E26 | E2: ='Conservador'!I14 | F2: ='Conservador'!I26 | G2: =SUM('Conservador'!J3:J14) | H2: =SUM('Conservador'!J15:J26) | I2: =MAX(0,-MIN('Conservador'!T2:T26)) | J2: =MAX(I2*Premissas!$B$20,MAX(Premissas!$B$17,Premissas!$B$18,Premissas!$B$19)*Premissas!$B$21) | K2: =ROUNDUP((I2+J2)/10000,0)*10000 | L2: ='Conservador'!T26 | M2: ='Conservador'!U26 | N2: =F2*12
A3: Base | B3: =SUM('Base'!B3:B26) | C3: ='Base'!E14 | D3: ='Base'!E26 | E3: ='Base'!I14 | F3: ='Base'!I26 | G3: =SUM('Base'!J3:J14) | H3: =SUM('Base'!J15:J26) | I3: =MAX(0,-MIN('Base'!T2:T26)) | J3: =MAX(I3*Premissas!$B$20,MAX(Premissas!$B$17,Premissas!$B$18,Premissas!$B$19)*Premissas!$B$21) | K3: =ROUNDUP((I3+J3)/10000,0)*10000 | L3: ='Base'!T26 | M3: ='Base'!U26 | N3: =F3*12
A4: Expansao | B4: =SUM('Expansao'!B3:B26) | C4: ='Expansao'!E14 | D4: ='Expansao'!E26 | E4: ='Expansao'!I14 | F4: ='Expansao'!I26 | G4: =SUM('Expansao'!J3:J14) | H4: =SUM('Expansao'!J15:J26) | I4: =MAX(0,-MIN('Expansao'!T2:T26)) | J4: =MAX(I4*Premissas!$B$20,MAX(Premissas!$B$17,Premissas!$B$18,Premissas!$B$19)*Premissas!$B$21) | K4: =ROUNDUP((I4+J4)/10000,0)*10000 | L4: ='Expansao'!T26 | M4: ='Expansao'!U26 | N4: =F4*12

Sheet Verificado
A1: Snapshot Python; estático; premissas originais de 01/10/2026
A2: Cenário | B2: peak_deficit | C2: buffer | D2: recommended_capital | E2: cumulative_end | F2: active_m12 | G2: active_m24 | H2: mrr12 | I2: mrr24 | J2: revenue_year1 | K2: revenue_year2 | L2: receipts_year1 | M2: receipts_year2 | N2: first_positive_cash | O2: first_recurring_breakeven | P2: max_delivery_hours | Q2: operating_cash24
A3: Conservador | B3: 1365150 | C3: 204772.5 | D3: 1570000 | E3: -1365150 | F3: 1 | G3: 2 | H3: 7500 | I3: 15000 | J3: 109500 | K3: 220500 | L3: 102000 | M3: 213000 | P3: 66 | Q3: -1191150
A4: Base | B4: 764720 | C4: 198000 | D4: 970000 | E4: -764720 | F4: 4 | G4: 12 | H4: 30000 | I4: 99000 | J4: 343500 | K4: 1165500 | L4: 313500 | M4: 1096500 | N4: 21 | O4: 24 | P4: 194 | Q4: -590720
A5: Expansao | B5: 571665 | C5: 198000 | D5: 770000 | E5: -425290 | F5: 6 | G5: 16 | H5: 54000 | I5: 147000 | J5: 505500 | K5: 1672500 | L5: 451500 | M5: 1579500 | N5: 16 | O5: 18 | P5: 240 | Q5: -251290
A7: Cenário | B7: month | C7: new | D7: adds | E7: churn | F7: active | G7: live | H7: setup_bill | I7: sub_bill | J7: billed | K7: receipts | L7: fixed | M7: impl_cost | N7: service_cost | O7: tax | P7: commission | Q7: outflow | R7: net | S7: cumulative | T7: recurring_result | U7: impl_hours | V7: care_hours
A8: Conservador | B8: 1 | C8: 0 | D8: 0 | E8: 0 | F8: 0 | G8: 0 | H8: 0 | I8: 0 | J8: 0 | K8: 0 | L8: 38000 | M8: 0 | N8: 0 | O8: 0 | P8: 0 | Q8: 38000 | R8: -38000 | S8: -212000 | T8: -38000 | U8: 0 | V8: 0
A9: Conservador | B9: 2 | C9: 0 | D9: 0 | E9: 0 | F9: 0 | G9: 0 | H9: 0 | I9: 0 | J9: 0 | K9: 0 | L9: 38000 | M9: 0 | N9: 0 | O9: 0 | P9: 0 | Q9: 38000 | R9: -38000 | S9: -250000 | T9: -38000 | U9: 0 | V9: 0
A10: Conservador | B10: 3 | C10: 0 | D10: 0 | E10: 0 | F10: 0 | G10: 0 | H10: 0 | I10: 0 | J10: 0 | K10: 0 | L10: 38000 | M10: 0 | N10: 0 | O10: 0 | P10: 0 | Q10: 38000 | R10: -38000 | S10: -288000 | T10: -38000 | U10: 0 | V10: 0
A11: Conservador | B11: 4 | C11: 0 | D11: 0 | E11: 0 | F11: 0 | G11: 0 | H11: 0 | I11: 0 | J11: 0 | K11: 0 | L11: 38000 | M11: 0 | N11: 0 | O11: 0 | P11: 0 | Q11: 38000 | R11: -38000 | S11: -326000 | T11: -38000 | U11: 0 | V11: 0
A12: Conservador | B12: 5 | C12: 0 | D12: 0 | E12: 0 | F12: 0 | G12: 0 | H12: 0 | I12: 0 | J12: 0 | K12: 0 | L12: 38000 | M12: 0 | N12: 0 | O12: 0 | P12: 0 | Q12: 38000 | R12: -38000 | S12: -364000 | T12: -38000 | U12: 0 | V12: 0
A13: Conservador | B13: 6 | C13: 1 | D13: 0 | E13: 0 | F13: 0 | G13: 0 | H13: 18000 | I13: 0 | J13: 18000 | K13: 18000 | L13: 38000 | M13: 9000 | N13: 0 | O13: 1440 | P13: 900 | Q13: 49340 | R13: -31340 | S13: -395340 | T13: -38000 | U13: 60 | V13: 0
A14: Conservador | B14: 7 | C14: 0 | D14: 0 | E14: 0 | F14: 0 | G14: 0 | H14: 18000 | I14: 0 | J14: 18000 | K14: 18000 | L14: 54000 | M14: 9000 | N14: 0 | O14: 1440 | P14: 900 | Q14: 65340 | R14: -47340 | S14: -442680 | T14: -54000 | U14: 60 | V14: 0
A15: Conservador | B15: 8 | C15: 0 | D15: 1 | E15: 0 | F15: 1 | G15: 0 | H15: 0 | I15: 7500 | J15: 7500 | K15: 0 | L15: 54000 | M15: 0 | N15: 1500 | O15: 600 | P15: 0 | Q15: 56100 | R15: -56100 | S15: -498780 | T15: -48975 | U15: 0 | V15: 6
A16: Conservador | B16: 9 | C16: 0 | D16: 0 | E16: 0 | F16: 1 | G16: 0 | H16: 0 | I16: 7500 | J16: 7500 | K16: 7500 | L16: 54000 | M16: 0 | N16: 1500 | O16: 600 | P16: 375 | Q16: 56475 | R16: -48975 | S16: -547755 | T16: -48975 | U16: 0 | V16: 6
A17: Conservador | B17: 10 | C17: 1 | D17: 0 | E17: 0 | F17: 1 | G17: 0 | H17: 18000 | I17: 7500 | J17: 25500 | K17: 25500 | L17: 54000 | M17: 9000 | N17: 1500 | O17: 2040 | P17: 1275 | Q17: 67815 | R17: -42315 | S17: -590070 | T17: -48975 | U17: 60 | V17: 6
A18: Conservador | B18: 11 | C18: 0 | D18: 0 | E18: 0 | F18: 1 | G18: 0 | H18: 18000 | I18: 7500 | J18: 25500 | K18: 25500 | L18: 54000 | M18: 9000 | N18: 1500 | O18: 2040 | P18: 1275 | Q18: 67815 | R18: -42315 | S18: -632385 | T18: -48975 | U18: 60 | V18: 6
A19: Conservador | B19: 12 | C19: 0 | D19: 0 | E19: 0 | F19: 1 | G19: 0 | H19: 0 | I19: 7500 | J19: 7500 | K19: 7500 | L19: 54000 | M19: 0 | N19: 1500 | O19: 600 | P19: 375 | Q19: 56475 | R19: -48975 | S19: -681360 | T19: -48975 | U19: 0 | V19: 6
... A79: Expansao | B79: 24 | C79: 1 | D79: 1 | E79: 0 | F79: 16 | G79: 6 | H79: 36000 | I79: 147000 | J79: 183000 | K79: 175500 | L79: 66000 | M79: 18000 | N79: 30000 | O79: 14640 | P79: 8775 | Q79: 137415 | R79: 38085 | S79: -425290 | T79: 31890 | U79: 120 | V79: 120

Sheet Fontes
A1: Fonte | B1: URL | C1: Status/data
A2: NVIDIA hardware | B2: https://docs.nvidia.com/dgx/dgx-spark/hardware.html | C2: Documentação 10/09/2026; consultada 01/10/2026
A3: NVIDIA Brasil | B3: https://www.nvidia.com/pt-br/products/workstations/dgx-spark/ | C3: Consulta 01/10/2026; preço BR não confirmado
A4: MCP OpenAI | B4: https://developers.openai.com/plugins/concepts/mcp-server | C4: Consulta nesta pesquisa; compatibilidade por cliente/plano
A5: Pesquisa anterior | B5: Pesquisa documental de apoio; fontes primárias listadas em plano-completo.html. | C5: Base documental; este BP atualiza o foco comercial para uso estratégico
A6: Preço DGX no orçamento | B6: Sem cotação válida de fornecedor | C6: R$65.000/unidade é premissa, NÃO preço verificado

Sheet Publicacao
A1: Topologic — publicação pública | B1: Base financeira preservada
A2: AUMI | B2: 50% — Marcos, Luciana e João conjuntamente; divisão interna não informada.
A3: Dani | B3: 50% — investidora; aporte e condições não definidos.
A4: Oferta-alvo | B4: R$200 mil por contrato, hipótese não incorporada aos cenários.
A5: Capital-base | B5: R$970 mil de planejamento, não obrigação da Dani nem valuation.
A6: Leitura | B6: Verificado e CSV são snapshots estáticos; fórmulas exigem recálculo no Excel/LibreOffice.
