Workbook

Sheet Leia primeiro
A1: AUMI | Portfólio: loja LATAM + mapa de TI
A4: PROPOSTA EM 02/10/2026 — Nichos ainda serão escolhidos por validação. Não há catálogo ou pipeline comprovado. Esta planilha não inclui a oferta Topologic empresarial de R$200 mil + R$12 mil/mês.
A6: Como usar: leia Resumo e Capital; examine Economia e Escala; edite células azuis em Premissas e agendas de pedidos/mapas nas três abas mensais. Fórmulas têm resultados em cache para leitura sem Excel; após editar, abra em aplicativo com recálculo de fórmulas.
A8: Unidade: BRL salvo indicação USD, pedidos, visitas, horas ou mês. Receita após estornos não é caixa. Loja recebe líquido da plataforma em M+1. Mapa recebe 50% no mês e 50% no seguinte. Tributos provisionados no mês da venda/fatura; comercial TI sobre caixa recebido.
A10: Capital exigido = pico do déficit acumulado incluindo M0 + três meses de fixo do ano 2, arredondado para cima em R$10 mil. Caixa acumulado exclui aportes, juros e dividendos. Os cenários pressupõem financiamento completo, sem interrupção por insolvência.
A12: Sociedade confirmada: Dani 50%; AUMI 50% conjunto (Marcos, Luciana e João; divisão interna indefinida). Aporte, cargos, remunerações, política de distribuição e instrumento societário não acordados.
A14: Dani: exemplo exclusivamente hipotético de financiadora única de todo capital requerido; 50% do excedente acumulado positivo do projeto. Não é dividendo automaticamente disponível, nem payout acordado. Sem tributos pessoais e sem reinvestimento. Não somar excedentes acumulados de meses diferentes.
A16: Sensibilidades CAC15 e FX4,5 usam exatamente as agendas do cenário Base. Custos, tributos, câmbio, preços, conversão e prazos são hipóteses. Taxa Hotmart: tabela/FAQ USD >15, 9,9% + USD1, efetiva em 21/09/2026; confirmar condições da conta.
A18: Volume operacional importa: todas as vendas suportam CAC, inclusive as que seriam orgânicas. Visitas usam conversão hipotética de 2%. Horas TI são horas diretas de entrega, além da equipe fixa. Escala é estado estacionário, não fluxo de lançamento.
A20: Navegação: Premissas → Economia → Conservador/Base/Escala24 → Resumo → Capital → Escala → CAC15/FX4,5 → Gates → Fontes. Dados e séries: pitch-data.json, revisão 2026-10-02.

Sheet Premissas
A1: Premissas editáveis | azul = entrada
A4: Premissa | B4: Valor | C4: Unidade / status | D4: Significado e limites
A5: Ticket loja | B5: 29 | C5: USD/pedido | D5: Preço hipotético antes dos tributos do comprador
A6: Câmbio | B6: 5 | C6: BRL/USD | D6: Hipótese; não é cotação
A7: Estornos | B7: 0.08 | C7: % bruto | D7: Estornos sobre pedidos aprovados
A8: Plataforma variável | B8: 0.099 | C8: % após estorno | D8: Hotmart tabela/FAQ; não sobre pedidos reembolsados
A9: Plataforma fixa | B9: 1 | C9: USD não reembolsado | D9: USD1 efetivo 21/09/2026; confirmar condições da conta
A10: Provisão tributária | B10: 0.15 | C10: % após estorno / fatura TI | D10: 15% novo portfólio; não 12% do modelo antigo. Confirmar regime.
A11: Meios / câmbio | B11: 0.03 | C11: % após estorno | D11: Reserva adicional hipotética; não tarifa citada
A12: Aquisição / CAC | B12: 10 | C12: USD/pedido aprovado | D12: Inclui todos os pedidos, inclusive reembolsados
A13: Suporte loja | B13: 1 | C13: USD/pedido aprovado | D13: Custo variável, sem duplicar equipe fixa
A14: Conversão em pedidos | B14: 0.02 | C14: % visitas qualificadas | D14: Hipótese, não medição
A15: Preço mapa TI | B15: 30000 | C15: BRL/projeto | D15: Oferta proposta; escopo limitado, validar com comprador
A16: Horas diretas mapa | B16: 80 | C16: horas/projeto | D16: 80h diretas, além de P&D fixo
... A22: Pré-operação M0 | B22: 24000 | C22: BRL | D22: Jurídico12k + segurança12k; provisões
A23: Investimento M0 | B23: ='Premissas'!$B$21+'Premissas'!$B$22 -> 100000 | C23: BRL calculado | D23: Infraestrutura + pré-operação; sem autorização de compra
A24: Fixo mensal ano 1 | B24: 37000 | C24: BRL/mês | D24: Envelopes operacionais, não salários pesquisados
A25: Fixo mensal ano 2 | B25: 42000 | C25: BRL/mês | D25: Hipótese de ampliação da equipe/custos
A26: Reserva de segurança | B26: 3 | C26: meses de fixo ano 2 | D26: Além do pico de déficit
A27: Arredondamento capital | B27: 10000 | C27: BRL | D27: Arredondar para cima em múltiplos deste valor
A28: Participação Dani | B28: 0.5 | C28: % | D28: 50% confirmado; payout não acordado
A29: CAC sensibilizado | B29: 15 | C29: USD/pedido | D29: Apenas sensibilidade, mesma agenda Base
A30: Câmbio sensibilizado | B30: 4.5 | C30: BRL/USD | D30: Apenas sensibilidade, mesma agenda Base

Sheet Economia
A1: Economia unitária | contribuição não é lucro
A4: Loja por pedido aprovado | B4: USD | C4: BRL | D4: Base de incidência | E4: Status
A5: Venda bruta | B5: ='Premissas'!$B$5 -> 29 | C5: =B5*'Premissas'!$B$6 -> 145 | D5: Pedido aprovado | E5: Hipótese / fonte em Fontes
A6: Estornos | B6: =B5*'Premissas'!$B$7 -> 2.32 | C6: =B6*'Premissas'!$B$6 -> 11.6 | D6: 8% bruto | E6: Hipótese / fonte em Fontes
A7: Receita após estorno | B7: =B5-B6 -> 26.68 | C7: =B7*'Premissas'!$B$6 -> 133.4 | D7: Receita reconhecida | E7: Hipótese / fonte em Fontes
A8: Plataforma | B8: =B7*'Premissas'!$B$8+(1-'Premissas'!$B$7)*'Premissas'!$B$9 -> 3.56132 | C8: =B8*'Premissas'!$B$6 -> 17.8066 | D8: Somente concluídos sem estorno | E8: Hipótese / fonte em Fontes
A9: Tributos provisionados | B9: =B7*'Premissas'!$B$10 -> 4.002 | C9: =B9*'Premissas'!$B$6 -> 20.01 | D9: Após estorno | E9: Hipótese / fonte em Fontes
A10: Reserva meios/câmbio | B10: =B7*'Premissas'!$B$11 -> 0.8004 | C10: =B10*'Premissas'!$B$6 -> 4.002 | D10: Após estorno | E10: Hipótese / fonte em Fontes
A11: CAC | B11: ='Premissas'!$B$12 -> 10 | C11: =B11*'Premissas'!$B$6 -> 50 | D11: Todos os pedidos aprovados | E11: Hipótese / fonte em Fontes
A12: Suporte | B12: ='Premissas'!$B$13 -> 1 | C12: =B12*'Premissas'!$B$6 -> 5 | D12: Todos os pedidos aprovados | E12: Hipótese / fonte em Fontes
A13: Contribuição loja | B13: =B7-SUM(B8:B12) -> 7.31628 | C13: =B13*'Premissas'!$B$6 -> 36.5814 | D13: Antes de fixo / M0 | E13: Hipótese / fonte em Fontes
A16: Mapa de TI por projeto | B16: BRL | C16: Cálculo | D16: Escopo | E16: Status
A17: Preço | B17: ='Premissas'!$B$15 -> 30000
A18: Entrega direta | B18: ='Premissas'!$B$16*'Premissas'!$B$17 -> 14400
A19: Tributos | B19: =B17*'Premissas'!$B$10 -> 4500
A20: Comercial | B20: =B17*'Premissas'!$B$18 -> 1500
A21: Contribuição mapa | B21: =B17-SUM(B18:B20) -> 9600
A24: Pedidos/mês para cobrir fixo ano 2, sem mapas | B24: =ROUNDUP('Premissas'!$B$25/C13,0) -> 1149
A25: CAC que zera contribuição unitária (USD) | B25: =B13+'Premissas'!$B$12 -> 17.31628
A28: Unitário preserva 6 casas; nos fluxos mensais cada componente monetário é arredondado a 2 casas. Contribuição não inclui fixo, M0 ou capital de giro.

Sheet Conservador
A1: Conservador | fluxo mensal em BRL, salvo indicação
A2: Agenda editável em azul. Cenário hipotético; não previsão. | M0 separado: -R$100 mil nas premissas. Acumulado exclui aportes/distribuição.
A4: Mês | B4: Pedidos aprovados | C4: Visitas qualificadas | D4: Mapas faturados | E4: Horas diretas TI | F4: Loja bruta USD | G4: Loja bruta BRL | H4: Estornos BRL | I4: Loja após estornos BRL | J4: Taxa plataforma BRL | K4: Liquidação gerada BRL | L4: Loja recebida BRL | M4: Tributos loja BRL | N4: Reserva meios/FX BRL | O4: Aquisição / mídia BRL | P4: Suporte loja BRL | Q4: Fatura TI BRL | R4: Recebimentos TI BRL | S4: Entrega TI BRL | T4: Tributos TI BRL | U4: Comercial TI caixa BRL | V4: Fixo BRL | W4: Vendas brutas BRL | X4: Receita após estornos BRL | Y4: Recebimentos BRL | Z4: Saídas caixa BRL | AA4: Fluxo líquido BRL | AB4: Acumulado sem aporte BRL | AC4: Resultado competência BRL | AD4: A receber BRL | AE4: 50% excedente positivo BRL | AF4: Mês elegível payback projeto | AG4: Mês elegível Dani hipotético | AH4: Saldo com 100k | AI4: Saldo com 150k | AJ4: Saldo com 200k
A5: 1 | B5: 0 | C5: =ROUNDUP(B5/'Premissas'!$B$14,0) -> 0 | D5: 0 | E5: =D5*'Premissas'!$B$16 -> 0 | F5: =ROUND(B5*'Premissas'!$B$5,2) -> 0 | G5: =ROUND(F5*'Premissas'!$B$6,2) -> 0 | H5: =ROUND(G5*'Premissas'!$B$7,2) -> 0 | I5: =ROUND(G5-H5,2) -> 0 | J5: =ROUND(I5*'Premissas'!$B$8+B5*(1-'Premissas'!$B$7)*'Premissas'!$B$9*'Premissas'!$B$6,2) -> 0 | K5: =ROUND(I5-J5,2) -> 0 | L5: =IF(A5>'Premissas'!$B$20,INDEX($K$5:$K$28,MAX(1,A5-'Premissas'!$B$20)),0) -> 0 | M5: =ROUND(I5*'Premissas'!$B$10,2) -> 0 | N5: =ROUND(I5*'Premissas'!$B$11,2) -> 0 | O5: =ROUND(B5*'Premissas'!$B$12*'Premissas'!$B$6,2) -> 0 | P5: =ROUND(B5*'Premissas'!$B$13*'Premissas'!$B$6,2) -> 0 | Q5: =ROUND(D5*'Premissas'!$B$15,2) -> 0 | R5: =ROUND(Q5*'Premissas'!$B$19+0*(1-'Premissas'!$B$19),2) -> 0 | S5: =ROUND(E5*'Premissas'!$B$17,2) -> 0 | T5: =ROUND(Q5*'Premissas'!$B$10,2) -> 0 | U5: =ROUND(R5*'Premissas'!$B$18,2) -> 0 | V5: =IF(A5<=12,'Premissas'!$B$24,'Premissas'!$B$25) -> 37000 | W5: =ROUND(G5+Q5,2) -> 0 | X5: =ROUND(I5+Q5,2) -> 0 | Y5: =ROUND(L5+R5,2) -> 0 | Z5: =ROUND(SUM(M5:P5)+SUM(S5:V5),2) -> 37000 | AA5: =ROUND(Y5-Z5,2) -> -37000 | AB5: =ROUND(-'Premissas'!$B$23+AA5,2) -> -137000 | AC5: =ROUND(X5-J5-SUM(M5:P5)-S5-T5-ROUND(Q5*'Premissas'!$B$18,2)-V5,2) -> -37000 | AD5: =ROUND(SUM($K$5:K5)-SUM($L$5:L5)+SUM($Q$5:Q5)-SUM($R$5:R5),2) -> 0 | AE5: =MAX(0,AB5)*'Premissas'!$B$28 -> 0 | AF5: =IF(AB5>=0,A5,999) -> 999 | AG5: =IF(AE5>=Resumo!$E$5,A5,999) -> 999 | AH5: =AB5+Capital!$A$5 -> -37000 | AI5: =AB5+Capital!$A$6 -> 13000 | AJ5: =AB5+Capital!$A$7 -> 63000
A6: 2 | B6: 0 | C6: =ROUNDUP(B6/'Premissas'!$B$14,0) -> 0 | D6: 0 | E6: =D6*'Premissas'!$B$16 -> 0 | F6: =ROUND(B6*'Premissas'!$B$5,2) -> 0 | G6: =ROUND(F6*'Premissas'!$B$6,2) -> 0 | H6: =ROUND(G6*'Premissas'!$B$7,2) -> 0 | I6: =ROUND(G6-H6,2) -> 0 | J6: =ROUND(I6*'Premissas'!$B$8+B6*(1-'Premissas'!$B$7)*'Premissas'!$B$9*'Premissas'!$B$6,2) -> 0 | K6: =ROUND(I6-J6,2) -> 0 | L6: =IF(A6>'Premissas'!$B$20,INDEX($K$5:$K$28,MAX(1,A6-'Premissas'!$B$20)),0) -> 0 | M6: =ROUND(I6*'Premissas'!$B$10,2) -> 0 | N6: =ROUND(I6*'Premissas'!$B$11,2) -> 0 | O6: =ROUND(B6*'Premissas'!$B$12*'Premissas'!$B$6,2) -> 0 | P6: =ROUND(B6*'Premissas'!$B$13*'Premissas'!$B$6,2) -> 0 | Q6: =ROUND(D6*'Premissas'!$B$15,2) -> 0 | R6: =ROUND(Q6*'Premissas'!$B$19+Q5*(1-'Premissas'!$B$19),2) -> 0 | S6: =ROUND(E6*'Premissas'!$B$17,2) -> 0 | T6: =ROUND(Q6*'Premissas'!$B$10,2) -> 0 | U6: =ROUND(R6*'Premissas'!$B$18,2) -> 0 | V6: =IF(A6<=12,'Premissas'!$B$24,'Premissas'!$B$25) -> 37000 | W6: =ROUND(G6+Q6,2) -> 0 | X6: =ROUND(I6+Q6,2) -> 0 | Y6: =ROUND(L6+R6,2) -> 0 | Z6: =ROUND(SUM(M6:P6)+SUM(S6:V6),2) -> 37000 | AA6: =ROUND(Y6-Z6,2) -> -37000 | AB6: =ROUND(AB5+AA6,2) -> -174000 | AC6: =ROUND(X6-J6-SUM(M6:P6)-S6-T6-ROUND(Q6*'Premissas'!$B$18,2)-V6,2) -> -37000 | AD6: =ROUND(SUM($K$5:K6)-SUM($L$5:L6)+SUM($Q$5:Q6)-SUM($R$5:R6),2) -> 0 | AE6: =MAX(0,AB6)*'Premissas'!$B$28 -> 0 | AF6: =IF(AB6>=0,A6,999) -> 999 | AG6: =IF(AE6>=Resumo!$E$5,A6,999) -> 999 | AH6: =AB6+Capital!$A$5 -> -74000 | AI6: =AB6+Capital!$A$6 -> -24000 | AJ6: =AB6+Capital!$A$7 -> 26000
A7: 3 | B7: 20 | C7: =ROUNDUP(B7/'Premissas'!$B$14,0) -> 1000 | D7: 0 | E7: =D7*'Premissas'!$B$16 -> 0 | F7: =ROUND(B7*'Premissas'!$B$5,2) -> 580 | G7: =ROUND(F7*'Premissas'!$B$6,2) -> 2900 | H7: =ROUND(G7*'Premissas'!$B$7,2) -> 232 | I7: =ROUND(G7-H7,2) -> 2668 | J7: =ROUND(I7*'Premissas'!$B$8+B7*(1-'Premissas'!$B$7)*'Premissas'!$B$9*'Premissas'!$B$6,2) -> 356.13 | K7: =ROUND(I7-J7,2) -> 2311.87 | L7: =IF(A7>'Premissas'!$B$20,INDEX($K$5:$K$28,MAX(1,A7-'Premissas'!$B$20)),0) -> 0 | M7: =ROUND(I7*'Premissas'!$B$10,2) -> 400.2 | N7: =ROUND(I7*'Premissas'!$B$11,2) -> 80.04 | O7: =ROUND(B7*'Premissas'!$B$12*'Premissas'!$B$6,2) -> 1000 | P7: =ROUND(B7*'Premissas'!$B$13*'Premissas'!$B$6,2) -> 100 | Q7: =ROUND(D7*'Premissas'!$B$15,2) -> 0 | R7: =ROUND(Q7*'Premissas'!$B$19+Q6*(1-'Premissas'!$B$19),2) -> 0 | S7: =ROUND(E7*'Premissas'!$B$17,2) -> 0 | T7: =ROUND(Q7*'Premissas'!$B$10,2) -> 0 | U7: =ROUND(R7*'Premissas'!$B$18,2) -> 0 | V7: =IF(A7<=12,'Premissas'!$B$24,'Premissas'!$B$25) -> 37000 | W7: =ROUND(G7+Q7,2) -> 2900 | X7: =ROUND(I7+Q7,2) -> 2668 | Y7: =ROUND(L7+R7,2) -> 0 | Z7: =ROUND(SUM(M7:P7)+SUM(S7:V7),2) -> 38580.24 | AA7: =ROUND(Y7-Z7,2) -> -38580.24 | AB7: =ROUND(AB6+AA7,2) -> -212580.24 | AC7: =ROUND(X7-J7-SUM(M7:P7)-S7-T7-ROUND(Q7*'Premissas'!$B$18,2)-V7,2) -> -36268.37 | AD7: =ROUND(SUM($K$5:K7)-SUM($L$5:L7)+SUM($Q$5:Q7)-SUM($R$5:R7),2) -> 2311.87 | AE7: =MAX(0,AB7)*'Premissas'!$B$28 -> 0 | AF7: =IF(AB7>=0,A7,999) -> 999 | AG7: =IF(AE7>=Resumo!$E$5,A7,999) -> 999 | AH7: =AB7+Capital!$A$5 -> -112580.24 | AI7: =AB7+Capital!$A$6 -> -62580.24 | AJ7: =AB7+Capital!$A$7 -> -12580.24
A8: 4 | B8: 40 | C8: =ROUNDUP(B8/'Premissas'!$B$14,0) -> 2000 | D8: 0 | E8: =D8*'Premissas'!$B$16 -> 0 | F8: =ROUND(B8*'Premissas'!$B$5,2) -> 1160 | G8: =ROUND(F8*'Premissas'!$B$6,2) -> 5800 | H8: =ROUND(G8*'Premissas'!$B$7,2) -> 464 | I8: =ROUND(G8-H8,2) -> 5336 | J8: =ROUND(I8*'Premissas'!$B$8+B8*(1-'Premissas'!$B$7)*'Premissas'!$B$9*'Premissas'!$B$6,2) -> 712.26 | K8: =ROUND(I8-J8,2) -> 4623.74 | L8: =IF(A8>'Premissas'!$B$20,INDEX($K$5:$K$28,MAX(1,A8-'Premissas'!$B$20)),0) -> 2311.87 | M8: =ROUND(I8*'Premissas'!$B$10,2) -> 800.4 | N8: =ROUND(I8*'Premissas'!$B$11,2) -> 160.08 | O8: =ROUND(B8*'Premissas'!$B$12*'Premissas'!$B$6,2) -> 2000 | P8: =ROUND(B8*'Premissas'!$B$13*'Premissas'!$B$6,2) -> 200 | Q8: =ROUND(D8*'Premissas'!$B$15,2) -> 0 | R8: =ROUND(Q8*'Premissas'!$B$19+Q7*(1-'Premissas'!$B$19),2) -> 0 | S8: =ROUND(E8*'Premissas'!$B$17,2) -> 0 | T8: =ROUND(Q8*'Premissas'!$B$10,2) -> 0 | U8: =ROUND(R8*'Premissas'!$B$18,2) -> 0 | V8: =IF(A8<=12,'Premissas'!$B$24,'Premissas'!$B$25) -> 37000 | W8: =ROUND(G8+Q8,2) -> 5800 | X8: =ROUND(I8+Q8,2) -> 5336 | Y8: =ROUND(L8+R8,2) -> 2311.87 | Z8: =ROUND(SUM(M8:P8)+SUM(S8:V8),2) -> 40160.48 | AA8: =ROUND(Y8-Z8,2) -> -37848.61 | AB8: =ROUND(AB7+AA8,2) -> -250428.85 | AC8: =ROUND(X8-J8-SUM(M8:P8)-S8-T8-ROUND(Q8*'Premissas'!$B$18,2)-V8,2) -> -35536.74 | AD8: =ROUND(SUM($K$5:K8)-SUM($L$5:L8)+SUM($Q$5:Q8)-SUM($R$5:R8),2) -> 4623.74 | AE8: =MAX(0,AB8)*'Premissas'!$B$28 -> 0 | AF8: =IF(AB8>=0,A8,999) -> 999 | AG8: =IF(AE8>=Resumo!$E$5,A8,999) -> 999 | AH8: =AB8+Capital!$A$5 -> -150428.85 | AI8: =AB8+Capital!$A$6 -> -100428.85 | AJ8: =AB8+Capital!$A$7 -> -50428.85
A9: 5 | B9: 80 | C9: =ROUNDUP(B9/'Premissas'!$B$14,0) -> 4000 | D9: 1 | E9: =D9*'Premissas'!$B$16 -> 80 | F9: =ROUND(B9*'Premissas'!$B$5,2) -> 2320 | G9: =ROUND(F9*'Premissas'!$B$6,2) -> 11600 | H9: =ROUND(G9*'Premissas'!$B$7,2) -> 928 | I9: =ROUND(G9-H9,2) -> 10672 | J9: =ROUND(I9*'Premissas'!$B$8+B9*(1-'Premissas'!$B$7)*'Premissas'!$B$9*'Premissas'!$B$6,2) -> 1424.53 | K9: =ROUND(I9-J9,2) -> 9247.47 | L9: =IF(A9>'Premissas'!$B$20,INDEX($K$5:$K$28,MAX(1,A9-'Premissas'!$B$20)),0) -> 4623.74 | M9: =ROUND(I9*'Premissas'!$B$10,2) -> 1600.8 | N9: =ROUND(I9*'Premissas'!$B$11,2) -> 320.16 | O9: =ROUND(B9*'Premissas'!$B$12*'Premissas'!$B$6,2) -> 4000 | P9: =ROUND(B9*'Premissas'!$B$13*'Premissas'!$B$6,2) -> 400 | Q9: =ROUND(D9*'Premissas'!$B$15,2) -> 30000 | R9: =ROUND(Q9*'Premissas'!$B$19+Q8*(1-'Premissas'!$B$19),2) -> 15000 | S9: =ROUND(E9*'Premissas'!$B$17,2) -> 14400 | T9: =ROUND(Q9*'Premissas'!$B$10,2) -> 4500 | U9: =ROUND(R9*'Premissas'!$B$18,2) -> 750 | V9: =IF(A9<=12,'Premissas'!$B$24,'Premissas'!$B$25) -> 37000 | W9: =ROUND(G9+Q9,2) -> 41600 | X9: =ROUND(I9+Q9,2) -> 40672 | Y9: =ROUND(L9+R9,2) -> 19623.74 | Z9: =ROUND(SUM(M9:P9)+SUM(S9:V9),2) -> 62970.96 | AA9: =ROUND(Y9-Z9,2) -> -43347.22 | AB9: =ROUND(AB8+AA9,2) -> -293776.07 | AC9: =ROUND(X9-J9-SUM(M9:P9)-S9-T9-ROUND(Q9*'Premissas'!$B$18,2)-V9,2) -> -24473.49 | AD9: =ROUND(SUM($K$5:K9)-SUM($L$5:L9)+SUM($Q$5:Q9)-SUM($R$5:R9),2) -> 24247.47 | AE9: =MAX(0,AB9)*'Premissas'!$B$28 -> 0 | AF9: =IF(AB9>=0,A9,999) -> 999 | AG9: =IF(AE9>=Resumo!$E$5,A9,999) -> 999 | AH9: =AB9+Capital!$A$5 -> -193776.07 | AI9: =AB9+Capital!$A$6 -> -143776.07 | AJ9: =AB9+Capital!$A$7 -> -93776.07
A10: 6 | B10: 120 | C10: =ROUNDUP(B10/'Premissas'!$B$14,0) -> 6000 | D10: 0 | E10: =D10*'Premissas'!$B$16 -> 0 | F10: =ROUND(B10*'Premissas'!$B$5,2) -> 3480 | G10: =ROUND(F10*'Premissas'!$B$6,2) -> 17400 | H10: =ROUND(G10*'Premissas'!$B$7,2) -> 1392 | I10: =ROUND(G10-H10,2) -> 16008 | J10: =ROUND(I10*'Premissas'!$B$8+B10*(1-'Premissas'!$B$7)*'Premissas'!$B$9*'Premissas'!$B$6,2) -> 2136.79 | K10: =ROUND(I10-J10,2) -> 13871.21 | L10: =IF(A10>'Premissas'!$B$20,INDEX($K$5:$K$28,MAX(1,A10-'Premissas'!$B$20)),0) -> 9247.47 | M10: =ROUND(I10*'Premissas'!$B$10,2) -> 2401.2 | N10: =ROUND(I10*'Premissas'!$B$11,2) -> 480.24 | O10: =ROUND(B10*'Premissas'!$B$12*'Premissas'!$B$6,2) -> 6000 | P10: =ROUND(B10*'Premissas'!$B$13*'Premissas'!$B$6,2) -> 600 | Q10: =ROUND(D10*'Premissas'!$B$15,2) -> 0 | R10: =ROUND(Q10*'Premissas'!$B$19+Q9*(1-'Premissas'!$B$19),2) -> 15000 | S10: =ROUND(E10*'Premissas'!$B$17,2) -> 0 | T10: =ROUND(Q10*'Premissas'!$B$10,2) -> 0 | U10: =ROUND(R10*'Premissas'!$B$18,2) -> 750 | V10: =IF(A10<=12,'Premissas'!$B$24,'Premissas'!$B$25) -> 37000 | W10: =ROUND(G10+Q10,2) -> 17400 | X10: =ROUND(I10+Q10,2) -> 16008 | Y10: =ROUND(L10+R10,2) -> 24247.47 | Z10: =ROUND(SUM(M10:P10)+SUM(S10:V10),2) -> 47231.44 | AA10: =ROUND(Y10-Z10,2) -> -22983.97 | AB10: =ROUND(AB9+AA10,2) -> -316760.04 | AC10: =ROUND(X10-J10-SUM(M10:P10)-S10-T10-ROUND(Q10*'Premissas'!$B$18,2)-V10,2) -> -32610.23 | AD10: =ROUND(SUM($K$5:K10)-SUM($L$5:L10)+SUM($Q$5:Q10)-SUM($R$5:R10),2) -> 13871.21 | AE10: =MAX(0,AB10)*'Premissas'!$B$28 -> 0 | AF10: =IF(AB10>=0,A10,999) -> 999 | AG10: =IF(AE10>=Resumo!$E$5,A10,999) -> 999 | AH10: =AB10+Capital!$A$5 -> -216760.04 | AI10: =AB10+Capital!$A$6 -> -166760.04 | AJ10: =AB10+Capital!$A$7 -> -116760.04
A11: 7 | B11: 180 | C11: =ROUNDUP(B11/'Premissas'!$B$14,0) -> 9000 | D11: 0 | E11: =D11*'Premissas'!$B$16 -> 0 | F11: =ROUND(B11*'Premissas'!$B$5,2) -> 5220 | G11: =ROUND(F11*'Premissas'!$B$6,2) -> 26100 | H11: =ROUND(G11*'Premissas'!$B$7,2) -> 2088 | I11: =ROUND(G11-H11,2) -> 24012 | J11: =ROUND(I11*'Premissas'!$B$8+B11*(1-'Premissas'!$B$7)*'Premissas'!$B$9*'Premissas'!$B$6,2) -> 3205.19 | K11: =ROUND(I11-J11,2) -> 20806.81 | L11: =IF(A11>'Premissas'!$B$20,INDEX($K$5:$K$28,MAX(1,A11-'Premissas'!$B$20)),0) -> 13871.21 | M11: =ROUND(I11*'Premissas'!$B$10,2) -> 3601.8 | N11: =ROUND(I11*'Premissas'!$B$11,2) -> 720.36 | O11: =ROUND(B11*'Premissas'!$B$12*'Premissas'!$B$6,2) -> 9000 | P11: =ROUND(B11*'Premissas'!$B$13*'Premissas'!$B$6,2) -> 900 | Q11: =ROUND(D11*'Premissas'!$B$15,2) -> 0 | R11: =ROUND(Q11*'Premissas'!$B$19+Q10*(1-'Premissas'!$B$19),2) -> 0 | S11: =ROUND(E11*'Premissas'!$B$17,2) -> 0 | T11: =ROUND(Q11*'Premissas'!$B$10,2) -> 0 | U11: =ROUND(R11*'Premissas'!$B$18,2) -> 0 | V11: =IF(A11<=12,'Premissas'!$B$24,'Premissas'!$B$25) -> 37000 | W11: =ROUND(G11+Q11,2) -> 26100 | X11: =ROUND(I11+Q11,2) -> 24012 | Y11: =ROUND(L11+R11,2) -> 13871.21 | Z11: =ROUND(SUM(M11:P11)+SUM(S11:V11),2) -> 51222.16 | AA11: =ROUND(Y11-Z11,2) -> -37350.95 | AB11: =ROUND(AB10+AA11,2) -> -354110.99 | AC11: =ROUND(X11-J11-SUM(M11:P11)-S11-T11-ROUND(Q11*'Premissas'!$B$18,2)-V11,2) -> -30415.35 | AD11: =ROUND(SUM($K$5:K11)-SUM($L$5:L11)+SUM($Q$5:Q11)-SUM($R$5:R11),2) -> 20806.81 | AE11: =MAX(0,AB11)*'Premissas'!$B$28 -> 0 | AF11: =IF(AB11>=0,A11,999) -> 999 | AG11: =IF(AE11>=Resumo!$E$5,A11,999) -> 999 | AH11: =AB11+Capital!$A$5 -> -254110.99 | AI11: =AB11+Capital!$A$6 -> -204110.99 | AJ11: =AB11+Capital!$A$7 -> -154110.99
A12: 8 | B12: 250 | C12: =ROUNDUP(B12/'Premissas'!$B$14,0) -> 12500 | D12: 0 | E12: =D12*'Premissas'!$B$16 -> 0 | F12: =ROUND(B12*'Premissas'!$B$5,2) -> 7250 | G12: =ROUND(F12*'Premissas'!$B$6,2) -> 36250 | H12: =ROUND(G12*'Premissas'!$B$7,2) -> 2900 | I12: =ROUND(G12-H12,2) -> 33350 | J12: =ROUND(I12*'Premissas'!$B$8+B12*(1-'Premissas'!$B$7)*'Premissas'!$B$9*'Premissas'!$B$6,2) -> 4451.65 | K12: =ROUND(I12-J12,2) -> 28898.35 | L12: =IF(A12>'Premissas'!$B$20,INDEX($K$5:$K$28,MAX(1,A12-'Premissas'!$B$20)),0) -> 20806.81 | M12: =ROUND(I12*'Premissas'!$B$10,2) -> 5002.5 | N12: =ROUND(I12*'Premissas'!$B$11,2) -> 1000.5 | O12: =ROUND(B12*'Premissas'!$B$12*'Premissas'!$B$6,2) -> 12500 | P12: =ROUND(B12*'Premissas'!$B$13*'Premissas'!$B$6,2) -> 1250 | Q12: =ROUND(D12*'Premissas'!$B$15,2) -> 0 | R12: =ROUND(Q12*'Premissas'!$B$19+Q11*(1-'Premissas'!$B$19),2) -> 0 | S12: =ROUND(E12*'Premissas'!$B$17,2) -> 0 | T12: =ROUND(Q12*'Premissas'!$B$10,2) -> 0 | U12: =ROUND(R12*'Premissas'!$B$18,2) -> 0 | V12: =IF(A12<=12,'Premissas'!$B$24,'Premissas'!$B$25) -> 37000 | W12: =ROUND(G12+Q12,2) -> 36250 | X12: =ROUND(I12+Q12,2) -> 33350 | Y12: =ROUND(L12+R12,2) -> 20806.81 | Z12: =ROUND(SUM(M12:P12)+SUM(S12:V12),2) -> 56753 | AA12: =ROUND(Y12-Z12,2) -> -35946.19 | AB12: =ROUND(AB11+AA12,2) -> -390057.18 | AC12: =ROUND(X12-J12-SUM(M12:P12)-S12-T12-ROUND(Q12*'Premissas'!$B$18,2)-V12,2) -> -27854.65 | AD12: =ROUND(SUM($K$5:K12)-SUM($L$5:L12)+SUM($Q$5:Q12)-SUM($R$5:R12),2) -> 28898.35 | AE12: =MAX(0,AB12)*'Premissas'!$B$28 -> 0 | AF12: =IF(AB12>=0,A12,999) -> 999 | AG12: =IF(AE12>=Resumo!$E$5,A12,999) -> 999 | AH12: =AB12+Capital!$A$5 -> -290057.18 | AI12: =AB12+Capital!$A$6 -> -240057.18 | AJ12: =AB12+Capital!$A$7 -> -190057.18
A13: 9 | B13: 300 | C13: =ROUNDUP(B13/'Premissas'!$B$14,0) -> 15000 | D13: 1 | E13: =D13*'Premissas'!$B$16 -> 80 | F13: =ROUND(B13*'Premissas'!$B$5,2) -> 8700 | G13: =ROUND(F13*'Premissas'!$B$6,2) -> 43500 | H13: =ROUND(G13*'Premissas'!$B$7,2) -> 3480 | I13: =ROUND(G13-H13,2) -> 40020 | J13: =ROUND(I13*'Premissas'!$B$8+B13*(1-'Premissas'!$B$7)*'Premissas'!$B$9*'Premissas'!$B$6,2) -> 5341.98 | K13: =ROUND(I13-J13,2) -> 34678.02 | L13: =IF(A13>'Premissas'!$B$20,INDEX($K$5:$K$28,MAX(1,A13-'Premissas'!$B$20)),0) -> 28898.35 | M13: =ROUND(I13*'Premissas'!$B$10,2) -> 6003 | N13: =ROUND(I13*'Premissas'!$B$11,2) -> 1200.6 | O13: =ROUND(B13*'Premissas'!$B$12*'Premissas'!$B$6,2) -> 15000 | P13: =ROUND(B13*'Premissas'!$B$13*'Premissas'!$B$6,2) -> 1500 | Q13: =ROUND(D13*'Premissas'!$B$15,2) -> 30000 | R13: =ROUND(Q13*'Premissas'!$B$19+Q12*(1-'Premissas'!$B$19),2) -> 15000 | S13: =ROUND(E13*'Premissas'!$B$17,2) -> 14400 | T13: =ROUND(Q13*'Premissas'!$B$10,2) -> 4500 | U13: =ROUND(R13*'Premissas'!$B$18,2) -> 750 | V13: =IF(A13<=12,'Premissas'!$B$24,'Premissas'!$B$25) -> 37000 | W13: =ROUND(G13+Q13,2) -> 73500 | X13: =ROUND(I13+Q13,2) -> 70020 | Y13: =ROUND(L13+R13,2) -> 43898.35 | Z13: =ROUND(SUM(M13:P13)+SUM(S13:V13),2) -> 80353.6 | AA13: =ROUND(Y13-Z13,2) -> -36455.25 | AB13: =ROUND(AB12+AA13,2) -> -426512.43 | AC13: =ROUND(X13-J13-SUM(M13:P13)-S13-T13-ROUND(Q13*'Premissas'!$B$18,2)-V13,2) -> -16425.58 | AD13: =ROUND(SUM($K$5:K13)-SUM($L$5:L13)+SUM($Q$5:Q13)-SUM($R$5:R13),2) -> 49678.02 | AE13: =MAX(0,AB13)*'Premissas'!$B$28 -> 0 | AF13: =IF(AB13>=0,A13,999) -> 999 | AG13: =IF(AE13>=Resumo!$E$5,A13,999) -> 999 | AH13: =AB13+Capital!$A$5 -> -326512.43 | AI13: =AB13+Capital!$A$6 -> -276512.43 | AJ13: =AB13+Capital!$A$7 -> -226512.43
A14: 10 | B14: 350 | C14: =ROUNDUP(B14/'Premissas'!$B$14,0) -> 17500 | D14: 0 | E14: =D14*'Premissas'!$B$16 -> 0 | F14: =ROUND(B14*'Premissas'!$B$5,2) -> 10150 | G14: =ROUND(F14*'Premissas'!$B$6,2) -> 50750 | H14: =ROUND(G14*'Premissas'!$B$7,2) -> 4060 | I14: =ROUND(G14-H14,2) -> 46690 | J14: =ROUND(I14*'Premissas'!$B$8+B14*(1-'Premissas'!$B$7)*'Premissas'!$B$9*'Premissas'!$B$6,2) -> 6232.31 | K14: =ROUND(I14-J14,2) -> 40457.69 | L14: =IF(A14>'Premissas'!$B$20,INDEX($K$5:$K$28,MAX(1,A14-'Premissas'!$B$20)),0) -> 34678.02 | M14: =ROUND(I14*'Premissas'!$B$10,2) -> 7003.5 | N14: =ROUND(I14*'Premissas'!$B$11,2) -> 1400.7 | O14: =ROUND(B14*'Premissas'!$B$12*'Premissas'!$B$6,2) -> 17500 | P14: =ROUND(B14*'Premissas'!$B$13*'Premissas'!$B$6,2) -> 1750 | Q14: =ROUND(D14*'Premissas'!$B$15,2) -> 0 | R14: =ROUND(Q14*'Premissas'!$B$19+Q13*(1-'Premissas'!$B$19),2) -> 15000 | S14: =ROUND(E14*'Premissas'!$B$17,2) -> 0 | T14: =ROUND(Q14*'Premissas'!$B$10,2) -> 0 | U14: =ROUND(R14*'Premissas'!$B$18,2) -> 750 | V14: =IF(A14<=12,'Premissas'!$B$24,'Premissas'!$B$25) -> 37000 | W14: =ROUND(G14+Q14,2) -> 50750 | X14: =ROUND(I14+Q14,2) -> 46690 | Y14: =ROUND(L14+R14,2) -> 49678.02 | Z14: =ROUND(SUM(M14:P14)+SUM(S14:V14),2) -> 65404.2 | AA14: =ROUND(Y14-Z14,2) -> -15726.18 | AB14: =ROUND(AB13+AA14,2) -> -442238.61 | AC14: =ROUND(X14-J14-SUM(M14:P14)-S14-T14-ROUND(Q14*'Premissas'!$B$18,2)-V14,2) -> -24196.51 | AD14: =ROUND(SUM($K$5:K14)-SUM($L$5:L14)+SUM($Q$5:Q14)-SUM($R$5:R14),2) -> 40457.69 | AE14: =MAX(0,AB14)*'Premissas'!$B$28 -> 0 | AF14: =IF(AB14>=0,A14,999) -> 999 | AG14: =IF(AE14>=Resumo!$E$5,A14,999) -> 999 | AH14: =AB14+Capital!$A$5 -> -342238.61 | AI14: =AB14+Capital!$A$6 -> -292238.61 | AJ14: =AB14+Capital!$A$7 -> -242238.61
A15: 11 | B15: 400 | C15: =ROUNDUP(B15/'Premissas'!$B$14,0) -> 20000 | D15: 0 | E15: =D15*'Premissas'!$B$16 -> 0 | F15: =ROUND(B15*'Premissas'!$B$5,2) -> 11600 | G15: =ROUND(F15*'Premissas'!$B$6,2) -> 58000 | H15: =ROUND(G15*'Premissas'!$B$7,2) -> 4640 | I15: =ROUND(G15-H15,2) -> 53360 | J15: =ROUND(I15*'Premissas'!$B$8+B15*(1-'Premissas'!$B$7)*'Premissas'!$B$9*'Premissas'!$B$6,2) -> 7122.64 | K15: =ROUND(I15-J15,2) -> 46237.36 | L15: =IF(A15>'Premissas'!$B$20,INDEX($K$5:$K$28,MAX(1,A15-'Premissas'!$B$20)),0) -> 40457.69 | M15: =ROUND(I15*'Premissas'!$B$10,2) -> 8004 | N15: =ROUND(I15*'Premissas'!$B$11,2) -> 1600.8 | O15: =ROUND(B15*'Premissas'!$B$12*'Premissas'!$B$6,2) -> 20000 | P15: =ROUND(B15*'Premissas'!$B$13*'Premissas'!$B$6,2) -> 2000 | Q15: =ROUND(D15*'Premissas'!$B$15,2) -> 0 | R15: =ROUND(Q15*'Premissas'!$B$19+Q14*(1-'Premissas'!$B$19),2) -> 0 | S15: =ROUND(E15*'Premissas'!$B$17,2) -> 0 | T15: =ROUND(Q15*'Premissas'!$B$10,2) -> 0 | U15: =ROUND(R15*'Premissas'!$B$18,2) -> 0 | V15: =IF(A15<=12,'Premissas'!$B$24,'Premissas'!$B$25) -> 37000 | W15: =ROUND(G15+Q15,2) -> 58000 | X15: =ROUND(I15+Q15,2) -> 53360 | Y15: =ROUND(L15+R15,2) -> 40457.69 | Z15: =ROUND(SUM(M15:P15)+SUM(S15:V15),2) -> 68604.8 | AA15: =ROUND(Y15-Z15,2) -> -28147.11 | AB15: =ROUND(AB14+AA15,2) -> -470385.72 | AC15: =ROUND(X15-J15-SUM(M15:P15)-S15-T15-ROUND(Q15*'Premissas'!$B$18,2)-V15,2) -> -22367.44 | AD15: =ROUND(SUM($K$5:K15)-SUM($L$5:L15)+SUM($Q$5:Q15)-SUM($R$5:R15),2) -> 46237.36 | AE15: =MAX(0,AB15)*'Premissas'!$B$28 -> 0 | AF15: =IF(AB15>=0,A15,999) -> 999 | AG15: =IF(AE15>=Resumo!$E$5,A15,999) -> 999 | AH15: =AB15+Capital!$A$5 -> -370385.72 | AI15: =AB15+Capital!$A$6 -> -320385.72 | AJ15: =AB15+Capital!$A$7 -> -270385.72
A16: 12 | B16: 450 | C16: =ROUNDUP(B16/'Premissas'!$B$14,0) -> 22500 | D16: 0 | E16: =D16*'Premissas'!$B$16 -> 0 | F16: =ROUND(B16*'Premissas'!$B$5,2) -> 13050 | G16: =ROUND(F16*'Premissas'!$B$6,2) -> 65250 | H16: =ROUND(G16*'Premissas'!$B$7,2) -> 5220 | I16: =ROUND(G16-H16,2) -> 60030 | J16: =ROUND(I16*'Premissas'!$B$8+B16*(1-'Premissas'!$B$7)*'Premissas'!$B$9*'Premissas'!$B$6,2) -> 8012.97 | K16: =ROUND(I16-J16,2) -> 52017.03 | L16: =IF(A16>'Premissas'!$B$20,INDEX($K$5:$K$28,MAX(1,A16-'Premissas'!$B$20)),0) -> 46237.36 | M16: =ROUND(I16*'Premissas'!$B$10,2) -> 9004.5 | N16: =ROUND(I16*'Premissas'!$B$11,2) -> 1800.9 | O16: =ROUND(B16*'Premissas'!$B$12*'Premissas'!$B$6,2) -> 22500 | P16: =ROUND(B16*'Premissas'!$B$13*'Premissas'!$B$6,2) -> 2250 | Q16: =ROUND(D16*'Premissas'!$B$15,2) -> 0 | R16: =ROUND(Q16*'Premissas'!$B$19+Q15*(1-'Premissas'!$B$19),2) -> 0 | S16: =ROUND(E16*'Premissas'!$B$17,2) -> 0 | T16: =ROUND(Q16*'Premissas'!$B$10,2) -> 0 | U16: =ROUND(R16*'Premissas'!$B$18,2) -> 0 | V16: =IF(A16<=12,'Premissas'!$B$24,'Premissas'!$B$25) -> 37000 | W16: =ROUND(G16+Q16,2) -> 65250 | X16: =ROUND(I16+Q16,2) -> 60030 | Y16: =ROUND(L16+R16,2) -> 46237.36 | Z16: =ROUND(SUM(M16:P16)+SUM(S16:V16),2) -> 72555.4 | AA16: =ROUND(Y16-Z16,2) -> -26318.04 | AB16: =ROUND(AB15+AA16,2) -> -496703.76 | AC16: =ROUND(X16-J16-SUM(M16:P16)-S16-T16-ROUND(Q16*'Premissas'!$B$18,2)-V16,2) -> -20538.37 | AD16: =ROUND(SUM($K$5:K16)-SUM($L$5:L16)+SUM($Q$5:Q16)-SUM($R$5:R16),2) -> 52017.03 | AE16: =MAX(0,AB16)*'Premissas'!$B$28 -> 0 | AF16: =IF(AB16>=0,A16,999) -> 999 | AG16: =IF(AE16>=Resumo!$E$5,A16,999) -> 999 | AH16: =AB16+Capital!$A$5 -> -396703.76 | AI16: =AB16+Capital!$A$6 -> -346703.76 | AJ16: =AB16+Capital!$A$7 -> -296703.76
A17: 13 | B17: 500 | C17: =ROUNDUP(B17/'Premissas'!$B$14,0) -> 25000 | D17: 1 | E17: =D17*'Premissas'!$B$16 -> 80 | F17: =ROUND(B17*'Premissas'!$B$5,2) -> 14500 | G17: =ROUND(F17*'Premissas'!$B$6,2) -> 72500 | H17: =ROUND(G17*'Premissas'!$B$7,2) -> 5800 | I17: =ROUND(G17-H17,2) -> 66700 | J17: =ROUND(I17*'Premissas'!$B$8+B17*(1-'Premissas'!$B$7)*'Premissas'!$B$9*'Premissas'!$B$6,2) -> 8903.3 | K17: =ROUND(I17-J17,2) -> 57796.7 | L17: =IF(A17>'Premissas'!$B$20,INDEX($K$5:$K$28,MAX(1,A17-'Premissas'!$B$20)),0) -> 52017.03 | M17: =ROUND(I17*'Premissas'!$B$10,2) -> 10005 | N17: =ROUND(I17*'Premissas'!$B$11,2) -> 2001 | O17: =ROUND(B17*'Premissas'!$B$12*'Premissas'!$B$6,2) -> 25000 | P17: =ROUND(B17*'Premissas'!$B$13*'Premissas'!$B$6,2) -> 2500 | Q17: =ROUND(D17*'Premissas'!$B$15,2) -> 30000 | R17: =ROUND(Q17*'Premissas'!$B$19+Q16*(1-'Premissas'!$B$19),2) -> 15000 | S17: =ROUND(E17*'Premissas'!$B$17,2) -> 14400 | T17: =ROUND(Q17*'Premissas'!$B$10,2) -> 4500 | U17: =ROUND(R17*'Premissas'!$B$18,2) -> 750 | V17: =IF(A17<=12,'Premissas'!$B$24,'Premissas'!$B$25) -> 42000 | W17: =ROUND(G17+Q17,2) -> 102500 | X17: =ROUND(I17+Q17,2) -> 96700 | Y17: =ROUND(L17+R17,2) -> 67017.03 | Z17: =ROUND(SUM(M17:P17)+SUM(S17:V17),2) -> 101156 | AA17: =ROUND(Y17-Z17,2) -> -34138.97 | AB17: =ROUND(AB16+AA17,2) -> -530842.73 | AC17: =ROUND(X17-J17-SUM(M17:P17)-S17-T17-ROUND(Q17*'Premissas'!$B$18,2)-V17,2) -> -14109.3 | AD17: =ROUND(SUM($K$5:K17)-SUM($L$5:L17)+SUM($Q$5:Q17)-SUM($R$5:R17),2) -> 72796.7 | AE17: =MAX(0,AB17)*'Premissas'!$B$28 -> 0 | AF17: =IF(AB17>=0,A17,999) -> 999 | AG17: =IF(AE17>=Resumo!$E$5,A17,999) -> 999 | AH17: =AB17+Capital!$A$5 -> -430842.73 | AI17: =AB17+Capital!$A$6 -> -380842.73 | AJ17: =AB17+Capital!$A$7 -> -330842.73
... A28: 24 | B28: 750 | C28: =ROUNDUP(B28/'Premissas'!$B$14,0) -> 37500 | D28: 0 | E28: =D28*'Premissas'!$B$16 -> 0 | F28: =ROUND(B28*'Premissas'!$B$5,2) -> 21750 | G28: =ROUND(F28*'Premissas'!$B$6,2) -> 108750 | H28: =ROUND(G28*'Premissas'!$B$7,2) -> 8700 | I28: =ROUND(G28-H28,2) -> 100050 | J28: =ROUND(I28*'Premissas'!$B$8+B28*(1-'Premissas'!$B$7)*'Premissas'!$B$9*'Premissas'!$B$6,2) -> 13354.95 | K28: =ROUND(I28-J28,2) -> 86695.05 | L28: =IF(A28>'Premissas'!$B$20,INDEX($K$5:$K$28,MAX(1,A28-'Premissas'!$B$20)),0) -> 80915.38 | M28: =ROUND(I28*'Premissas'!$B$10,2) -> 15007.5 | N28: =ROUND(I28*'Premissas'!$B$11,2) -> 3001.5 | O28: =ROUND(B28*'Premissas'!$B$12*'Premissas'!$B$6,2) -> 37500 | P28: =ROUND(B28*'Premissas'!$B$13*'Premissas'!$B$6,2) -> 3750 | Q28: =ROUND(D28*'Premissas'!$B$15,2) -> 0 | R28: =ROUND(Q28*'Premissas'!$B$19+Q27*(1-'Premissas'!$B$19),2) -> 0 | S28: =ROUND(E28*'Premissas'!$B$17,2) -> 0 | T28: =ROUND(Q28*'Premissas'!$B$10,2) -> 0 | U28: =ROUND(R28*'Premissas'!$B$18,2) -> 0 | V28: =IF(A28<=12,'Premissas'!$B$24,'Premissas'!$B$25) -> 42000 | W28: =ROUND(G28+Q28,2) -> 108750 | X28: =ROUND(I28+Q28,2) -> 100050 | Y28: =ROUND(L28+R28,2) -> 80915.38 | Z28: =ROUND(SUM(M28:P28)+SUM(S28:V28),2) -> 101259 | AA28: =ROUND(Y28-Z28,2) -> -20343.62 | AB28: =ROUND(AB27+AA28,2) -> -737708.49 | AC28: =ROUND(X28-J28-SUM(M28:P28)-S28-T28-ROUND(Q28*'Premissas'!$B$18,2)-V28,2) -> -14563.95 | AD28: =ROUND(SUM($K$5:K28)-SUM($L$5:L28)+SUM($Q$5:Q28)-SUM($R$5:R28),2) -> 86695.05 | AE28: =MAX(0,AB28)*'Premissas'!$B$28 -> 0 | AF28: =IF(AB28>=0,A28,999) -> 999 | AG28: =IF(AE28>=Resumo!$E$5,A28,999) -> 999 | AH28: =AB28+Capital!$A$5 -> -637708.49 | AI28: =AB28+Capital!$A$6 -> -587708.49 | AJ28: =AB28+Capital!$A$7 -> -537708.49

Sheet Base
A1: Base | fluxo mensal em BRL, salvo indicação
A2: Agenda editável em azul. Cenário hipotético; não previsão. | M0 separado: -R$100 mil nas premissas. Acumulado exclui aportes/distribuição.
A4: Mês | B4: Pedidos aprovados | C4: Visitas qualificadas | D4: Mapas faturados | E4: Horas diretas TI | F4: Loja bruta USD | G4: Loja bruta BRL | H4: Estornos BRL | I4: Loja após estornos BRL | J4: Taxa plataforma BRL | K4: Liquidação gerada BRL | L4: Loja recebida BRL | M4: Tributos loja BRL | N4: Reserva meios/FX BRL | O4: Aquisição / mídia BRL | P4: Suporte loja BRL | Q4: Fatura TI BRL | R4: Recebimentos TI BRL | S4: Entrega TI BRL | T4: Tributos TI BRL | U4: Comercial TI caixa BRL | V4: Fixo BRL | W4: Vendas brutas BRL | X4: Receita após estornos BRL | Y4: Recebimentos BRL | Z4: Saídas caixa BRL | AA4: Fluxo líquido BRL | AB4: Acumulado sem aporte BRL | AC4: Resultado competência BRL | AD4: A receber BRL | AE4: 50% excedente positivo BRL | AF4: Mês elegível payback projeto | AG4: Mês elegível Dani hipotético | AH4: Saldo com 100k | AI4: Saldo com 150k | AJ4: Saldo com 200k
A5: 1 | B5: 0 | C5: =ROUNDUP(B5/'Premissas'!$B$14,0) -> 0 | D5: 0 | E5: =D5*'Premissas'!$B$16 -> 0 | F5: =ROUND(B5*'Premissas'!$B$5,2) -> 0 | G5: =ROUND(F5*'Premissas'!$B$6,2) -> 0 | H5: =ROUND(G5*'Premissas'!$B$7,2) -> 0 | I5: =ROUND(G5-H5,2) -> 0 | J5: =ROUND(I5*'Premissas'!$B$8+B5*(1-'Premissas'!$B$7)*'Premissas'!$B$9*'Premissas'!$B$6,2) -> 0 | K5: =ROUND(I5-J5,2) -> 0 | L5: =IF(A5>'Premissas'!$B$20,INDEX($K$5:$K$28,MAX(1,A5-'Premissas'!$B$20)),0) -> 0 | M5: =ROUND(I5*'Premissas'!$B$10,2) -> 0 | N5: =ROUND(I5*'Premissas'!$B$11,2) -> 0 | O5: =ROUND(B5*'Premissas'!$B$12*'Premissas'!$B$6,2) -> 0 | P5: =ROUND(B5*'Premissas'!$B$13*'Premissas'!$B$6,2) -> 0 | Q5: =ROUND(D5*'Premissas'!$B$15,2) -> 0 | R5: =ROUND(Q5*'Premissas'!$B$19+0*(1-'Premissas'!$B$19),2) -> 0 | S5: =ROUND(E5*'Premissas'!$B$17,2) -> 0 | T5: =ROUND(Q5*'Premissas'!$B$10,2) -> 0 | U5: =ROUND(R5*'Premissas'!$B$18,2) -> 0 | V5: =IF(A5<=12,'Premissas'!$B$24,'Premissas'!$B$25) -> 37000 | W5: =ROUND(G5+Q5,2) -> 0 | X5: =ROUND(I5+Q5,2) -> 0 | Y5: =ROUND(L5+R5,2) -> 0 | Z5: =ROUND(SUM(M5:P5)+SUM(S5:V5),2) -> 37000 | AA5: =ROUND(Y5-Z5,2) -> -37000 | AB5: =ROUND(-'Premissas'!$B$23+AA5,2) -> -137000 | AC5: =ROUND(X5-J5-SUM(M5:P5)-S5-T5-ROUND(Q5*'Premissas'!$B$18,2)-V5,2) -> -37000 | AD5: =ROUND(SUM($K$5:K5)-SUM($L$5:L5)+SUM($Q$5:Q5)-SUM($R$5:R5),2) -> 0 | AE5: =MAX(0,AB5)*'Premissas'!$B$28 -> 0 | AF5: =IF(AB5>=0,A5,999) -> 999 | AG5: =IF(AE5>=Resumo!$E$6,A5,999) -> 999 | AH5: =AB5+Capital!$A$5 -> -37000 | AI5: =AB5+Capital!$A$6 -> 13000 | AJ5: =AB5+Capital!$A$7 -> 63000
A6: 2 | B6: 0 | C6: =ROUNDUP(B6/'Premissas'!$B$14,0) -> 0 | D6: 0 | E6: =D6*'Premissas'!$B$16 -> 0 | F6: =ROUND(B6*'Premissas'!$B$5,2) -> 0 | G6: =ROUND(F6*'Premissas'!$B$6,2) -> 0 | H6: =ROUND(G6*'Premissas'!$B$7,2) -> 0 | I6: =ROUND(G6-H6,2) -> 0 | J6: =ROUND(I6*'Premissas'!$B$8+B6*(1-'Premissas'!$B$7)*'Premissas'!$B$9*'Premissas'!$B$6,2) -> 0 | K6: =ROUND(I6-J6,2) -> 0 | L6: =IF(A6>'Premissas'!$B$20,INDEX($K$5:$K$28,MAX(1,A6-'Premissas'!$B$20)),0) -> 0 | M6: =ROUND(I6*'Premissas'!$B$10,2) -> 0 | N6: =ROUND(I6*'Premissas'!$B$11,2) -> 0 | O6: =ROUND(B6*'Premissas'!$B$12*'Premissas'!$B$6,2) -> 0 | P6: =ROUND(B6*'Premissas'!$B$13*'Premissas'!$B$6,2) -> 0 | Q6: =ROUND(D6*'Premissas'!$B$15,2) -> 0 | R6: =ROUND(Q6*'Premissas'!$B$19+Q5*(1-'Premissas'!$B$19),2) -> 0 | S6: =ROUND(E6*'Premissas'!$B$17,2) -> 0 | T6: =ROUND(Q6*'Premissas'!$B$10,2) -> 0 | U6: =ROUND(R6*'Premissas'!$B$18,2) -> 0 | V6: =IF(A6<=12,'Premissas'!$B$24,'Premissas'!$B$25) -> 37000 | W6: =ROUND(G6+Q6,2) -> 0 | X6: =ROUND(I6+Q6,2) -> 0 | Y6: =ROUND(L6+R6,2) -> 0 | Z6: =ROUND(SUM(M6:P6)+SUM(S6:V6),2) -> 37000 | AA6: =ROUND(Y6-Z6,2) -> -37000 | AB6: =ROUND(AB5+AA6,2) -> -174000 | AC6: =ROUND(X6-J6-SUM(M6:P6)-S6-T6-ROUND(Q6*'Premissas'!$B$18,2)-V6,2) -> -37000 | AD6: =ROUND(SUM($K$5:K6)-SUM($L$5:L6)+SUM($Q$5:Q6)-SUM($R$5:R6),2) -> 0 | AE6: =MAX(0,AB6)*'Premissas'!$B$28 -> 0 | AF6: =IF(AB6>=0,A6,999) -> 999 | AG6: =IF(AE6>=Resumo!$E$6,A6,999) -> 999 | AH6: =AB6+Capital!$A$5 -> -74000 | AI6: =AB6+Capital!$A$6 -> -24000 | AJ6: =AB6+Capital!$A$7 -> 26000
A7: 3 | B7: 50 | C7: =ROUNDUP(B7/'Premissas'!$B$14,0) -> 2500 | D7: 1 | E7: =D7*'Premissas'!$B$16 -> 80 | F7: =ROUND(B7*'Premissas'!$B$5,2) -> 1450 | G7: =ROUND(F7*'Premissas'!$B$6,2) -> 7250 | H7: =ROUND(G7*'Premissas'!$B$7,2) -> 580 | I7: =ROUND(G7-H7,2) -> 6670 | J7: =ROUND(I7*'Premissas'!$B$8+B7*(1-'Premissas'!$B$7)*'Premissas'!$B$9*'Premissas'!$B$6,2) -> 890.33 | K7: =ROUND(I7-J7,2) -> 5779.67 | L7: =IF(A7>'Premissas'!$B$20,INDEX($K$5:$K$28,MAX(1,A7-'Premissas'!$B$20)),0) -> 0 | M7: =ROUND(I7*'Premissas'!$B$10,2) -> 1000.5 | N7: =ROUND(I7*'Premissas'!$B$11,2) -> 200.1 | O7: =ROUND(B7*'Premissas'!$B$12*'Premissas'!$B$6,2) -> 2500 | P7: =ROUND(B7*'Premissas'!$B$13*'Premissas'!$B$6,2) -> 250 | Q7: =ROUND(D7*'Premissas'!$B$15,2) -> 30000 | R7: =ROUND(Q7*'Premissas'!$B$19+Q6*(1-'Premissas'!$B$19),2) -> 15000 | S7: =ROUND(E7*'Premissas'!$B$17,2) -> 14400 | T7: =ROUND(Q7*'Premissas'!$B$10,2) -> 4500 | U7: =ROUND(R7*'Premissas'!$B$18,2) -> 750 | V7: =IF(A7<=12,'Premissas'!$B$24,'Premissas'!$B$25) -> 37000 | W7: =ROUND(G7+Q7,2) -> 37250 | X7: =ROUND(I7+Q7,2) -> 36670 | Y7: =ROUND(L7+R7,2) -> 15000 | Z7: =ROUND(SUM(M7:P7)+SUM(S7:V7),2) -> 60600.6 | AA7: =ROUND(Y7-Z7,2) -> -45600.6 | AB7: =ROUND(AB6+AA7,2) -> -219600.6 | AC7: =ROUND(X7-J7-SUM(M7:P7)-S7-T7-ROUND(Q7*'Premissas'!$B$18,2)-V7,2) -> -25570.93 | AD7: =ROUND(SUM($K$5:K7)-SUM($L$5:L7)+SUM($Q$5:Q7)-SUM($R$5:R7),2) -> 20779.67 | AE7: =MAX(0,AB7)*'Premissas'!$B$28 -> 0 | AF7: =IF(AB7>=0,A7,999) -> 999 | AG7: =IF(AE7>=Resumo!$E$6,A7,999) -> 999 | AH7: =AB7+Capital!$A$5 -> -119600.6 | AI7: =AB7+Capital!$A$6 -> -69600.6 | AJ7: =AB7+Capital!$A$7 -> -19600.6
A8: 4 | B8: 150 | C8: =ROUNDUP(B8/'Premissas'!$B$14,0) -> 7500 | D8: 0 | E8: =D8*'Premissas'!$B$16 -> 0 | F8: =ROUND(B8*'Premissas'!$B$5,2) -> 4350 | G8: =ROUND(F8*'Premissas'!$B$6,2) -> 21750 | H8: =ROUND(G8*'Premissas'!$B$7,2) -> 1740 | I8: =ROUND(G8-H8,2) -> 20010 | J8: =ROUND(I8*'Premissas'!$B$8+B8*(1-'Premissas'!$B$7)*'Premissas'!$B$9*'Premissas'!$B$6,2) -> 2670.99 | K8: =ROUND(I8-J8,2) -> 17339.01 | L8: =IF(A8>'Premissas'!$B$20,INDEX($K$5:$K$28,MAX(1,A8-'Premissas'!$B$20)),0) -> 5779.67 | M8: =ROUND(I8*'Premissas'!$B$10,2) -> 3001.5 | N8: =ROUND(I8*'Premissas'!$B$11,2) -> 600.3 | O8: =ROUND(B8*'Premissas'!$B$12*'Premissas'!$B$6,2) -> 7500 | P8: =ROUND(B8*'Premissas'!$B$13*'Premissas'!$B$6,2) -> 750 | Q8: =ROUND(D8*'Premissas'!$B$15,2) -> 0 | R8: =ROUND(Q8*'Premissas'!$B$19+Q7*(1-'Premissas'!$B$19),2) -> 15000 | S8: =ROUND(E8*'Premissas'!$B$17,2) -> 0 | T8: =ROUND(Q8*'Premissas'!$B$10,2) -> 0 | U8: =ROUND(R8*'Premissas'!$B$18,2) -> 750 | V8: =IF(A8<=12,'Premissas'!$B$24,'Premissas'!$B$25) -> 37000 | W8: =ROUND(G8+Q8,2) -> 21750 | X8: =ROUND(I8+Q8,2) -> 20010 | Y8: =ROUND(L8+R8,2) -> 20779.67 | Z8: =ROUND(SUM(M8:P8)+SUM(S8:V8),2) -> 49601.8 | AA8: =ROUND(Y8-Z8,2) -> -28822.13 | AB8: =ROUND(AB7+AA8,2) -> -248422.73 | AC8: =ROUND(X8-J8-SUM(M8:P8)-S8-T8-ROUND(Q8*'Premissas'!$B$18,2)-V8,2) -> -31512.79 | AD8: =ROUND(SUM($K$5:K8)-SUM($L$5:L8)+SUM($Q$5:Q8)-SUM($R$5:R8),2) -> 17339.01 | AE8: =MAX(0,AB8)*'Premissas'!$B$28 -> 0 | AF8: =IF(AB8>=0,A8,999) -> 999 | AG8: =IF(AE8>=Resumo!$E$6,A8,999) -> 999 | AH8: =AB8+Capital!$A$5 -> -148422.73 | AI8: =AB8+Capital!$A$6 -> -98422.73 | AJ8: =AB8+Capital!$A$7 -> -48422.73
A9: 5 | B9: 300 | C9: =ROUNDUP(B9/'Premissas'!$B$14,0) -> 15000 | D9: 1 | E9: =D9*'Premissas'!$B$16 -> 80 | F9: =ROUND(B9*'Premissas'!$B$5,2) -> 8700 | G9: =ROUND(F9*'Premissas'!$B$6,2) -> 43500 | H9: =ROUND(G9*'Premissas'!$B$7,2) -> 3480 | I9: =ROUND(G9-H9,2) -> 40020 | J9: =ROUND(I9*'Premissas'!$B$8+B9*(1-'Premissas'!$B$7)*'Premissas'!$B$9*'Premissas'!$B$6,2) -> 5341.98 | K9: =ROUND(I9-J9,2) -> 34678.02 | L9: =IF(A9>'Premissas'!$B$20,INDEX($K$5:$K$28,MAX(1,A9-'Premissas'!$B$20)),0) -> 17339.01 | M9: =ROUND(I9*'Premissas'!$B$10,2) -> 6003 | N9: =ROUND(I9*'Premissas'!$B$11,2) -> 1200.6 | O9: =ROUND(B9*'Premissas'!$B$12*'Premissas'!$B$6,2) -> 15000 | P9: =ROUND(B9*'Premissas'!$B$13*'Premissas'!$B$6,2) -> 1500 | Q9: =ROUND(D9*'Premissas'!$B$15,2) -> 30000 | R9: =ROUND(Q9*'Premissas'!$B$19+Q8*(1-'Premissas'!$B$19),2) -> 15000 | S9: =ROUND(E9*'Premissas'!$B$17,2) -> 14400 | T9: =ROUND(Q9*'Premissas'!$B$10,2) -> 4500 | U9: =ROUND(R9*'Premissas'!$B$18,2) -> 750 | V9: =IF(A9<=12,'Premissas'!$B$24,'Premissas'!$B$25) -> 37000 | W9: =ROUND(G9+Q9,2) -> 73500 | X9: =ROUND(I9+Q9,2) -> 70020 | Y9: =ROUND(L9+R9,2) -> 32339.01 | Z9: =ROUND(SUM(M9:P9)+SUM(S9:V9),2) -> 80353.6 | AA9: =ROUND(Y9-Z9,2) -> -48014.59 | AB9: =ROUND(AB8+AA9,2) -> -296437.32 | AC9: =ROUND(X9-J9-SUM(M9:P9)-S9-T9-ROUND(Q9*'Premissas'!$B$18,2)-V9,2) -> -16425.58 | AD9: =ROUND(SUM($K$5:K9)-SUM($L$5:L9)+SUM($Q$5:Q9)-SUM($R$5:R9),2) -> 49678.02 | AE9: =MAX(0,AB9)*'Premissas'!$B$28 -> 0 | AF9: =IF(AB9>=0,A9,999) -> 999 | AG9: =IF(AE9>=Resumo!$E$6,A9,999) -> 999 | AH9: =AB9+Capital!$A$5 -> -196437.32 | AI9: =AB9+Capital!$A$6 -> -146437.32 | AJ9: =AB9+Capital!$A$7 -> -96437.32
A10: 6 | B10: 500 | C10: =ROUNDUP(B10/'Premissas'!$B$14,0) -> 25000 | D10: 0 | E10: =D10*'Premissas'!$B$16 -> 0 | F10: =ROUND(B10*'Premissas'!$B$5,2) -> 14500 | G10: =ROUND(F10*'Premissas'!$B$6,2) -> 72500 | H10: =ROUND(G10*'Premissas'!$B$7,2) -> 5800 | I10: =ROUND(G10-H10,2) -> 66700 | J10: =ROUND(I10*'Premissas'!$B$8+B10*(1-'Premissas'!$B$7)*'Premissas'!$B$9*'Premissas'!$B$6,2) -> 8903.3 | K10: =ROUND(I10-J10,2) -> 57796.7 | L10: =IF(A10>'Premissas'!$B$20,INDEX($K$5:$K$28,MAX(1,A10-'Premissas'!$B$20)),0) -> 34678.02 | M10: =ROUND(I10*'Premissas'!$B$10,2) -> 10005 | N10: =ROUND(I10*'Premissas'!$B$11,2) -> 2001 | O10: =ROUND(B10*'Premissas'!$B$12*'Premissas'!$B$6,2) -> 25000 | P10: =ROUND(B10*'Premissas'!$B$13*'Premissas'!$B$6,2) -> 2500 | Q10: =ROUND(D10*'Premissas'!$B$15,2) -> 0 | R10: =ROUND(Q10*'Premissas'!$B$19+Q9*(1-'Premissas'!$B$19),2) -> 15000 | S10: =ROUND(E10*'Premissas'!$B$17,2) -> 0 | T10: =ROUND(Q10*'Premissas'!$B$10,2) -> 0 | U10: =ROUND(R10*'Premissas'!$B$18,2) -> 750 | V10: =IF(A10<=12,'Premissas'!$B$24,'Premissas'!$B$25) -> 37000 | W10: =ROUND(G10+Q10,2) -> 72500 | X10: =ROUND(I10+Q10,2) -> 66700 | Y10: =ROUND(L10+R10,2) -> 49678.02 | Z10: =ROUND(SUM(M10:P10)+SUM(S10:V10),2) -> 77256 | AA10: =ROUND(Y10-Z10,2) -> -27577.98 | AB10: =ROUND(AB9+AA10,2) -> -324015.3 | AC10: =ROUND(X10-J10-SUM(M10:P10)-S10-T10-ROUND(Q10*'Premissas'!$B$18,2)-V10,2) -> -18709.3 | AD10: =ROUND(SUM($K$5:K10)-SUM($L$5:L10)+SUM($Q$5:Q10)-SUM($R$5:R10),2) -> 57796.7 | AE10: =MAX(0,AB10)*'Premissas'!$B$28 -> 0 | AF10: =IF(AB10>=0,A10,999) -> 999 | AG10: =IF(AE10>=Resumo!$E$6,A10,999) -> 999 | AH10: =AB10+Capital!$A$5 -> -224015.3 | AI10: =AB10+Capital!$A$6 -> -174015.3 | AJ10: =AB10+Capital!$A$7 -> -124015.3
A11: 7 | B11: 750 | C11: =ROUNDUP(B11/'Premissas'!$B$14,0) -> 37500 | D11: 1 | E11: =D11*'Premissas'!$B$16 -> 80 | F11: =ROUND(B11*'Premissas'!$B$5,2) -> 21750 | G11: =ROUND(F11*'Premissas'!$B$6,2) -> 108750 | H11: =ROUND(G11*'Premissas'!$B$7,2) -> 8700 | I11: =ROUND(G11-H11,2) -> 100050 | J11: =ROUND(I11*'Premissas'!$B$8+B11*(1-'Premissas'!$B$7)*'Premissas'!$B$9*'Premissas'!$B$6,2) -> 13354.95 | K11: =ROUND(I11-J11,2) -> 86695.05 | L11: =IF(A11>'Premissas'!$B$20,INDEX($K$5:$K$28,MAX(1,A11-'Premissas'!$B$20)),0) -> 57796.7 | M11: =ROUND(I11*'Premissas'!$B$10,2) -> 15007.5 | N11: =ROUND(I11*'Premissas'!$B$11,2) -> 3001.5 | O11: =ROUND(B11*'Premissas'!$B$12*'Premissas'!$B$6,2) -> 37500 | P11: =ROUND(B11*'Premissas'!$B$13*'Premissas'!$B$6,2) -> 3750 | Q11: =ROUND(D11*'Premissas'!$B$15,2) -> 30000 | R11: =ROUND(Q11*'Premissas'!$B$19+Q10*(1-'Premissas'!$B$19),2) -> 15000 | S11: =ROUND(E11*'Premissas'!$B$17,2) -> 14400 | T11: =ROUND(Q11*'Premissas'!$B$10,2) -> 4500 | U11: =ROUND(R11*'Premissas'!$B$18,2) -> 750 | V11: =IF(A11<=12,'Premissas'!$B$24,'Premissas'!$B$25) -> 37000 | W11: =ROUND(G11+Q11,2) -> 138750 | X11: =ROUND(I11+Q11,2) -> 130050 | Y11: =ROUND(L11+R11,2) -> 72796.7 | Z11: =ROUND(SUM(M11:P11)+SUM(S11:V11),2) -> 115909 | AA11: =ROUND(Y11-Z11,2) -> -43112.3 | AB11: =ROUND(AB10+AA11,2) -> -367127.6 | AC11: =ROUND(X11-J11-SUM(M11:P11)-S11-T11-ROUND(Q11*'Premissas'!$B$18,2)-V11,2) -> 36.05 | AD11: =ROUND(SUM($K$5:K11)-SUM($L$5:L11)+SUM($Q$5:Q11)-SUM($R$5:R11),2) -> 101695.05 | AE11: =MAX(0,AB11)*'Premissas'!$B$28 -> 0 | AF11: =IF(AB11>=0,A11,999) -> 999 | AG11: =IF(AE11>=Resumo!$E$6,A11,999) -> 999 | AH11: =AB11+Capital!$A$5 -> -267127.6 | AI11: =AB11+Capital!$A$6 -> -217127.6 | AJ11: =AB11+Capital!$A$7 -> -167127.6
A12: 8 | B12: 1000 | C12: =ROUNDUP(B12/'Premissas'!$B$14,0) -> 50000 | D12: 1 | E12: =D12*'Premissas'!$B$16 -> 80 | F12: =ROUND(B12*'Premissas'!$B$5,2) -> 29000 | G12: =ROUND(F12*'Premissas'!$B$6,2) -> 145000 | H12: =ROUND(G12*'Premissas'!$B$7,2) -> 11600 | I12: =ROUND(G12-H12,2) -> 133400 | J12: =ROUND(I12*'Premissas'!$B$8+B12*(1-'Premissas'!$B$7)*'Premissas'!$B$9*'Premissas'!$B$6,2) -> 17806.6 | K12: =ROUND(I12-J12,2) -> 115593.4 | L12: =IF(A12>'Premissas'!$B$20,INDEX($K$5:$K$28,MAX(1,A12-'Premissas'!$B$20)),0) -> 86695.05 | M12: =ROUND(I12*'Premissas'!$B$10,2) -> 20010 | N12: =ROUND(I12*'Premissas'!$B$11,2) -> 4002 | O12: =ROUND(B12*'Premissas'!$B$12*'Premissas'!$B$6,2) -> 50000 | P12: =ROUND(B12*'Premissas'!$B$13*'Premissas'!$B$6,2) -> 5000 | Q12: =ROUND(D12*'Premissas'!$B$15,2) -> 30000 | R12: =ROUND(Q12*'Premissas'!$B$19+Q11*(1-'Premissas'!$B$19),2) -> 30000 | S12: =ROUND(E12*'Premissas'!$B$17,2) -> 14400 | T12: =ROUND(Q12*'Premissas'!$B$10,2) -> 4500 | U12: =ROUND(R12*'Premissas'!$B$18,2) -> 1500 | V12: =IF(A12<=12,'Premissas'!$B$24,'Premissas'!$B$25) -> 37000 | W12: =ROUND(G12+Q12,2) -> 175000 | X12: =ROUND(I12+Q12,2) -> 163400 | Y12: =ROUND(L12+R12,2) -> 116695.05 | Z12: =ROUND(SUM(M12:P12)+SUM(S12:V12),2) -> 136412 | AA12: =ROUND(Y12-Z12,2) -> -19716.95 | AB12: =ROUND(AB11+AA12,2) -> -386844.55 | AC12: =ROUND(X12-J12-SUM(M12:P12)-S12-T12-ROUND(Q12*'Premissas'!$B$18,2)-V12,2) -> 9181.4 | AD12: =ROUND(SUM($K$5:K12)-SUM($L$5:L12)+SUM($Q$5:Q12)-SUM($R$5:R12),2) -> 130593.4 | AE12: =MAX(0,AB12)*'Premissas'!$B$28 -> 0 | AF12: =IF(AB12>=0,A12,999) -> 999 | AG12: =IF(AE12>=Resumo!$E$6,A12,999) -> 999 | AH12: =AB12+Capital!$A$5 -> -286844.55 | AI12: =AB12+Capital!$A$6 -> -236844.55 | AJ12: =AB12+Capital!$A$7 -> -186844.55
A13: 9 | B13: 1250 | C13: =ROUNDUP(B13/'Premissas'!$B$14,0) -> 62500 | D13: 1 | E13: =D13*'Premissas'!$B$16 -> 80 | F13: =ROUND(B13*'Premissas'!$B$5,2) -> 36250 | G13: =ROUND(F13*'Premissas'!$B$6,2) -> 181250 | H13: =ROUND(G13*'Premissas'!$B$7,2) -> 14500 | I13: =ROUND(G13-H13,2) -> 166750 | J13: =ROUND(I13*'Premissas'!$B$8+B13*(1-'Premissas'!$B$7)*'Premissas'!$B$9*'Premissas'!$B$6,2) -> 22258.25 | K13: =ROUND(I13-J13,2) -> 144491.75 | L13: =IF(A13>'Premissas'!$B$20,INDEX($K$5:$K$28,MAX(1,A13-'Premissas'!$B$20)),0) -> 115593.4 | M13: =ROUND(I13*'Premissas'!$B$10,2) -> 25012.5 | N13: =ROUND(I13*'Premissas'!$B$11,2) -> 5002.5 | O13: =ROUND(B13*'Premissas'!$B$12*'Premissas'!$B$6,2) -> 62500 | P13: =ROUND(B13*'Premissas'!$B$13*'Premissas'!$B$6,2) -> 6250 | Q13: =ROUND(D13*'Premissas'!$B$15,2) -> 30000 | R13: =ROUND(Q13*'Premissas'!$B$19+Q12*(1-'Premissas'!$B$19),2) -> 30000 | S13: =ROUND(E13*'Premissas'!$B$17,2) -> 14400 | T13: =ROUND(Q13*'Premissas'!$B$10,2) -> 4500 | U13: =ROUND(R13*'Premissas'!$B$18,2) -> 1500 | V13: =IF(A13<=12,'Premissas'!$B$24,'Premissas'!$B$25) -> 37000 | W13: =ROUND(G13+Q13,2) -> 211250 | X13: =ROUND(I13+Q13,2) -> 196750 | Y13: =ROUND(L13+R13,2) -> 145593.4 | Z13: =ROUND(SUM(M13:P13)+SUM(S13:V13),2) -> 156165 | AA13: =ROUND(Y13-Z13,2) -> -10571.6 | AB13: =ROUND(AB12+AA13,2) -> -397416.15 | AC13: =ROUND(X13-J13-SUM(M13:P13)-S13-T13-ROUND(Q13*'Premissas'!$B$18,2)-V13,2) -> 18326.75 | AD13: =ROUND(SUM($K$5:K13)-SUM($L$5:L13)+SUM($Q$5:Q13)-SUM($R$5:R13),2) -> 159491.75 | AE13: =MAX(0,AB13)*'Premissas'!$B$28 -> 0 | AF13: =IF(AB13>=0,A13,999) -> 999 | AG13: =IF(AE13>=Resumo!$E$6,A13,999) -> 999 | AH13: =AB13+Capital!$A$5 -> -297416.15 | AI13: =AB13+Capital!$A$6 -> -247416.15 | AJ13: =AB13+Capital!$A$7 -> -197416.15
A14: 10 | B14: 1500 | C14: =ROUNDUP(B14/'Premissas'!$B$14,0) -> 75000 | D14: 1 | E14: =D14*'Premissas'!$B$16 -> 80 | F14: =ROUND(B14*'Premissas'!$B$5,2) -> 43500 | G14: =ROUND(F14*'Premissas'!$B$6,2) -> 217500 | H14: =ROUND(G14*'Premissas'!$B$7,2) -> 17400 | I14: =ROUND(G14-H14,2) -> 200100 | J14: =ROUND(I14*'Premissas'!$B$8+B14*(1-'Premissas'!$B$7)*'Premissas'!$B$9*'Premissas'!$B$6,2) -> 26709.9 | K14: =ROUND(I14-J14,2) -> 173390.1 | L14: =IF(A14>'Premissas'!$B$20,INDEX($K$5:$K$28,MAX(1,A14-'Premissas'!$B$20)),0) -> 144491.75 | M14: =ROUND(I14*'Premissas'!$B$10,2) -> 30015 | N14: =ROUND(I14*'Premissas'!$B$11,2) -> 6003 | O14: =ROUND(B14*'Premissas'!$B$12*'Premissas'!$B$6,2) -> 75000 | P14: =ROUND(B14*'Premissas'!$B$13*'Premissas'!$B$6,2) -> 7500 | Q14: =ROUND(D14*'Premissas'!$B$15,2) -> 30000 | R14: =ROUND(Q14*'Premissas'!$B$19+Q13*(1-'Premissas'!$B$19),2) -> 30000 | S14: =ROUND(E14*'Premissas'!$B$17,2) -> 14400 | T14: =ROUND(Q14*'Premissas'!$B$10,2) -> 4500 | U14: =ROUND(R14*'Premissas'!$B$18,2) -> 1500 | V14: =IF(A14<=12,'Premissas'!$B$24,'Premissas'!$B$25) -> 37000 | W14: =ROUND(G14+Q14,2) -> 247500 | X14: =ROUND(I14+Q14,2) -> 230100 | Y14: =ROUND(L14+R14,2) -> 174491.75 | Z14: =ROUND(SUM(M14:P14)+SUM(S14:V14),2) -> 175918 | AA14: =ROUND(Y14-Z14,2) -> -1426.25 | AB14: =ROUND(AB13+AA14,2) -> -398842.4 | AC14: =ROUND(X14-J14-SUM(M14:P14)-S14-T14-ROUND(Q14*'Premissas'!$B$18,2)-V14,2) -> 27472.1 | AD14: =ROUND(SUM($K$5:K14)-SUM($L$5:L14)+SUM($Q$5:Q14)-SUM($R$5:R14),2) -> 188390.1 | AE14: =MAX(0,AB14)*'Premissas'!$B$28 -> 0 | AF14: =IF(AB14>=0,A14,999) -> 999 | AG14: =IF(AE14>=Resumo!$E$6,A14,999) -> 999 | AH14: =AB14+Capital!$A$5 -> -298842.4 | AI14: =AB14+Capital!$A$6 -> -248842.4 | AJ14: =AB14+Capital!$A$7 -> -198842.4
A15: 11 | B15: 1750 | C15: =ROUNDUP(B15/'Premissas'!$B$14,0) -> 87500 | D15: 1 | E15: =D15*'Premissas'!$B$16 -> 80 | F15: =ROUND(B15*'Premissas'!$B$5,2) -> 50750 | G15: =ROUND(F15*'Premissas'!$B$6,2) -> 253750 | H15: =ROUND(G15*'Premissas'!$B$7,2) -> 20300 | I15: =ROUND(G15-H15,2) -> 233450 | J15: =ROUND(I15*'Premissas'!$B$8+B15*(1-'Premissas'!$B$7)*'Premissas'!$B$9*'Premissas'!$B$6,2) -> 31161.55 | K15: =ROUND(I15-J15,2) -> 202288.45 | L15: =IF(A15>'Premissas'!$B$20,INDEX($K$5:$K$28,MAX(1,A15-'Premissas'!$B$20)),0) -> 173390.1 | M15: =ROUND(I15*'Premissas'!$B$10,2) -> 35017.5 | N15: =ROUND(I15*'Premissas'!$B$11,2) -> 7003.5 | O15: =ROUND(B15*'Premissas'!$B$12*'Premissas'!$B$6,2) -> 87500 | P15: =ROUND(B15*'Premissas'!$B$13*'Premissas'!$B$6,2) -> 8750 | Q15: =ROUND(D15*'Premissas'!$B$15,2) -> 30000 | R15: =ROUND(Q15*'Premissas'!$B$19+Q14*(1-'Premissas'!$B$19),2) -> 30000 | S15: =ROUND(E15*'Premissas'!$B$17,2) -> 14400 | T15: =ROUND(Q15*'Premissas'!$B$10,2) -> 4500 | U15: =ROUND(R15*'Premissas'!$B$18,2) -> 1500 | V15: =IF(A15<=12,'Premissas'!$B$24,'Premissas'!$B$25) -> 37000 | W15: =ROUND(G15+Q15,2) -> 283750 | X15: =ROUND(I15+Q15,2) -> 263450 | Y15: =ROUND(L15+R15,2) -> 203390.1 | Z15: =ROUND(SUM(M15:P15)+SUM(S15:V15),2) -> 195671 | AA15: =ROUND(Y15-Z15,2) -> 7719.1 | AB15: =ROUND(AB14+AA15,2) -> -391123.3 | AC15: =ROUND(X15-J15-SUM(M15:P15)-S15-T15-ROUND(Q15*'Premissas'!$B$18,2)-V15,2) -> 36617.45 | AD15: =ROUND(SUM($K$5:K15)-SUM($L$5:L15)+SUM($Q$5:Q15)-SUM($R$5:R15),2) -> 217288.45 | AE15: =MAX(0,AB15)*'Premissas'!$B$28 -> 0 | AF15: =IF(AB15>=0,A15,999) -> 999 | AG15: =IF(AE15>=Resumo!$E$6,A15,999) -> 999 | AH15: =AB15+Capital!$A$5 -> -291123.3 | AI15: =AB15+Capital!$A$6 -> -241123.3 | AJ15: =AB15+Capital!$A$7 -> -191123.3
A16: 12 | B16: 2000 | C16: =ROUNDUP(B16/'Premissas'!$B$14,0) -> 100000 | D16: 1 | E16: =D16*'Premissas'!$B$16 -> 80 | F16: =ROUND(B16*'Premissas'!$B$5,2) -> 58000 | G16: =ROUND(F16*'Premissas'!$B$6,2) -> 290000 | H16: =ROUND(G16*'Premissas'!$B$7,2) -> 23200 | I16: =ROUND(G16-H16,2) -> 266800 | J16: =ROUND(I16*'Premissas'!$B$8+B16*(1-'Premissas'!$B$7)*'Premissas'!$B$9*'Premissas'!$B$6,2) -> 35613.2 | K16: =ROUND(I16-J16,2) -> 231186.8 | L16: =IF(A16>'Premissas'!$B$20,INDEX($K$5:$K$28,MAX(1,A16-'Premissas'!$B$20)),0) -> 202288.45 | M16: =ROUND(I16*'Premissas'!$B$10,2) -> 40020 | N16: =ROUND(I16*'Premissas'!$B$11,2) -> 8004 | O16: =ROUND(B16*'Premissas'!$B$12*'Premissas'!$B$6,2) -> 100000 | P16: =ROUND(B16*'Premissas'!$B$13*'Premissas'!$B$6,2) -> 10000 | Q16: =ROUND(D16*'Premissas'!$B$15,2) -> 30000 | R16: =ROUND(Q16*'Premissas'!$B$19+Q15*(1-'Premissas'!$B$19),2) -> 30000 | S16: =ROUND(E16*'Premissas'!$B$17,2) -> 14400 | T16: =ROUND(Q16*'Premissas'!$B$10,2) -> 4500 | U16: =ROUND(R16*'Premissas'!$B$18,2) -> 1500 | V16: =IF(A16<=12,'Premissas'!$B$24,'Premissas'!$B$25) -> 37000 | W16: =ROUND(G16+Q16,2) -> 320000 | X16: =ROUND(I16+Q16,2) -> 296800 | Y16: =ROUND(L16+R16,2) -> 232288.45 | Z16: =ROUND(SUM(M16:P16)+SUM(S16:V16),2) -> 215424 | AA16: =ROUND(Y16-Z16,2) -> 16864.45 | AB16: =ROUND(AB15+AA16,2) -> -374258.85 | AC16: =ROUND(X16-J16-SUM(M16:P16)-S16-T16-ROUND(Q16*'Premissas'!$B$18,2)-V16,2) -> 45762.8 | AD16: =ROUND(SUM($K$5:K16)-SUM($L$5:L16)+SUM($Q$5:Q16)-SUM($R$5:R16),2) -> 246186.8 | AE16: =MAX(0,AB16)*'Premissas'!$B$28 -> 0 | AF16: =IF(AB16>=0,A16,999) -> 999 | AG16: =IF(AE16>=Resumo!$E$6,A16,999) -> 999 | AH16: =AB16+Capital!$A$5 -> -274258.85 | AI16: =AB16+Capital!$A$6 -> -224258.85 | AJ16: =AB16+Capital!$A$7 -> -174258.85
A17: 13 | B17: 2200 | C17: =ROUNDUP(B17/'Premissas'!$B$14,0) -> 110000 | D17: 2 | E17: =D17*'Premissas'!$B$16 -> 160 | F17: =ROUND(B17*'Premissas'!$B$5,2) -> 63800 | G17: =ROUND(F17*'Premissas'!$B$6,2) -> 319000 | H17: =ROUND(G17*'Premissas'!$B$7,2) -> 25520 | I17: =ROUND(G17-H17,2) -> 293480 | J17: =ROUND(I17*'Premissas'!$B$8+B17*(1-'Premissas'!$B$7)*'Premissas'!$B$9*'Premissas'!$B$6,2) -> 39174.52 | K17: =ROUND(I17-J17,2) -> 254305.48 | L17: =IF(A17>'Premissas'!$B$20,INDEX($K$5:$K$28,MAX(1,A17-'Premissas'!$B$20)),0) -> 231186.8 | M17: =ROUND(I17*'Premissas'!$B$10,2) -> 44022 | N17: =ROUND(I17*'Premissas'!$B$11,2) -> 8804.4 | O17: =ROUND(B17*'Premissas'!$B$12*'Premissas'!$B$6,2) -> 110000 | P17: =ROUND(B17*'Premissas'!$B$13*'Premissas'!$B$6,2) -> 11000 | Q17: =ROUND(D17*'Premissas'!$B$15,2) -> 60000 | R17: =ROUND(Q17*'Premissas'!$B$19+Q16*(1-'Premissas'!$B$19),2) -> 45000 | S17: =ROUND(E17*'Premissas'!$B$17,2) -> 28800 | T17: =ROUND(Q17*'Premissas'!$B$10,2) -> 9000 | U17: =ROUND(R17*'Premissas'!$B$18,2) -> 2250 | V17: =IF(A17<=12,'Premissas'!$B$24,'Premissas'!$B$25) -> 42000 | W17: =ROUND(G17+Q17,2) -> 379000 | X17: =ROUND(I17+Q17,2) -> 353480 | Y17: =ROUND(L17+R17,2) -> 276186.8 | Z17: =ROUND(SUM(M17:P17)+SUM(S17:V17),2) -> 255876.4 | AA17: =ROUND(Y17-Z17,2) -> 20310.4 | AB17: =ROUND(AB16+AA17,2) -> -353948.45 | AC17: =ROUND(X17-J17-SUM(M17:P17)-S17-T17-ROUND(Q17*'Premissas'!$B$18,2)-V17,2) -> 57679.08 | AD17: =ROUND(SUM($K$5:K17)-SUM($L$5:L17)+SUM($Q$5:Q17)-SUM($R$5:R17),2) -> 284305.48 | AE17: =MAX(0,AB17)*'Premissas'!$B$28 -> 0 | AF17: =IF(AB17>=0,A17,999) -> 999 | AG17: =IF(AE17>=Resumo!$E$6,A17,999) -> 999 | AH17: =AB17+Capital!$A$5 -> -253948.45 | AI17: =AB17+Capital!$A$6 -> -203948.45 | AJ17: =AB17+Capital!$A$7 -> -153948.45
... A28: 24 | B28: 3000 | C28: =ROUNDUP(B28/'Premissas'!$B$14,0) -> 150000 | D28: 2 | E28: =D28*'Premissas'!$B$16 -> 160 | F28: =ROUND(B28*'Premissas'!$B$5,2) -> 87000 | G28: =ROUND(F28*'Premissas'!$B$6,2) -> 435000 | H28: =ROUND(G28*'Premissas'!$B$7,2) -> 34800 | I28: =ROUND(G28-H28,2) -> 400200 | J28: =ROUND(I28*'Premissas'!$B$8+B28*(1-'Premissas'!$B$7)*'Premissas'!$B$9*'Premissas'!$B$6,2) -> 53419.8 | K28: =ROUND(I28-J28,2) -> 346780.2 | L28: =IF(A28>'Premissas'!$B$20,INDEX($K$5:$K$28,MAX(1,A28-'Premissas'!$B$20)),0) -> 346780.2 | M28: =ROUND(I28*'Premissas'!$B$10,2) -> 60030 | N28: =ROUND(I28*'Premissas'!$B$11,2) -> 12006 | O28: =ROUND(B28*'Premissas'!$B$12*'Premissas'!$B$6,2) -> 150000 | P28: =ROUND(B28*'Premissas'!$B$13*'Premissas'!$B$6,2) -> 15000 | Q28: =ROUND(D28*'Premissas'!$B$15,2) -> 60000 | R28: =ROUND(Q28*'Premissas'!$B$19+Q27*(1-'Premissas'!$B$19),2) -> 60000 | S28: =ROUND(E28*'Premissas'!$B$17,2) -> 28800 | T28: =ROUND(Q28*'Premissas'!$B$10,2) -> 9000 | U28: =ROUND(R28*'Premissas'!$B$18,2) -> 3000 | V28: =IF(A28<=12,'Premissas'!$B$24,'Premissas'!$B$25) -> 42000 | W28: =ROUND(G28+Q28,2) -> 495000 | X28: =ROUND(I28+Q28,2) -> 460200 | Y28: =ROUND(L28+R28,2) -> 406780.2 | Z28: =ROUND(SUM(M28:P28)+SUM(S28:V28),2) -> 319836 | AA28: =ROUND(Y28-Z28,2) -> 86944.2 | AB28: =ROUND(AB27+AA28,2) -> 466065.35 | AC28: =ROUND(X28-J28-SUM(M28:P28)-S28-T28-ROUND(Q28*'Premissas'!$B$18,2)-V28,2) -> 86944.2 | AD28: =ROUND(SUM($K$5:K28)-SUM($L$5:L28)+SUM($Q$5:Q28)-SUM($R$5:R28),2) -> 376780.2 | AE28: =MAX(0,AB28)*'Premissas'!$B$28 -> 233032.67 | AF28: =IF(AB28>=0,A28,999) -> 24 | AG28: =IF(AE28>=Resumo!$E$6,A28,999) -> 999 | AH28: =AB28+Capital!$A$5 -> 566065.35 | AI28: =AB28+Capital!$A$6 -> 616065.35 | AJ28: =AB28+Capital!$A$7 -> 666065.35

Sheet Escala24
A1: Escala24 | fluxo mensal em BRL, salvo indicação
A2: Agenda editável em azul. Cenário hipotético; não previsão. | M0 separado: -R$100 mil nas premissas. Acumulado exclui aportes/distribuição.
A4: Mês | B4: Pedidos aprovados | C4: Visitas qualificadas | D4: Mapas faturados | E4: Horas diretas TI | F4: Loja bruta USD | G4: Loja bruta BRL | H4: Estornos BRL | I4: Loja após estornos BRL | J4: Taxa plataforma BRL | K4: Liquidação gerada BRL | L4: Loja recebida BRL | M4: Tributos loja BRL | N4: Reserva meios/FX BRL | O4: Aquisição / mídia BRL | P4: Suporte loja BRL | Q4: Fatura TI BRL | R4: Recebimentos TI BRL | S4: Entrega TI BRL | T4: Tributos TI BRL | U4: Comercial TI caixa BRL | V4: Fixo BRL | W4: Vendas brutas BRL | X4: Receita após estornos BRL | Y4: Recebimentos BRL | Z4: Saídas caixa BRL | AA4: Fluxo líquido BRL | AB4: Acumulado sem aporte BRL | AC4: Resultado competência BRL | AD4: A receber BRL | AE4: 50% excedente positivo BRL | AF4: Mês elegível payback projeto | AG4: Mês elegível Dani hipotético | AH4: Saldo com 100k | AI4: Saldo com 150k | AJ4: Saldo com 200k
A5: 1 | B5: 0 | C5: =ROUNDUP(B5/'Premissas'!$B$14,0) -> 0 | D5: 0 | E5: =D5*'Premissas'!$B$16 -> 0 | F5: =ROUND(B5*'Premissas'!$B$5,2) -> 0 | G5: =ROUND(F5*'Premissas'!$B$6,2) -> 0 | H5: =ROUND(G5*'Premissas'!$B$7,2) -> 0 | I5: =ROUND(G5-H5,2) -> 0 | J5: =ROUND(I5*'Premissas'!$B$8+B5*(1-'Premissas'!$B$7)*'Premissas'!$B$9*'Premissas'!$B$6,2) -> 0 | K5: =ROUND(I5-J5,2) -> 0 | L5: =IF(A5>'Premissas'!$B$20,INDEX($K$5:$K$28,MAX(1,A5-'Premissas'!$B$20)),0) -> 0 | M5: =ROUND(I5*'Premissas'!$B$10,2) -> 0 | N5: =ROUND(I5*'Premissas'!$B$11,2) -> 0 | O5: =ROUND(B5*'Premissas'!$B$12*'Premissas'!$B$6,2) -> 0 | P5: =ROUND(B5*'Premissas'!$B$13*'Premissas'!$B$6,2) -> 0 | Q5: =ROUND(D5*'Premissas'!$B$15,2) -> 0 | R5: =ROUND(Q5*'Premissas'!$B$19+0*(1-'Premissas'!$B$19),2) -> 0 | S5: =ROUND(E5*'Premissas'!$B$17,2) -> 0 | T5: =ROUND(Q5*'Premissas'!$B$10,2) -> 0 | U5: =ROUND(R5*'Premissas'!$B$18,2) -> 0 | V5: =IF(A5<=12,'Premissas'!$B$24,'Premissas'!$B$25) -> 37000 | W5: =ROUND(G5+Q5,2) -> 0 | X5: =ROUND(I5+Q5,2) -> 0 | Y5: =ROUND(L5+R5,2) -> 0 | Z5: =ROUND(SUM(M5:P5)+SUM(S5:V5),2) -> 37000 | AA5: =ROUND(Y5-Z5,2) -> -37000 | AB5: =ROUND(-'Premissas'!$B$23+AA5,2) -> -137000 | AC5: =ROUND(X5-J5-SUM(M5:P5)-S5-T5-ROUND(Q5*'Premissas'!$B$18,2)-V5,2) -> -37000 | AD5: =ROUND(SUM($K$5:K5)-SUM($L$5:L5)+SUM($Q$5:Q5)-SUM($R$5:R5),2) -> 0 | AE5: =MAX(0,AB5)*'Premissas'!$B$28 -> 0 | AF5: =IF(AB5>=0,A5,999) -> 999 | AG5: =IF(AE5>=Resumo!$E$7,A5,999) -> 999 | AH5: =AB5+Capital!$A$5 -> -37000 | AI5: =AB5+Capital!$A$6 -> 13000 | AJ5: =AB5+Capital!$A$7 -> 63000
A6: 2 | B6: 0 | C6: =ROUNDUP(B6/'Premissas'!$B$14,0) -> 0 | D6: 0 | E6: =D6*'Premissas'!$B$16 -> 0 | F6: =ROUND(B6*'Premissas'!$B$5,2) -> 0 | G6: =ROUND(F6*'Premissas'!$B$6,2) -> 0 | H6: =ROUND(G6*'Premissas'!$B$7,2) -> 0 | I6: =ROUND(G6-H6,2) -> 0 | J6: =ROUND(I6*'Premissas'!$B$8+B6*(1-'Premissas'!$B$7)*'Premissas'!$B$9*'Premissas'!$B$6,2) -> 0 | K6: =ROUND(I6-J6,2) -> 0 | L6: =IF(A6>'Premissas'!$B$20,INDEX($K$5:$K$28,MAX(1,A6-'Premissas'!$B$20)),0) -> 0 | M6: =ROUND(I6*'Premissas'!$B$10,2) -> 0 | N6: =ROUND(I6*'Premissas'!$B$11,2) -> 0 | O6: =ROUND(B6*'Premissas'!$B$12*'Premissas'!$B$6,2) -> 0 | P6: =ROUND(B6*'Premissas'!$B$13*'Premissas'!$B$6,2) -> 0 | Q6: =ROUND(D6*'Premissas'!$B$15,2) -> 0 | R6: =ROUND(Q6*'Premissas'!$B$19+Q5*(1-'Premissas'!$B$19),2) -> 0 | S6: =ROUND(E6*'Premissas'!$B$17,2) -> 0 | T6: =ROUND(Q6*'Premissas'!$B$10,2) -> 0 | U6: =ROUND(R6*'Premissas'!$B$18,2) -> 0 | V6: =IF(A6<=12,'Premissas'!$B$24,'Premissas'!$B$25) -> 37000 | W6: =ROUND(G6+Q6,2) -> 0 | X6: =ROUND(I6+Q6,2) -> 0 | Y6: =ROUND(L6+R6,2) -> 0 | Z6: =ROUND(SUM(M6:P6)+SUM(S6:V6),2) -> 37000 | AA6: =ROUND(Y6-Z6,2) -> -37000 | AB6: =ROUND(AB5+AA6,2) -> -174000 | AC6: =ROUND(X6-J6-SUM(M6:P6)-S6-T6-ROUND(Q6*'Premissas'!$B$18,2)-V6,2) -> -37000 | AD6: =ROUND(SUM($K$5:K6)-SUM($L$5:L6)+SUM($Q$5:Q6)-SUM($R$5:R6),2) -> 0 | AE6: =MAX(0,AB6)*'Premissas'!$B$28 -> 0 | AF6: =IF(AB6>=0,A6,999) -> 999 | AG6: =IF(AE6>=Resumo!$E$7,A6,999) -> 999 | AH6: =AB6+Capital!$A$5 -> -74000 | AI6: =AB6+Capital!$A$6 -> -24000 | AJ6: =AB6+Capital!$A$7 -> 26000
A7: 3 | B7: 100 | C7: =ROUNDUP(B7/'Premissas'!$B$14,0) -> 5000 | D7: 1 | E7: =D7*'Premissas'!$B$16 -> 80 | F7: =ROUND(B7*'Premissas'!$B$5,2) -> 2900 | G7: =ROUND(F7*'Premissas'!$B$6,2) -> 14500 | H7: =ROUND(G7*'Premissas'!$B$7,2) -> 1160 | I7: =ROUND(G7-H7,2) -> 13340 | J7: =ROUND(I7*'Premissas'!$B$8+B7*(1-'Premissas'!$B$7)*'Premissas'!$B$9*'Premissas'!$B$6,2) -> 1780.66 | K7: =ROUND(I7-J7,2) -> 11559.34 | L7: =IF(A7>'Premissas'!$B$20,INDEX($K$5:$K$28,MAX(1,A7-'Premissas'!$B$20)),0) -> 0 | M7: =ROUND(I7*'Premissas'!$B$10,2) -> 2001 | N7: =ROUND(I7*'Premissas'!$B$11,2) -> 400.2 | O7: =ROUND(B7*'Premissas'!$B$12*'Premissas'!$B$6,2) -> 5000 | P7: =ROUND(B7*'Premissas'!$B$13*'Premissas'!$B$6,2) -> 500 | Q7: =ROUND(D7*'Premissas'!$B$15,2) -> 30000 | R7: =ROUND(Q7*'Premissas'!$B$19+Q6*(1-'Premissas'!$B$19),2) -> 15000 | S7: =ROUND(E7*'Premissas'!$B$17,2) -> 14400 | T7: =ROUND(Q7*'Premissas'!$B$10,2) -> 4500 | U7: =ROUND(R7*'Premissas'!$B$18,2) -> 750 | V7: =IF(A7<=12,'Premissas'!$B$24,'Premissas'!$B$25) -> 37000 | W7: =ROUND(G7+Q7,2) -> 44500 | X7: =ROUND(I7+Q7,2) -> 43340 | Y7: =ROUND(L7+R7,2) -> 15000 | Z7: =ROUND(SUM(M7:P7)+SUM(S7:V7),2) -> 64551.2 | AA7: =ROUND(Y7-Z7,2) -> -49551.2 | AB7: =ROUND(AB6+AA7,2) -> -223551.2 | AC7: =ROUND(X7-J7-SUM(M7:P7)-S7-T7-ROUND(Q7*'Premissas'!$B$18,2)-V7,2) -> -23741.86 | AD7: =ROUND(SUM($K$5:K7)-SUM($L$5:L7)+SUM($Q$5:Q7)-SUM($R$5:R7),2) -> 26559.34 | AE7: =MAX(0,AB7)*'Premissas'!$B$28 -> 0 | AF7: =IF(AB7>=0,A7,999) -> 999 | AG7: =IF(AE7>=Resumo!$E$7,A7,999) -> 999 | AH7: =AB7+Capital!$A$5 -> -123551.2 | AI7: =AB7+Capital!$A$6 -> -73551.2 | AJ7: =AB7+Capital!$A$7 -> -23551.2
A8: 4 | B8: 300 | C8: =ROUNDUP(B8/'Premissas'!$B$14,0) -> 15000 | D8: 1 | E8: =D8*'Premissas'!$B$16 -> 80 | F8: =ROUND(B8*'Premissas'!$B$5,2) -> 8700 | G8: =ROUND(F8*'Premissas'!$B$6,2) -> 43500 | H8: =ROUND(G8*'Premissas'!$B$7,2) -> 3480 | I8: =ROUND(G8-H8,2) -> 40020 | J8: =ROUND(I8*'Premissas'!$B$8+B8*(1-'Premissas'!$B$7)*'Premissas'!$B$9*'Premissas'!$B$6,2) -> 5341.98 | K8: =ROUND(I8-J8,2) -> 34678.02 | L8: =IF(A8>'Premissas'!$B$20,INDEX($K$5:$K$28,MAX(1,A8-'Premissas'!$B$20)),0) -> 11559.34 | M8: =ROUND(I8*'Premissas'!$B$10,2) -> 6003 | N8: =ROUND(I8*'Premissas'!$B$11,2) -> 1200.6 | O8: =ROUND(B8*'Premissas'!$B$12*'Premissas'!$B$6,2) -> 15000 | P8: =ROUND(B8*'Premissas'!$B$13*'Premissas'!$B$6,2) -> 1500 | Q8: =ROUND(D8*'Premissas'!$B$15,2) -> 30000 | R8: =ROUND(Q8*'Premissas'!$B$19+Q7*(1-'Premissas'!$B$19),2) -> 30000 | S8: =ROUND(E8*'Premissas'!$B$17,2) -> 14400 | T8: =ROUND(Q8*'Premissas'!$B$10,2) -> 4500 | U8: =ROUND(R8*'Premissas'!$B$18,2) -> 1500 | V8: =IF(A8<=12,'Premissas'!$B$24,'Premissas'!$B$25) -> 37000 | W8: =ROUND(G8+Q8,2) -> 73500 | X8: =ROUND(I8+Q8,2) -> 70020 | Y8: =ROUND(L8+R8,2) -> 41559.34 | Z8: =ROUND(SUM(M8:P8)+SUM(S8:V8),2) -> 81103.6 | AA8: =ROUND(Y8-Z8,2) -> -39544.26 | AB8: =ROUND(AB7+AA8,2) -> -263095.46 | AC8: =ROUND(X8-J8-SUM(M8:P8)-S8-T8-ROUND(Q8*'Premissas'!$B$18,2)-V8,2) -> -16425.58 | AD8: =ROUND(SUM($K$5:K8)-SUM($L$5:L8)+SUM($Q$5:Q8)-SUM($R$5:R8),2) -> 49678.02 | AE8: =MAX(0,AB8)*'Premissas'!$B$28 -> 0 | AF8: =IF(AB8>=0,A8,999) -> 999 | AG8: =IF(AE8>=Resumo!$E$7,A8,999) -> 999 | AH8: =AB8+Capital!$A$5 -> -163095.46 | AI8: =AB8+Capital!$A$6 -> -113095.46 | AJ8: =AB8+Capital!$A$7 -> -63095.46
A9: 5 | B9: 600 | C9: =ROUNDUP(B9/'Premissas'!$B$14,0) -> 30000 | D9: 1 | E9: =D9*'Premissas'!$B$16 -> 80 | F9: =ROUND(B9*'Premissas'!$B$5,2) -> 17400 | G9: =ROUND(F9*'Premissas'!$B$6,2) -> 87000 | H9: =ROUND(G9*'Premissas'!$B$7,2) -> 6960 | I9: =ROUND(G9-H9,2) -> 80040 | J9: =ROUND(I9*'Premissas'!$B$8+B9*(1-'Premissas'!$B$7)*'Premissas'!$B$9*'Premissas'!$B$6,2) -> 10683.96 | K9: =ROUND(I9-J9,2) -> 69356.04 | L9: =IF(A9>'Premissas'!$B$20,INDEX($K$5:$K$28,MAX(1,A9-'Premissas'!$B$20)),0) -> 34678.02 | M9: =ROUND(I9*'Premissas'!$B$10,2) -> 12006 | N9: =ROUND(I9*'Premissas'!$B$11,2) -> 2401.2 | O9: =ROUND(B9*'Premissas'!$B$12*'Premissas'!$B$6,2) -> 30000 | P9: =ROUND(B9*'Premissas'!$B$13*'Premissas'!$B$6,2) -> 3000 | Q9: =ROUND(D9*'Premissas'!$B$15,2) -> 30000 | R9: =ROUND(Q9*'Premissas'!$B$19+Q8*(1-'Premissas'!$B$19),2) -> 30000 | S9: =ROUND(E9*'Premissas'!$B$17,2) -> 14400 | T9: =ROUND(Q9*'Premissas'!$B$10,2) -> 4500 | U9: =ROUND(R9*'Premissas'!$B$18,2) -> 1500 | V9: =IF(A9<=12,'Premissas'!$B$24,'Premissas'!$B$25) -> 37000 | W9: =ROUND(G9+Q9,2) -> 117000 | X9: =ROUND(I9+Q9,2) -> 110040 | Y9: =ROUND(L9+R9,2) -> 64678.02 | Z9: =ROUND(SUM(M9:P9)+SUM(S9:V9),2) -> 104807.2 | AA9: =ROUND(Y9-Z9,2) -> -40129.18 | AB9: =ROUND(AB8+AA9,2) -> -303224.64 | AC9: =ROUND(X9-J9-SUM(M9:P9)-S9-T9-ROUND(Q9*'Premissas'!$B$18,2)-V9,2) -> -5451.16 | AD9: =ROUND(SUM($K$5:K9)-SUM($L$5:L9)+SUM($Q$5:Q9)-SUM($R$5:R9),2) -> 84356.04 | AE9: =MAX(0,AB9)*'Premissas'!$B$28 -> 0 | AF9: =IF(AB9>=0,A9,999) -> 999 | AG9: =IF(AE9>=Resumo!$E$7,A9,999) -> 999 | AH9: =AB9+Capital!$A$5 -> -203224.64 | AI9: =AB9+Capital!$A$6 -> -153224.64 | AJ9: =AB9+Capital!$A$7 -> -103224.64
A10: 6 | B10: 1000 | C10: =ROUNDUP(B10/'Premissas'!$B$14,0) -> 50000 | D10: 2 | E10: =D10*'Premissas'!$B$16 -> 160 | F10: =ROUND(B10*'Premissas'!$B$5,2) -> 29000 | G10: =ROUND(F10*'Premissas'!$B$6,2) -> 145000 | H10: =ROUND(G10*'Premissas'!$B$7,2) -> 11600 | I10: =ROUND(G10-H10,2) -> 133400 | J10: =ROUND(I10*'Premissas'!$B$8+B10*(1-'Premissas'!$B$7)*'Premissas'!$B$9*'Premissas'!$B$6,2) -> 17806.6 | K10: =ROUND(I10-J10,2) -> 115593.4 | L10: =IF(A10>'Premissas'!$B$20,INDEX($K$5:$K$28,MAX(1,A10-'Premissas'!$B$20)),0) -> 69356.04 | M10: =ROUND(I10*'Premissas'!$B$10,2) -> 20010 | N10: =ROUND(I10*'Premissas'!$B$11,2) -> 4002 | O10: =ROUND(B10*'Premissas'!$B$12*'Premissas'!$B$6,2) -> 50000 | P10: =ROUND(B10*'Premissas'!$B$13*'Premissas'!$B$6,2) -> 5000 | Q10: =ROUND(D10*'Premissas'!$B$15,2) -> 60000 | R10: =ROUND(Q10*'Premissas'!$B$19+Q9*(1-'Premissas'!$B$19),2) -> 45000 | S10: =ROUND(E10*'Premissas'!$B$17,2) -> 28800 | T10: =ROUND(Q10*'Premissas'!$B$10,2) -> 9000 | U10: =ROUND(R10*'Premissas'!$B$18,2) -> 2250 | V10: =IF(A10<=12,'Premissas'!$B$24,'Premissas'!$B$25) -> 37000 | W10: =ROUND(G10+Q10,2) -> 205000 | X10: =ROUND(I10+Q10,2) -> 193400 | Y10: =ROUND(L10+R10,2) -> 114356.04 | Z10: =ROUND(SUM(M10:P10)+SUM(S10:V10),2) -> 156062 | AA10: =ROUND(Y10-Z10,2) -> -41705.96 | AB10: =ROUND(AB9+AA10,2) -> -344930.6 | AC10: =ROUND(X10-J10-SUM(M10:P10)-S10-T10-ROUND(Q10*'Premissas'!$B$18,2)-V10,2) -> 18781.4 | AD10: =ROUND(SUM($K$5:K10)-SUM($L$5:L10)+SUM($Q$5:Q10)-SUM($R$5:R10),2) -> 145593.4 | AE10: =MAX(0,AB10)*'Premissas'!$B$28 -> 0 | AF10: =IF(AB10>=0,A10,999) -> 999 | AG10: =IF(AE10>=Resumo!$E$7,A10,999) -> 999 | AH10: =AB10+Capital!$A$5 -> -244930.6 | AI10: =AB10+Capital!$A$6 -> -194930.6 | AJ10: =AB10+Capital!$A$7 -> -144930.6
A11: 7 | B11: 1500 | C11: =ROUNDUP(B11/'Premissas'!$B$14,0) -> 75000 | D11: 2 | E11: =D11*'Premissas'!$B$16 -> 160 | F11: =ROUND(B11*'Premissas'!$B$5,2) -> 43500 | G11: =ROUND(F11*'Premissas'!$B$6,2) -> 217500 | H11: =ROUND(G11*'Premissas'!$B$7,2) -> 17400 | I11: =ROUND(G11-H11,2) -> 200100 | J11: =ROUND(I11*'Premissas'!$B$8+B11*(1-'Premissas'!$B$7)*'Premissas'!$B$9*'Premissas'!$B$6,2) -> 26709.9 | K11: =ROUND(I11-J11,2) -> 173390.1 | L11: =IF(A11>'Premissas'!$B$20,INDEX($K$5:$K$28,MAX(1,A11-'Premissas'!$B$20)),0) -> 115593.4 | M11: =ROUND(I11*'Premissas'!$B$10,2) -> 30015 | N11: =ROUND(I11*'Premissas'!$B$11,2) -> 6003 | O11: =ROUND(B11*'Premissas'!$B$12*'Premissas'!$B$6,2) -> 75000 | P11: =ROUND(B11*'Premissas'!$B$13*'Premissas'!$B$6,2) -> 7500 | Q11: =ROUND(D11*'Premissas'!$B$15,2) -> 60000 | R11: =ROUND(Q11*'Premissas'!$B$19+Q10*(1-'Premissas'!$B$19),2) -> 60000 | S11: =ROUND(E11*'Premissas'!$B$17,2) -> 28800 | T11: =ROUND(Q11*'Premissas'!$B$10,2) -> 9000 | U11: =ROUND(R11*'Premissas'!$B$18,2) -> 3000 | V11: =IF(A11<=12,'Premissas'!$B$24,'Premissas'!$B$25) -> 37000 | W11: =ROUND(G11+Q11,2) -> 277500 | X11: =ROUND(I11+Q11,2) -> 260100 | Y11: =ROUND(L11+R11,2) -> 175593.4 | Z11: =ROUND(SUM(M11:P11)+SUM(S11:V11),2) -> 196318 | AA11: =ROUND(Y11-Z11,2) -> -20724.6 | AB11: =ROUND(AB10+AA11,2) -> -365655.2 | AC11: =ROUND(X11-J11-SUM(M11:P11)-S11-T11-ROUND(Q11*'Premissas'!$B$18,2)-V11,2) -> 37072.1 | AD11: =ROUND(SUM($K$5:K11)-SUM($L$5:L11)+SUM($Q$5:Q11)-SUM($R$5:R11),2) -> 203390.1 | AE11: =MAX(0,AB11)*'Premissas'!$B$28 -> 0 | AF11: =IF(AB11>=0,A11,999) -> 999 | AG11: =IF(AE11>=Resumo!$E$7,A11,999) -> 999 | AH11: =AB11+Capital!$A$5 -> -265655.2 | AI11: =AB11+Capital!$A$6 -> -215655.2 | AJ11: =AB11+Capital!$A$7 -> -165655.2
A12: 8 | B12: 2200 | C12: =ROUNDUP(B12/'Premissas'!$B$14,0) -> 110000 | D12: 2 | E12: =D12*'Premissas'!$B$16 -> 160 | F12: =ROUND(B12*'Premissas'!$B$5,2) -> 63800 | G12: =ROUND(F12*'Premissas'!$B$6,2) -> 319000 | H12: =ROUND(G12*'Premissas'!$B$7,2) -> 25520 | I12: =ROUND(G12-H12,2) -> 293480 | J12: =ROUND(I12*'Premissas'!$B$8+B12*(1-'Premissas'!$B$7)*'Premissas'!$B$9*'Premissas'!$B$6,2) -> 39174.52 | K12: =ROUND(I12-J12,2) -> 254305.48 | L12: =IF(A12>'Premissas'!$B$20,INDEX($K$5:$K$28,MAX(1,A12-'Premissas'!$B$20)),0) -> 173390.1 | M12: =ROUND(I12*'Premissas'!$B$10,2) -> 44022 | N12: =ROUND(I12*'Premissas'!$B$11,2) -> 8804.4 | O12: =ROUND(B12*'Premissas'!$B$12*'Premissas'!$B$6,2) -> 110000 | P12: =ROUND(B12*'Premissas'!$B$13*'Premissas'!$B$6,2) -> 11000 | Q12: =ROUND(D12*'Premissas'!$B$15,2) -> 60000 | R12: =ROUND(Q12*'Premissas'!$B$19+Q11*(1-'Premissas'!$B$19),2) -> 60000 | S12: =ROUND(E12*'Premissas'!$B$17,2) -> 28800 | T12: =ROUND(Q12*'Premissas'!$B$10,2) -> 9000 | U12: =ROUND(R12*'Premissas'!$B$18,2) -> 3000 | V12: =IF(A12<=12,'Premissas'!$B$24,'Premissas'!$B$25) -> 37000 | W12: =ROUND(G12+Q12,2) -> 379000 | X12: =ROUND(I12+Q12,2) -> 353480 | Y12: =ROUND(L12+R12,2) -> 233390.1 | Z12: =ROUND(SUM(M12:P12)+SUM(S12:V12),2) -> 251626.4 | AA12: =ROUND(Y12-Z12,2) -> -18236.3 | AB12: =ROUND(AB11+AA12,2) -> -383891.5 | AC12: =ROUND(X12-J12-SUM(M12:P12)-S12-T12-ROUND(Q12*'Premissas'!$B$18,2)-V12,2) -> 62679.08 | AD12: =ROUND(SUM($K$5:K12)-SUM($L$5:L12)+SUM($Q$5:Q12)-SUM($R$5:R12),2) -> 284305.48 | AE12: =MAX(0,AB12)*'Premissas'!$B$28 -> 0 | AF12: =IF(AB12>=0,A12,999) -> 999 | AG12: =IF(AE12>=Resumo!$E$7,A12,999) -> 999 | AH12: =AB12+Capital!$A$5 -> -283891.5 | AI12: =AB12+Capital!$A$6 -> -233891.5 | AJ12: =AB12+Capital!$A$7 -> -183891.5
A13: 9 | B13: 3000 | C13: =ROUNDUP(B13/'Premissas'!$B$14,0) -> 150000 | D13: 2 | E13: =D13*'Premissas'!$B$16 -> 160 | F13: =ROUND(B13*'Premissas'!$B$5,2) -> 87000 | G13: =ROUND(F13*'Premissas'!$B$6,2) -> 435000 | H13: =ROUND(G13*'Premissas'!$B$7,2) -> 34800 | I13: =ROUND(G13-H13,2) -> 400200 | J13: =ROUND(I13*'Premissas'!$B$8+B13*(1-'Premissas'!$B$7)*'Premissas'!$B$9*'Premissas'!$B$6,2) -> 53419.8 | K13: =ROUND(I13-J13,2) -> 346780.2 | L13: =IF(A13>'Premissas'!$B$20,INDEX($K$5:$K$28,MAX(1,A13-'Premissas'!$B$20)),0) -> 254305.48 | M13: =ROUND(I13*'Premissas'!$B$10,2) -> 60030 | N13: =ROUND(I13*'Premissas'!$B$11,2) -> 12006 | O13: =ROUND(B13*'Premissas'!$B$12*'Premissas'!$B$6,2) -> 150000 | P13: =ROUND(B13*'Premissas'!$B$13*'Premissas'!$B$6,2) -> 15000 | Q13: =ROUND(D13*'Premissas'!$B$15,2) -> 60000 | R13: =ROUND(Q13*'Premissas'!$B$19+Q12*(1-'Premissas'!$B$19),2) -> 60000 | S13: =ROUND(E13*'Premissas'!$B$17,2) -> 28800 | T13: =ROUND(Q13*'Premissas'!$B$10,2) -> 9000 | U13: =ROUND(R13*'Premissas'!$B$18,2) -> 3000 | V13: =IF(A13<=12,'Premissas'!$B$24,'Premissas'!$B$25) -> 37000 | W13: =ROUND(G13+Q13,2) -> 495000 | X13: =ROUND(I13+Q13,2) -> 460200 | Y13: =ROUND(L13+R13,2) -> 314305.48 | Z13: =ROUND(SUM(M13:P13)+SUM(S13:V13),2) -> 314836 | AA13: =ROUND(Y13-Z13,2) -> -530.52 | AB13: =ROUND(AB12+AA13,2) -> -384422.02 | AC13: =ROUND(X13-J13-SUM(M13:P13)-S13-T13-ROUND(Q13*'Premissas'!$B$18,2)-V13,2) -> 91944.2 | AD13: =ROUND(SUM($K$5:K13)-SUM($L$5:L13)+SUM($Q$5:Q13)-SUM($R$5:R13),2) -> 376780.2 | AE13: =MAX(0,AB13)*'Premissas'!$B$28 -> 0 | AF13: =IF(AB13>=0,A13,999) -> 999 | AG13: =IF(AE13>=Resumo!$E$7,A13,999) -> 999 | AH13: =AB13+Capital!$A$5 -> -284422.02 | AI13: =AB13+Capital!$A$6 -> -234422.02 | AJ13: =AB13+Capital!$A$7 -> -184422.02
A14: 10 | B14: 3500 | C14: =ROUNDUP(B14/'Premissas'!$B$14,0) -> 175000 | D14: 3 | E14: =D14*'Premissas'!$B$16 -> 240 | F14: =ROUND(B14*'Premissas'!$B$5,2) -> 101500 | G14: =ROUND(F14*'Premissas'!$B$6,2) -> 507500 | H14: =ROUND(G14*'Premissas'!$B$7,2) -> 40600 | I14: =ROUND(G14-H14,2) -> 466900 | J14: =ROUND(I14*'Premissas'!$B$8+B14*(1-'Premissas'!$B$7)*'Premissas'!$B$9*'Premissas'!$B$6,2) -> 62323.1 | K14: =ROUND(I14-J14,2) -> 404576.9 | L14: =IF(A14>'Premissas'!$B$20,INDEX($K$5:$K$28,MAX(1,A14-'Premissas'!$B$20)),0) -> 346780.2 | M14: =ROUND(I14*'Premissas'!$B$10,2) -> 70035 | N14: =ROUND(I14*'Premissas'!$B$11,2) -> 14007 | O14: =ROUND(B14*'Premissas'!$B$12*'Premissas'!$B$6,2) -> 175000 | P14: =ROUND(B14*'Premissas'!$B$13*'Premissas'!$B$6,2) -> 17500 | Q14: =ROUND(D14*'Premissas'!$B$15,2) -> 90000 | R14: =ROUND(Q14*'Premissas'!$B$19+Q13*(1-'Premissas'!$B$19),2) -> 75000 | S14: =ROUND(E14*'Premissas'!$B$17,2) -> 43200 | T14: =ROUND(Q14*'Premissas'!$B$10,2) -> 13500 | U14: =ROUND(R14*'Premissas'!$B$18,2) -> 3750 | V14: =IF(A14<=12,'Premissas'!$B$24,'Premissas'!$B$25) -> 37000 | W14: =ROUND(G14+Q14,2) -> 597500 | X14: =ROUND(I14+Q14,2) -> 556900 | Y14: =ROUND(L14+R14,2) -> 421780.2 | Z14: =ROUND(SUM(M14:P14)+SUM(S14:V14),2) -> 373992 | AA14: =ROUND(Y14-Z14,2) -> 47788.2 | AB14: =ROUND(AB13+AA14,2) -> -336633.82 | AC14: =ROUND(X14-J14-SUM(M14:P14)-S14-T14-ROUND(Q14*'Premissas'!$B$18,2)-V14,2) -> 119834.9 | AD14: =ROUND(SUM($K$5:K14)-SUM($L$5:L14)+SUM($Q$5:Q14)-SUM($R$5:R14),2) -> 449576.9 | AE14: =MAX(0,AB14)*'Premissas'!$B$28 -> 0 | AF14: =IF(AB14>=0,A14,999) -> 999 | AG14: =IF(AE14>=Resumo!$E$7,A14,999) -> 999 | AH14: =AB14+Capital!$A$5 -> -236633.82 | AI14: =AB14+Capital!$A$6 -> -186633.82 | AJ14: =AB14+Capital!$A$7 -> -136633.82
A15: 11 | B15: 4000 | C15: =ROUNDUP(B15/'Premissas'!$B$14,0) -> 200000 | D15: 3 | E15: =D15*'Premissas'!$B$16 -> 240 | F15: =ROUND(B15*'Premissas'!$B$5,2) -> 116000 | G15: =ROUND(F15*'Premissas'!$B$6,2) -> 580000 | H15: =ROUND(G15*'Premissas'!$B$7,2) -> 46400 | I15: =ROUND(G15-H15,2) -> 533600 | J15: =ROUND(I15*'Premissas'!$B$8+B15*(1-'Premissas'!$B$7)*'Premissas'!$B$9*'Premissas'!$B$6,2) -> 71226.4 | K15: =ROUND(I15-J15,2) -> 462373.6 | L15: =IF(A15>'Premissas'!$B$20,INDEX($K$5:$K$28,MAX(1,A15-'Premissas'!$B$20)),0) -> 404576.9 | M15: =ROUND(I15*'Premissas'!$B$10,2) -> 80040 | N15: =ROUND(I15*'Premissas'!$B$11,2) -> 16008 | O15: =ROUND(B15*'Premissas'!$B$12*'Premissas'!$B$6,2) -> 200000 | P15: =ROUND(B15*'Premissas'!$B$13*'Premissas'!$B$6,2) -> 20000 | Q15: =ROUND(D15*'Premissas'!$B$15,2) -> 90000 | R15: =ROUND(Q15*'Premissas'!$B$19+Q14*(1-'Premissas'!$B$19),2) -> 90000 | S15: =ROUND(E15*'Premissas'!$B$17,2) -> 43200 | T15: =ROUND(Q15*'Premissas'!$B$10,2) -> 13500 | U15: =ROUND(R15*'Premissas'!$B$18,2) -> 4500 | V15: =IF(A15<=12,'Premissas'!$B$24,'Premissas'!$B$25) -> 37000 | W15: =ROUND(G15+Q15,2) -> 670000 | X15: =ROUND(I15+Q15,2) -> 623600 | Y15: =ROUND(L15+R15,2) -> 494576.9 | Z15: =ROUND(SUM(M15:P15)+SUM(S15:V15),2) -> 414248 | AA15: =ROUND(Y15-Z15,2) -> 80328.9 | AB15: =ROUND(AB14+AA15,2) -> -256304.92 | AC15: =ROUND(X15-J15-SUM(M15:P15)-S15-T15-ROUND(Q15*'Premissas'!$B$18,2)-V15,2) -> 138125.6 | AD15: =ROUND(SUM($K$5:K15)-SUM($L$5:L15)+SUM($Q$5:Q15)-SUM($R$5:R15),2) -> 507373.6 | AE15: =MAX(0,AB15)*'Premissas'!$B$28 -> 0 | AF15: =IF(AB15>=0,A15,999) -> 999 | AG15: =IF(AE15>=Resumo!$E$7,A15,999) -> 999 | AH15: =AB15+Capital!$A$5 -> -156304.92 | AI15: =AB15+Capital!$A$6 -> -106304.92 | AJ15: =AB15+Capital!$A$7 -> -56304.92
A16: 12 | B16: 4500 | C16: =ROUNDUP(B16/'Premissas'!$B$14,0) -> 225000 | D16: 3 | E16: =D16*'Premissas'!$B$16 -> 240 | F16: =ROUND(B16*'Premissas'!$B$5,2) -> 130500 | G16: =ROUND(F16*'Premissas'!$B$6,2) -> 652500 | H16: =ROUND(G16*'Premissas'!$B$7,2) -> 52200 | I16: =ROUND(G16-H16,2) -> 600300 | J16: =ROUND(I16*'Premissas'!$B$8+B16*(1-'Premissas'!$B$7)*'Premissas'!$B$9*'Premissas'!$B$6,2) -> 80129.7 | K16: =ROUND(I16-J16,2) -> 520170.3 | L16: =IF(A16>'Premissas'!$B$20,INDEX($K$5:$K$28,MAX(1,A16-'Premissas'!$B$20)),0) -> 462373.6 | M16: =ROUND(I16*'Premissas'!$B$10,2) -> 90045 | N16: =ROUND(I16*'Premissas'!$B$11,2) -> 18009 | O16: =ROUND(B16*'Premissas'!$B$12*'Premissas'!$B$6,2) -> 225000 | P16: =ROUND(B16*'Premissas'!$B$13*'Premissas'!$B$6,2) -> 22500 | Q16: =ROUND(D16*'Premissas'!$B$15,2) -> 90000 | R16: =ROUND(Q16*'Premissas'!$B$19+Q15*(1-'Premissas'!$B$19),2) -> 90000 | S16: =ROUND(E16*'Premissas'!$B$17,2) -> 43200 | T16: =ROUND(Q16*'Premissas'!$B$10,2) -> 13500 | U16: =ROUND(R16*'Premissas'!$B$18,2) -> 4500 | V16: =IF(A16<=12,'Premissas'!$B$24,'Premissas'!$B$25) -> 37000 | W16: =ROUND(G16+Q16,2) -> 742500 | X16: =ROUND(I16+Q16,2) -> 690300 | Y16: =ROUND(L16+R16,2) -> 552373.6 | Z16: =ROUND(SUM(M16:P16)+SUM(S16:V16),2) -> 453754 | AA16: =ROUND(Y16-Z16,2) -> 98619.6 | AB16: =ROUND(AB15+AA16,2) -> -157685.32 | AC16: =ROUND(X16-J16-SUM(M16:P16)-S16-T16-ROUND(Q16*'Premissas'!$B$18,2)-V16,2) -> 156416.3 | AD16: =ROUND(SUM($K$5:K16)-SUM($L$5:L16)+SUM($Q$5:Q16)-SUM($R$5:R16),2) -> 565170.3 | AE16: =MAX(0,AB16)*'Premissas'!$B$28 -> 0 | AF16: =IF(AB16>=0,A16,999) -> 999 | AG16: =IF(AE16>=Resumo!$E$7,A16,999) -> 999 | AH16: =AB16+Capital!$A$5 -> -57685.32 | AI16: =AB16+Capital!$A$6 -> -7685.32 | AJ16: =AB16+Capital!$A$7 -> 42314.68
A17: 13 | B17: 5000 | C17: =ROUNDUP(B17/'Premissas'!$B$14,0) -> 250000 | D17: 3 | E17: =D17*'Premissas'!$B$16 -> 240 | F17: =ROUND(B17*'Premissas'!$B$5,2) -> 145000 | G17: =ROUND(F17*'Premissas'!$B$6,2) -> 725000 | H17: =ROUND(G17*'Premissas'!$B$7,2) -> 58000 | I17: =ROUND(G17-H17,2) -> 667000 | J17: =ROUND(I17*'Premissas'!$B$8+B17*(1-'Premissas'!$B$7)*'Premissas'!$B$9*'Premissas'!$B$6,2) -> 89033 | K17: =ROUND(I17-J17,2) -> 577967 | L17: =IF(A17>'Premissas'!$B$20,INDEX($K$5:$K$28,MAX(1,A17-'Premissas'!$B$20)),0) -> 520170.3 | M17: =ROUND(I17*'Premissas'!$B$10,2) -> 100050 | N17: =ROUND(I17*'Premissas'!$B$11,2) -> 20010 | O17: =ROUND(B17*'Premissas'!$B$12*'Premissas'!$B$6,2) -> 250000 | P17: =ROUND(B17*'Premissas'!$B$13*'Premissas'!$B$6,2) -> 25000 | Q17: =ROUND(D17*'Premissas'!$B$15,2) -> 90000 | R17: =ROUND(Q17*'Premissas'!$B$19+Q16*(1-'Premissas'!$B$19),2) -> 90000 | S17: =ROUND(E17*'Premissas'!$B$17,2) -> 43200 | T17: =ROUND(Q17*'Premissas'!$B$10,2) -> 13500 | U17: =ROUND(R17*'Premissas'!$B$18,2) -> 4500 | V17: =IF(A17<=12,'Premissas'!$B$24,'Premissas'!$B$25) -> 42000 | W17: =ROUND(G17+Q17,2) -> 815000 | X17: =ROUND(I17+Q17,2) -> 757000 | Y17: =ROUND(L17+R17,2) -> 610170.3 | Z17: =ROUND(SUM(M17:P17)+SUM(S17:V17),2) -> 498260 | AA17: =ROUND(Y17-Z17,2) -> 111910.3 | AB17: =ROUND(AB16+AA17,2) -> -45775.02 | AC17: =ROUND(X17-J17-SUM(M17:P17)-S17-T17-ROUND(Q17*'Premissas'!$B$18,2)-V17,2) -> 169707 | AD17: =ROUND(SUM($K$5:K17)-SUM($L$5:L17)+SUM($Q$5:Q17)-SUM($R$5:R17),2) -> 622967 | AE17: =MAX(0,AB17)*'Premissas'!$B$28 -> 0 | AF17: =IF(AB17>=0,A17,999) -> 999 | AG17: =IF(AE17>=Resumo!$E$7,A17,999) -> 999 | AH17: =AB17+Capital!$A$5 -> 54224.98 | AI17: =AB17+Capital!$A$6 -> 104224.98 | AJ17: =AB17+Capital!$A$7 -> 154224.98
... A28: 24 | B28: 5000 | C28: =ROUNDUP(B28/'Premissas'!$B$14,0) -> 250000 | D28: 3 | E28: =D28*'Premissas'!$B$16 -> 240 | F28: =ROUND(B28*'Premissas'!$B$5,2) -> 145000 | G28: =ROUND(F28*'Premissas'!$B$6,2) -> 725000 | H28: =ROUND(G28*'Premissas'!$B$7,2) -> 58000 | I28: =ROUND(G28-H28,2) -> 667000 | J28: =ROUND(I28*'Premissas'!$B$8+B28*(1-'Premissas'!$B$7)*'Premissas'!$B$9*'Premissas'!$B$6,2) -> 89033 | K28: =ROUND(I28-J28,2) -> 577967 | L28: =IF(A28>'Premissas'!$B$20,INDEX($K$5:$K$28,MAX(1,A28-'Premissas'!$B$20)),0) -> 577967 | M28: =ROUND(I28*'Premissas'!$B$10,2) -> 100050 | N28: =ROUND(I28*'Premissas'!$B$11,2) -> 20010 | O28: =ROUND(B28*'Premissas'!$B$12*'Premissas'!$B$6,2) -> 250000 | P28: =ROUND(B28*'Premissas'!$B$13*'Premissas'!$B$6,2) -> 25000 | Q28: =ROUND(D28*'Premissas'!$B$15,2) -> 90000 | R28: =ROUND(Q28*'Premissas'!$B$19+Q27*(1-'Premissas'!$B$19),2) -> 90000 | S28: =ROUND(E28*'Premissas'!$B$17,2) -> 43200 | T28: =ROUND(Q28*'Premissas'!$B$10,2) -> 13500 | U28: =ROUND(R28*'Premissas'!$B$18,2) -> 4500 | V28: =IF(A28<=12,'Premissas'!$B$24,'Premissas'!$B$25) -> 42000 | W28: =ROUND(G28+Q28,2) -> 815000 | X28: =ROUND(I28+Q28,2) -> 757000 | Y28: =ROUND(L28+R28,2) -> 667967 | Z28: =ROUND(SUM(M28:P28)+SUM(S28:V28),2) -> 498260 | AA28: =ROUND(Y28-Z28,2) -> 169707 | AB28: =ROUND(AB27+AA28,2) -> 1821002 | AC28: =ROUND(X28-J28-SUM(M28:P28)-S28-T28-ROUND(Q28*'Premissas'!$B$18,2)-V28,2) -> 169707 | AD28: =ROUND(SUM($K$5:K28)-SUM($L$5:L28)+SUM($Q$5:Q28)-SUM($R$5:R28),2) -> 622967 | AE28: =MAX(0,AB28)*'Premissas'!$B$28 -> 910500.99 | AF28: =IF(AB28>=0,A28,999) -> 24 | AG28: =IF(AE28>=Resumo!$E$7,A28,999) -> 24 | AH28: =AB28+Capital!$A$5 -> 1921002 | AI28: =AB28+Capital!$A$6 -> 1971002 | AJ28: =AB28+Capital!$A$7 -> 2021002

Sheet CAC15
A1: CAC15 | fluxo mensal em BRL, salvo indicação
A2: Agenda vinculada à Base; nenhum aumento de vendas. CAC de USD10 para USD15, demais premissas iguais | M0 separado: -R$100 mil nas premissas. Acumulado exclui aportes/distribuição.
A4: Mês | B4: Pedidos aprovados | C4: Visitas qualificadas | D4: Mapas faturados | E4: Horas diretas TI | F4: Loja bruta USD | G4: Loja bruta BRL | H4: Estornos BRL | I4: Loja após estornos BRL | J4: Taxa plataforma BRL | K4: Liquidação gerada BRL | L4: Loja recebida BRL | M4: Tributos loja BRL | N4: Reserva meios/FX BRL | O4: Aquisição / mídia BRL | P4: Suporte loja BRL | Q4: Fatura TI BRL | R4: Recebimentos TI BRL | S4: Entrega TI BRL | T4: Tributos TI BRL | U4: Comercial TI caixa BRL | V4: Fixo BRL | W4: Vendas brutas BRL | X4: Receita após estornos BRL | Y4: Recebimentos BRL | Z4: Saídas caixa BRL | AA4: Fluxo líquido BRL | AB4: Acumulado sem aporte BRL | AC4: Resultado competência BRL | AD4: A receber BRL | AE4: 50% excedente positivo BRL | AF4: Mês elegível payback projeto | AG4: Mês elegível Dani hipotético | AH4: Saldo com 100k | AI4: Saldo com 150k | AJ4: Saldo com 200k
A5: 1 | B5: ='Base'!B5 -> 0 | C5: =ROUNDUP(B5/'Premissas'!$B$14,0) -> 0 | D5: ='Base'!D5 -> 0 | E5: =D5*'Premissas'!$B$16 -> 0 | F5: =ROUND(B5*'Premissas'!$B$5,2) -> 0 | G5: =ROUND(F5*'Premissas'!$B$6,2) -> 0 | H5: =ROUND(G5*'Premissas'!$B$7,2) -> 0 | I5: =ROUND(G5-H5,2) -> 0 | J5: =ROUND(I5*'Premissas'!$B$8+B5*(1-'Premissas'!$B$7)*'Premissas'!$B$9*'Premissas'!$B$6,2) -> 0 | K5: =ROUND(I5-J5,2) -> 0 | L5: =IF(A5>'Premissas'!$B$20,INDEX($K$5:$K$28,MAX(1,A5-'Premissas'!$B$20)),0) -> 0 | M5: =ROUND(I5*'Premissas'!$B$10,2) -> 0 | N5: =ROUND(I5*'Premissas'!$B$11,2) -> 0 | O5: =ROUND(B5*'Premissas'!$B$29*'Premissas'!$B$6,2) -> 0 | P5: =ROUND(B5*'Premissas'!$B$13*'Premissas'!$B$6,2) -> 0 | Q5: =ROUND(D5*'Premissas'!$B$15,2) -> 0 | R5: =ROUND(Q5*'Premissas'!$B$19+0*(1-'Premissas'!$B$19),2) -> 0 | S5: =ROUND(E5*'Premissas'!$B$17,2) -> 0 | T5: =ROUND(Q5*'Premissas'!$B$10,2) -> 0 | U5: =ROUND(R5*'Premissas'!$B$18,2) -> 0 | V5: =IF(A5<=12,'Premissas'!$B$24,'Premissas'!$B$25) -> 37000 | W5: =ROUND(G5+Q5,2) -> 0 | X5: =ROUND(I5+Q5,2) -> 0 | Y5: =ROUND(L5+R5,2) -> 0 | Z5: =ROUND(SUM(M5:P5)+SUM(S5:V5),2) -> 37000 | AA5: =ROUND(Y5-Z5,2) -> -37000 | AB5: =ROUND(-'Premissas'!$B$23+AA5,2) -> -137000 | AC5: =ROUND(X5-J5-SUM(M5:P5)-S5-T5-ROUND(Q5*'Premissas'!$B$18,2)-V5,2) -> -37000 | AD5: =ROUND(SUM($K$5:K5)-SUM($L$5:L5)+SUM($Q$5:Q5)-SUM($R$5:R5),2) -> 0 | AE5: =MAX(0,AB5)*'Premissas'!$B$28 -> 0 | AF5: =IF(AB5>=0,A5,999) -> 999 | AG5: =IF(AE5>=Resumo!$E$8,A5,999) -> 999 | AH5: =AB5+Capital!$A$5 -> -37000 | AI5: =AB5+Capital!$A$6 -> 13000 | AJ5: =AB5+Capital!$A$7 -> 63000
A6: 2 | B6: ='Base'!B6 -> 0 | C6: =ROUNDUP(B6/'Premissas'!$B$14,0) -> 0 | D6: ='Base'!D6 -> 0 | E6: =D6*'Premissas'!$B$16 -> 0 | F6: =ROUND(B6*'Premissas'!$B$5,2) -> 0 | G6: =ROUND(F6*'Premissas'!$B$6,2) -> 0 | H6: =ROUND(G6*'Premissas'!$B$7,2) -> 0 | I6: =ROUND(G6-H6,2) -> 0 | J6: =ROUND(I6*'Premissas'!$B$8+B6*(1-'Premissas'!$B$7)*'Premissas'!$B$9*'Premissas'!$B$6,2) -> 0 | K6: =ROUND(I6-J6,2) -> 0 | L6: =IF(A6>'Premissas'!$B$20,INDEX($K$5:$K$28,MAX(1,A6-'Premissas'!$B$20)),0) -> 0 | M6: =ROUND(I6*'Premissas'!$B$10,2) -> 0 | N6: =ROUND(I6*'Premissas'!$B$11,2) -> 0 | O6: =ROUND(B6*'Premissas'!$B$29*'Premissas'!$B$6,2) -> 0 | P6: =ROUND(B6*'Premissas'!$B$13*'Premissas'!$B$6,2) -> 0 | Q6: =ROUND(D6*'Premissas'!$B$15,2) -> 0 | R6: =ROUND(Q6*'Premissas'!$B$19+Q5*(1-'Premissas'!$B$19),2) -> 0 | S6: =ROUND(E6*'Premissas'!$B$17,2) -> 0 | T6: =ROUND(Q6*'Premissas'!$B$10,2) -> 0 | U6: =ROUND(R6*'Premissas'!$B$18,2) -> 0 | V6: =IF(A6<=12,'Premissas'!$B$24,'Premissas'!$B$25) -> 37000 | W6: =ROUND(G6+Q6,2) -> 0 | X6: =ROUND(I6+Q6,2) -> 0 | Y6: =ROUND(L6+R6,2) -> 0 | Z6: =ROUND(SUM(M6:P6)+SUM(S6:V6),2) -> 37000 | AA6: =ROUND(Y6-Z6,2) -> -37000 | AB6: =ROUND(AB5+AA6,2) -> -174000 | AC6: =ROUND(X6-J6-SUM(M6:P6)-S6-T6-ROUND(Q6*'Premissas'!$B$18,2)-V6,2) -> -37000 | AD6: =ROUND(SUM($K$5:K6)-SUM($L$5:L6)+SUM($Q$5:Q6)-SUM($R$5:R6),2) -> 0 | AE6: =MAX(0,AB6)*'Premissas'!$B$28 -> 0 | AF6: =IF(AB6>=0,A6,999) -> 999 | AG6: =IF(AE6>=Resumo!$E$8,A6,999) -> 999 | AH6: =AB6+Capital!$A$5 -> -74000 | AI6: =AB6+Capital!$A$6 -> -24000 | AJ6: =AB6+Capital!$A$7 -> 26000
A7: 3 | B7: ='Base'!B7 -> 50 | C7: =ROUNDUP(B7/'Premissas'!$B$14,0) -> 2500 | D7: ='Base'!D7 -> 1 | E7: =D7*'Premissas'!$B$16 -> 80 | F7: =ROUND(B7*'Premissas'!$B$5,2) -> 1450 | G7: =ROUND(F7*'Premissas'!$B$6,2) -> 7250 | H7: =ROUND(G7*'Premissas'!$B$7,2) -> 580 | I7: =ROUND(G7-H7,2) -> 6670 | J7: =ROUND(I7*'Premissas'!$B$8+B7*(1-'Premissas'!$B$7)*'Premissas'!$B$9*'Premissas'!$B$6,2) -> 890.33 | K7: =ROUND(I7-J7,2) -> 5779.67 | L7: =IF(A7>'Premissas'!$B$20,INDEX($K$5:$K$28,MAX(1,A7-'Premissas'!$B$20)),0) -> 0 | M7: =ROUND(I7*'Premissas'!$B$10,2) -> 1000.5 | N7: =ROUND(I7*'Premissas'!$B$11,2) -> 200.1 | O7: =ROUND(B7*'Premissas'!$B$29*'Premissas'!$B$6,2) -> 3750 | P7: =ROUND(B7*'Premissas'!$B$13*'Premissas'!$B$6,2) -> 250 | Q7: =ROUND(D7*'Premissas'!$B$15,2) -> 30000 | R7: =ROUND(Q7*'Premissas'!$B$19+Q6*(1-'Premissas'!$B$19),2) -> 15000 | S7: =ROUND(E7*'Premissas'!$B$17,2) -> 14400 | T7: =ROUND(Q7*'Premissas'!$B$10,2) -> 4500 | U7: =ROUND(R7*'Premissas'!$B$18,2) -> 750 | V7: =IF(A7<=12,'Premissas'!$B$24,'Premissas'!$B$25) -> 37000 | W7: =ROUND(G7+Q7,2) -> 37250 | X7: =ROUND(I7+Q7,2) -> 36670 | Y7: =ROUND(L7+R7,2) -> 15000 | Z7: =ROUND(SUM(M7:P7)+SUM(S7:V7),2) -> 61850.6 | AA7: =ROUND(Y7-Z7,2) -> -46850.6 | AB7: =ROUND(AB6+AA7,2) -> -220850.6 | AC7: =ROUND(X7-J7-SUM(M7:P7)-S7-T7-ROUND(Q7*'Premissas'!$B$18,2)-V7,2) -> -26820.93 | AD7: =ROUND(SUM($K$5:K7)-SUM($L$5:L7)+SUM($Q$5:Q7)-SUM($R$5:R7),2) -> 20779.67 | AE7: =MAX(0,AB7)*'Premissas'!$B$28 -> 0 | AF7: =IF(AB7>=0,A7,999) -> 999 | AG7: =IF(AE7>=Resumo!$E$8,A7,999) -> 999 | AH7: =AB7+Capital!$A$5 -> -120850.6 | AI7: =AB7+Capital!$A$6 -> -70850.6 | AJ7: =AB7+Capital!$A$7 -> -20850.6
A8: 4 | B8: ='Base'!B8 -> 150 | C8: =ROUNDUP(B8/'Premissas'!$B$14,0) -> 7500 | D8: ='Base'!D8 -> 0 | E8: =D8*'Premissas'!$B$16 -> 0 | F8: =ROUND(B8*'Premissas'!$B$5,2) -> 4350 | G8: =ROUND(F8*'Premissas'!$B$6,2) -> 21750 | H8: =ROUND(G8*'Premissas'!$B$7,2) -> 1740 | I8: =ROUND(G8-H8,2) -> 20010 | J8: =ROUND(I8*'Premissas'!$B$8+B8*(1-'Premissas'!$B$7)*'Premissas'!$B$9*'Premissas'!$B$6,2) -> 2670.99 | K8: =ROUND(I8-J8,2) -> 17339.01 | L8: =IF(A8>'Premissas'!$B$20,INDEX($K$5:$K$28,MAX(1,A8-'Premissas'!$B$20)),0) -> 5779.67 | M8: =ROUND(I8*'Premissas'!$B$10,2) -> 3001.5 | N8: =ROUND(I8*'Premissas'!$B$11,2) -> 600.3 | O8: =ROUND(B8*'Premissas'!$B$29*'Premissas'!$B$6,2) -> 11250 | P8: =ROUND(B8*'Premissas'!$B$13*'Premissas'!$B$6,2) -> 750 | Q8: =ROUND(D8*'Premissas'!$B$15,2) -> 0 | R8: =ROUND(Q8*'Premissas'!$B$19+Q7*(1-'Premissas'!$B$19),2) -> 15000 | S8: =ROUND(E8*'Premissas'!$B$17,2) -> 0 | T8: =ROUND(Q8*'Premissas'!$B$10,2) -> 0 | U8: =ROUND(R8*'Premissas'!$B$18,2) -> 750 | V8: =IF(A8<=12,'Premissas'!$B$24,'Premissas'!$B$25) -> 37000 | W8: =ROUND(G8+Q8,2) -> 21750 | X8: =ROUND(I8+Q8,2) -> 20010 | Y8: =ROUND(L8+R8,2) -> 20779.67 | Z8: =ROUND(SUM(M8:P8)+SUM(S8:V8),2) -> 53351.8 | AA8: =ROUND(Y8-Z8,2) -> -32572.13 | AB8: =ROUND(AB7+AA8,2) -> -253422.73 | AC8: =ROUND(X8-J8-SUM(M8:P8)-S8-T8-ROUND(Q8*'Premissas'!$B$18,2)-V8,2) -> -35262.79 | AD8: =ROUND(SUM($K$5:K8)-SUM($L$5:L8)+SUM($Q$5:Q8)-SUM($R$5:R8),2) -> 17339.01 | AE8: =MAX(0,AB8)*'Premissas'!$B$28 -> 0 | AF8: =IF(AB8>=0,A8,999) -> 999 | AG8: =IF(AE8>=Resumo!$E$8,A8,999) -> 999 | AH8: =AB8+Capital!$A$5 -> -153422.73 | AI8: =AB8+Capital!$A$6 -> -103422.73 | AJ8: =AB8+Capital!$A$7 -> -53422.73
A9: 5 | B9: ='Base'!B9 -> 300 | C9: =ROUNDUP(B9/'Premissas'!$B$14,0) -> 15000 | D9: ='Base'!D9 -> 1 | E9: =D9*'Premissas'!$B$16 -> 80 | F9: =ROUND(B9*'Premissas'!$B$5,2) -> 8700 | G9: =ROUND(F9*'Premissas'!$B$6,2) -> 43500 | H9: =ROUND(G9*'Premissas'!$B$7,2) -> 3480 | I9: =ROUND(G9-H9,2) -> 40020 | J9: =ROUND(I9*'Premissas'!$B$8+B9*(1-'Premissas'!$B$7)*'Premissas'!$B$9*'Premissas'!$B$6,2) -> 5341.98 | K9: =ROUND(I9-J9,2) -> 34678.02 | L9: =IF(A9>'Premissas'!$B$20,INDEX($K$5:$K$28,MAX(1,A9-'Premissas'!$B$20)),0) -> 17339.01 | M9: =ROUND(I9*'Premissas'!$B$10,2) -> 6003 | N9: =ROUND(I9*'Premissas'!$B$11,2) -> 1200.6 | O9: =ROUND(B9*'Premissas'!$B$29*'Premissas'!$B$6,2) -> 22500 | P9: =ROUND(B9*'Premissas'!$B$13*'Premissas'!$B$6,2) -> 1500 | Q9: =ROUND(D9*'Premissas'!$B$15,2) -> 30000 | R9: =ROUND(Q9*'Premissas'!$B$19+Q8*(1-'Premissas'!$B$19),2) -> 15000 | S9: =ROUND(E9*'Premissas'!$B$17,2) -> 14400 | T9: =ROUND(Q9*'Premissas'!$B$10,2) -> 4500 | U9: =ROUND(R9*'Premissas'!$B$18,2) -> 750 | V9: =IF(A9<=12,'Premissas'!$B$24,'Premissas'!$B$25) -> 37000 | W9: =ROUND(G9+Q9,2) -> 73500 | X9: =ROUND(I9+Q9,2) -> 70020 | Y9: =ROUND(L9+R9,2) -> 32339.01 | Z9: =ROUND(SUM(M9:P9)+SUM(S9:V9),2) -> 87853.6 | AA9: =ROUND(Y9-Z9,2) -> -55514.59 | AB9: =ROUND(AB8+AA9,2) -> -308937.32 | AC9: =ROUND(X9-J9-SUM(M9:P9)-S9-T9-ROUND(Q9*'Premissas'!$B$18,2)-V9,2) -> -23925.58 | AD9: =ROUND(SUM($K$5:K9)-SUM($L$5:L9)+SUM($Q$5:Q9)-SUM($R$5:R9),2) -> 49678.02 | AE9: =MAX(0,AB9)*'Premissas'!$B$28 -> 0 | AF9: =IF(AB9>=0,A9,999) -> 999 | AG9: =IF(AE9>=Resumo!$E$8,A9,999) -> 999 | AH9: =AB9+Capital!$A$5 -> -208937.32 | AI9: =AB9+Capital!$A$6 -> -158937.32 | AJ9: =AB9+Capital!$A$7 -> -108937.32
A10: 6 | B10: ='Base'!B10 -> 500 | C10: =ROUNDUP(B10/'Premissas'!$B$14,0) -> 25000 | D10: ='Base'!D10 -> 0 | E10: =D10*'Premissas'!$B$16 -> 0 | F10: =ROUND(B10*'Premissas'!$B$5,2) -> 14500 | G10: =ROUND(F10*'Premissas'!$B$6,2) -> 72500 | H10: =ROUND(G10*'Premissas'!$B$7,2) -> 5800 | I10: =ROUND(G10-H10,2) -> 66700 | J10: =ROUND(I10*'Premissas'!$B$8+B10*(1-'Premissas'!$B$7)*'Premissas'!$B$9*'Premissas'!$B$6,2) -> 8903.3 | K10: =ROUND(I10-J10,2) -> 57796.7 | L10: =IF(A10>'Premissas'!$B$20,INDEX($K$5:$K$28,MAX(1,A10-'Premissas'!$B$20)),0) -> 34678.02 | M10: =ROUND(I10*'Premissas'!$B$10,2) -> 10005 | N10: =ROUND(I10*'Premissas'!$B$11,2) -> 2001 | O10: =ROUND(B10*'Premissas'!$B$29*'Premissas'!$B$6,2) -> 37500 | P10: =ROUND(B10*'Premissas'!$B$13*'Premissas'!$B$6,2) -> 2500 | Q10: =ROUND(D10*'Premissas'!$B$15,2) -> 0 | R10: =ROUND(Q10*'Premissas'!$B$19+Q9*(1-'Premissas'!$B$19),2) -> 15000 | S10: =ROUND(E10*'Premissas'!$B$17,2) -> 0 | T10: =ROUND(Q10*'Premissas'!$B$10,2) -> 0 | U10: =ROUND(R10*'Premissas'!$B$18,2) -> 750 | V10: =IF(A10<=12,'Premissas'!$B$24,'Premissas'!$B$25) -> 37000 | W10: =ROUND(G10+Q10,2) -> 72500 | X10: =ROUND(I10+Q10,2) -> 66700 | Y10: =ROUND(L10+R10,2) -> 49678.02 | Z10: =ROUND(SUM(M10:P10)+SUM(S10:V10),2) -> 89756 | AA10: =ROUND(Y10-Z10,2) -> -40077.98 | AB10: =ROUND(AB9+AA10,2) -> -349015.3 | AC10: =ROUND(X10-J10-SUM(M10:P10)-S10-T10-ROUND(Q10*'Premissas'!$B$18,2)-V10,2) -> -31209.3 | AD10: =ROUND(SUM($K$5:K10)-SUM($L$5:L10)+SUM($Q$5:Q10)-SUM($R$5:R10),2) -> 57796.7 | AE10: =MAX(0,AB10)*'Premissas'!$B$28 -> 0 | AF10: =IF(AB10>=0,A10,999) -> 999 | AG10: =IF(AE10>=Resumo!$E$8,A10,999) -> 999 | AH10: =AB10+Capital!$A$5 -> -249015.3 | AI10: =AB10+Capital!$A$6 -> -199015.3 | AJ10: =AB10+Capital!$A$7 -> -149015.3
A11: 7 | B11: ='Base'!B11 -> 750 | C11: =ROUNDUP(B11/'Premissas'!$B$14,0) -> 37500 | D11: ='Base'!D11 -> 1 | E11: =D11*'Premissas'!$B$16 -> 80 | F11: =ROUND(B11*'Premissas'!$B$5,2) -> 21750 | G11: =ROUND(F11*'Premissas'!$B$6,2) -> 108750 | H11: =ROUND(G11*'Premissas'!$B$7,2) -> 8700 | I11: =ROUND(G11-H11,2) -> 100050 | J11: =ROUND(I11*'Premissas'!$B$8+B11*(1-'Premissas'!$B$7)*'Premissas'!$B$9*'Premissas'!$B$6,2) -> 13354.95 | K11: =ROUND(I11-J11,2) -> 86695.05 | L11: =IF(A11>'Premissas'!$B$20,INDEX($K$5:$K$28,MAX(1,A11-'Premissas'!$B$20)),0) -> 57796.7 | M11: =ROUND(I11*'Premissas'!$B$10,2) -> 15007.5 | N11: =ROUND(I11*'Premissas'!$B$11,2) -> 3001.5 | O11: =ROUND(B11*'Premissas'!$B$29*'Premissas'!$B$6,2) -> 56250 | P11: =ROUND(B11*'Premissas'!$B$13*'Premissas'!$B$6,2) -> 3750 | Q11: =ROUND(D11*'Premissas'!$B$15,2) -> 30000 | R11: =ROUND(Q11*'Premissas'!$B$19+Q10*(1-'Premissas'!$B$19),2) -> 15000 | S11: =ROUND(E11*'Premissas'!$B$17,2) -> 14400 | T11: =ROUND(Q11*'Premissas'!$B$10,2) -> 4500 | U11: =ROUND(R11*'Premissas'!$B$18,2) -> 750 | V11: =IF(A11<=12,'Premissas'!$B$24,'Premissas'!$B$25) -> 37000 | W11: =ROUND(G11+Q11,2) -> 138750 | X11: =ROUND(I11+Q11,2) -> 130050 | Y11: =ROUND(L11+R11,2) -> 72796.7 | Z11: =ROUND(SUM(M11:P11)+SUM(S11:V11),2) -> 134659 | AA11: =ROUND(Y11-Z11,2) -> -61862.3 | AB11: =ROUND(AB10+AA11,2) -> -410877.6 | AC11: =ROUND(X11-J11-SUM(M11:P11)-S11-T11-ROUND(Q11*'Premissas'!$B$18,2)-V11,2) -> -18713.95 | AD11: =ROUND(SUM($K$5:K11)-SUM($L$5:L11)+SUM($Q$5:Q11)-SUM($R$5:R11),2) -> 101695.05 | AE11: =MAX(0,AB11)*'Premissas'!$B$28 -> 0 | AF11: =IF(AB11>=0,A11,999) -> 999 | AG11: =IF(AE11>=Resumo!$E$8,A11,999) -> 999 | AH11: =AB11+Capital!$A$5 -> -310877.6 | AI11: =AB11+Capital!$A$6 -> -260877.6 | AJ11: =AB11+Capital!$A$7 -> -210877.6
A12: 8 | B12: ='Base'!B12 -> 1000 | C12: =ROUNDUP(B12/'Premissas'!$B$14,0) -> 50000 | D12: ='Base'!D12 -> 1 | E12: =D12*'Premissas'!$B$16 -> 80 | F12: =ROUND(B12*'Premissas'!$B$5,2) -> 29000 | G12: =ROUND(F12*'Premissas'!$B$6,2) -> 145000 | H12: =ROUND(G12*'Premissas'!$B$7,2) -> 11600 | I12: =ROUND(G12-H12,2) -> 133400 | J12: =ROUND(I12*'Premissas'!$B$8+B12*(1-'Premissas'!$B$7)*'Premissas'!$B$9*'Premissas'!$B$6,2) -> 17806.6 | K12: =ROUND(I12-J12,2) -> 115593.4 | L12: =IF(A12>'Premissas'!$B$20,INDEX($K$5:$K$28,MAX(1,A12-'Premissas'!$B$20)),0) -> 86695.05 | M12: =ROUND(I12*'Premissas'!$B$10,2) -> 20010 | N12: =ROUND(I12*'Premissas'!$B$11,2) -> 4002 | O12: =ROUND(B12*'Premissas'!$B$29*'Premissas'!$B$6,2) -> 75000 | P12: =ROUND(B12*'Premissas'!$B$13*'Premissas'!$B$6,2) -> 5000 | Q12: =ROUND(D12*'Premissas'!$B$15,2) -> 30000 | R12: =ROUND(Q12*'Premissas'!$B$19+Q11*(1-'Premissas'!$B$19),2) -> 30000 | S12: =ROUND(E12*'Premissas'!$B$17,2) -> 14400 | T12: =ROUND(Q12*'Premissas'!$B$10,2) -> 4500 | U12: =ROUND(R12*'Premissas'!$B$18,2) -> 1500 | V12: =IF(A12<=12,'Premissas'!$B$24,'Premissas'!$B$25) -> 37000 | W12: =ROUND(G12+Q12,2) -> 175000 | X12: =ROUND(I12+Q12,2) -> 163400 | Y12: =ROUND(L12+R12,2) -> 116695.05 | Z12: =ROUND(SUM(M12:P12)+SUM(S12:V12),2) -> 161412 | AA12: =ROUND(Y12-Z12,2) -> -44716.95 | AB12: =ROUND(AB11+AA12,2) -> -455594.55 | AC12: =ROUND(X12-J12-SUM(M12:P12)-S12-T12-ROUND(Q12*'Premissas'!$B$18,2)-V12,2) -> -15818.6 | AD12: =ROUND(SUM($K$5:K12)-SUM($L$5:L12)+SUM($Q$5:Q12)-SUM($R$5:R12),2) -> 130593.4 | AE12: =MAX(0,AB12)*'Premissas'!$B$28 -> 0 | AF12: =IF(AB12>=0,A12,999) -> 999 | AG12: =IF(AE12>=Resumo!$E$8,A12,999) -> 999 | AH12: =AB12+Capital!$A$5 -> -355594.55 | AI12: =AB12+Capital!$A$6 -> -305594.55 | AJ12: =AB12+Capital!$A$7 -> -255594.55
A13: 9 | B13: ='Base'!B13 -> 1250 | C13: =ROUNDUP(B13/'Premissas'!$B$14,0) -> 62500 | D13: ='Base'!D13 -> 1 | E13: =D13*'Premissas'!$B$16 -> 80 | F13: =ROUND(B13*'Premissas'!$B$5,2) -> 36250 | G13: =ROUND(F13*'Premissas'!$B$6,2) -> 181250 | H13: =ROUND(G13*'Premissas'!$B$7,2) -> 14500 | I13: =ROUND(G13-H13,2) -> 166750 | J13: =ROUND(I13*'Premissas'!$B$8+B13*(1-'Premissas'!$B$7)*'Premissas'!$B$9*'Premissas'!$B$6,2) -> 22258.25 | K13: =ROUND(I13-J13,2) -> 144491.75 | L13: =IF(A13>'Premissas'!$B$20,INDEX($K$5:$K$28,MAX(1,A13-'Premissas'!$B$20)),0) -> 115593.4 | M13: =ROUND(I13*'Premissas'!$B$10,2) -> 25012.5 | N13: =ROUND(I13*'Premissas'!$B$11,2) -> 5002.5 | O13: =ROUND(B13*'Premissas'!$B$29*'Premissas'!$B$6,2) -> 93750 | P13: =ROUND(B13*'Premissas'!$B$13*'Premissas'!$B$6,2) -> 6250 | Q13: =ROUND(D13*'Premissas'!$B$15,2) -> 30000 | R13: =ROUND(Q13*'Premissas'!$B$19+Q12*(1-'Premissas'!$B$19),2) -> 30000 | S13: =ROUND(E13*'Premissas'!$B$17,2) -> 14400 | T13: =ROUND(Q13*'Premissas'!$B$10,2) -> 4500 | U13: =ROUND(R13*'Premissas'!$B$18,2) -> 1500 | V13: =IF(A13<=12,'Premissas'!$B$24,'Premissas'!$B$25) -> 37000 | W13: =ROUND(G13+Q13,2) -> 211250 | X13: =ROUND(I13+Q13,2) -> 196750 | Y13: =ROUND(L13+R13,2) -> 145593.4 | Z13: =ROUND(SUM(M13:P13)+SUM(S13:V13),2) -> 187415 | AA13: =ROUND(Y13-Z13,2) -> -41821.6 | AB13: =ROUND(AB12+AA13,2) -> -497416.15 | AC13: =ROUND(X13-J13-SUM(M13:P13)-S13-T13-ROUND(Q13*'Premissas'!$B$18,2)-V13,2) -> -12923.25 | AD13: =ROUND(SUM($K$5:K13)-SUM($L$5:L13)+SUM($Q$5:Q13)-SUM($R$5:R13),2) -> 159491.75 | AE13: =MAX(0,AB13)*'Premissas'!$B$28 -> 0 | AF13: =IF(AB13>=0,A13,999) -> 999 | AG13: =IF(AE13>=Resumo!$E$8,A13,999) -> 999 | AH13: =AB13+Capital!$A$5 -> -397416.15 | AI13: =AB13+Capital!$A$6 -> -347416.15 | AJ13: =AB13+Capital!$A$7 -> -297416.15
A14: 10 | B14: ='Base'!B14 -> 1500 | C14: =ROUNDUP(B14/'Premissas'!$B$14,0) -> 75000 | D14: ='Base'!D14 -> 1 | E14: =D14*'Premissas'!$B$16 -> 80 | F14: =ROUND(B14*'Premissas'!$B$5,2) -> 43500 | G14: =ROUND(F14*'Premissas'!$B$6,2) -> 217500 | H14: =ROUND(G14*'Premissas'!$B$7,2) -> 17400 | I14: =ROUND(G14-H14,2) -> 200100 | J14: =ROUND(I14*'Premissas'!$B$8+B14*(1-'Premissas'!$B$7)*'Premissas'!$B$9*'Premissas'!$B$6,2) -> 26709.9 | K14: =ROUND(I14-J14,2) -> 173390.1 | L14: =IF(A14>'Premissas'!$B$20,INDEX($K$5:$K$28,MAX(1,A14-'Premissas'!$B$20)),0) -> 144491.75 | M14: =ROUND(I14*'Premissas'!$B$10,2) -> 30015 | N14: =ROUND(I14*'Premissas'!$B$11,2) -> 6003 | O14: =ROUND(B14*'Premissas'!$B$29*'Premissas'!$B$6,2) -> 112500 | P14: =ROUND(B14*'Premissas'!$B$13*'Premissas'!$B$6,2) -> 7500 | Q14: =ROUND(D14*'Premissas'!$B$15,2) -> 30000 | R14: =ROUND(Q14*'Premissas'!$B$19+Q13*(1-'Premissas'!$B$19),2) -> 30000 | S14: =ROUND(E14*'Premissas'!$B$17,2) -> 14400 | T14: =ROUND(Q14*'Premissas'!$B$10,2) -> 4500 | U14: =ROUND(R14*'Premissas'!$B$18,2) -> 1500 | V14: =IF(A14<=12,'Premissas'!$B$24,'Premissas'!$B$25) -> 37000 | W14: =ROUND(G14+Q14,2) -> 247500 | X14: =ROUND(I14+Q14,2) -> 230100 | Y14: =ROUND(L14+R14,2) -> 174491.75 | Z14: =ROUND(SUM(M14:P14)+SUM(S14:V14),2) -> 213418 | AA14: =ROUND(Y14-Z14,2) -> -38926.25 | AB14: =ROUND(AB13+AA14,2) -> -536342.4 | AC14: =ROUND(X14-J14-SUM(M14:P14)-S14-T14-ROUND(Q14*'Premissas'!$B$18,2)-V14,2) -> -10027.9 | AD14: =ROUND(SUM($K$5:K14)-SUM($L$5:L14)+SUM($Q$5:Q14)-SUM($R$5:R14),2) -> 188390.1 | AE14: =MAX(0,AB14)*'Premissas'!$B$28 -> 0 | AF14: =IF(AB14>=0,A14,999) -> 999 | AG14: =IF(AE14>=Resumo!$E$8,A14,999) -> 999 | AH14: =AB14+Capital!$A$5 -> -436342.4 | AI14: =AB14+Capital!$A$6 -> -386342.4 | AJ14: =AB14+Capital!$A$7 -> -336342.4
A15: 11 | B15: ='Base'!B15 -> 1750 | C15: =ROUNDUP(B15/'Premissas'!$B$14,0) -> 87500 | D15: ='Base'!D15 -> 1 | E15: =D15*'Premissas'!$B$16 -> 80 | F15: =ROUND(B15*'Premissas'!$B$5,2) -> 50750 | G15: =ROUND(F15*'Premissas'!$B$6,2) -> 253750 | H15: =ROUND(G15*'Premissas'!$B$7,2) -> 20300 | I15: =ROUND(G15-H15,2) -> 233450 | J15: =ROUND(I15*'Premissas'!$B$8+B15*(1-'Premissas'!$B$7)*'Premissas'!$B$9*'Premissas'!$B$6,2) -> 31161.55 | K15: =ROUND(I15-J15,2) -> 202288.45 | L15: =IF(A15>'Premissas'!$B$20,INDEX($K$5:$K$28,MAX(1,A15-'Premissas'!$B$20)),0) -> 173390.1 | M15: =ROUND(I15*'Premissas'!$B$10,2) -> 35017.5 | N15: =ROUND(I15*'Premissas'!$B$11,2) -> 7003.5 | O15: =ROUND(B15*'Premissas'!$B$29*'Premissas'!$B$6,2) -> 131250 | P15: =ROUND(B15*'Premissas'!$B$13*'Premissas'!$B$6,2) -> 8750 | Q15: =ROUND(D15*'Premissas'!$B$15,2) -> 30000 | R15: =ROUND(Q15*'Premissas'!$B$19+Q14*(1-'Premissas'!$B$19),2) -> 30000 | S15: =ROUND(E15*'Premissas'!$B$17,2) -> 14400 | T15: =ROUND(Q15*'Premissas'!$B$10,2) -> 4500 | U15: =ROUND(R15*'Premissas'!$B$18,2) -> 1500 | V15: =IF(A15<=12,'Premissas'!$B$24,'Premissas'!$B$25) -> 37000 | W15: =ROUND(G15+Q15,2) -> 283750 | X15: =ROUND(I15+Q15,2) -> 263450 | Y15: =ROUND(L15+R15,2) -> 203390.1 | Z15: =ROUND(SUM(M15:P15)+SUM(S15:V15),2) -> 239421 | AA15: =ROUND(Y15-Z15,2) -> -36030.9 | AB15: =ROUND(AB14+AA15,2) -> -572373.3 | AC15: =ROUND(X15-J15-SUM(M15:P15)-S15-T15-ROUND(Q15*'Premissas'!$B$18,2)-V15,2) -> -7132.55 | AD15: =ROUND(SUM($K$5:K15)-SUM($L$5:L15)+SUM($Q$5:Q15)-SUM($R$5:R15),2) -> 217288.45 | AE15: =MAX(0,AB15)*'Premissas'!$B$28 -> 0 | AF15: =IF(AB15>=0,A15,999) -> 999 | AG15: =IF(AE15>=Resumo!$E$8,A15,999) -> 999 | AH15: =AB15+Capital!$A$5 -> -472373.3 | AI15: =AB15+Capital!$A$6 -> -422373.3 | AJ15: =AB15+Capital!$A$7 -> -372373.3
A16: 12 | B16: ='Base'!B16 -> 2000 | C16: =ROUNDUP(B16/'Premissas'!$B$14,0) -> 100000 | D16: ='Base'!D16 -> 1 | E16: =D16*'Premissas'!$B$16 -> 80 | F16: =ROUND(B16*'Premissas'!$B$5,2) -> 58000 | G16: =ROUND(F16*'Premissas'!$B$6,2) -> 290000 | H16: =ROUND(G16*'Premissas'!$B$7,2) -> 23200 | I16: =ROUND(G16-H16,2) -> 266800 | J16: =ROUND(I16*'Premissas'!$B$8+B16*(1-'Premissas'!$B$7)*'Premissas'!$B$9*'Premissas'!$B$6,2) -> 35613.2 | K16: =ROUND(I16-J16,2) -> 231186.8 | L16: =IF(A16>'Premissas'!$B$20,INDEX($K$5:$K$28,MAX(1,A16-'Premissas'!$B$20)),0) -> 202288.45 | M16: =ROUND(I16*'Premissas'!$B$10,2) -> 40020 | N16: =ROUND(I16*'Premissas'!$B$11,2) -> 8004 | O16: =ROUND(B16*'Premissas'!$B$29*'Premissas'!$B$6,2) -> 150000 | P16: =ROUND(B16*'Premissas'!$B$13*'Premissas'!$B$6,2) -> 10000 | Q16: =ROUND(D16*'Premissas'!$B$15,2) -> 30000 | R16: =ROUND(Q16*'Premissas'!$B$19+Q15*(1-'Premissas'!$B$19),2) -> 30000 | S16: =ROUND(E16*'Premissas'!$B$17,2) -> 14400 | T16: =ROUND(Q16*'Premissas'!$B$10,2) -> 4500 | U16: =ROUND(R16*'Premissas'!$B$18,2) -> 1500 | V16: =IF(A16<=12,'Premissas'!$B$24,'Premissas'!$B$25) -> 37000 | W16: =ROUND(G16+Q16,2) -> 320000 | X16: =ROUND(I16+Q16,2) -> 296800 | Y16: =ROUND(L16+R16,2) -> 232288.45 | Z16: =ROUND(SUM(M16:P16)+SUM(S16:V16),2) -> 265424 | AA16: =ROUND(Y16-Z16,2) -> -33135.55 | AB16: =ROUND(AB15+AA16,2) -> -605508.85 | AC16: =ROUND(X16-J16-SUM(M16:P16)-S16-T16-ROUND(Q16*'Premissas'!$B$18,2)-V16,2) -> -4237.2 | AD16: =ROUND(SUM($K$5:K16)-SUM($L$5:L16)+SUM($Q$5:Q16)-SUM($R$5:R16),2) -> 246186.8 | AE16: =MAX(0,AB16)*'Premissas'!$B$28 -> 0 | AF16: =IF(AB16>=0,A16,999) -> 999 | AG16: =IF(AE16>=Resumo!$E$8,A16,999) -> 999 | AH16: =AB16+Capital!$A$5 -> -505508.85 | AI16: =AB16+Capital!$A$6 -> -455508.85 | AJ16: =AB16+Capital!$A$7 -> -405508.85
A17: 13 | B17: ='Base'!B17 -> 2200 | C17: =ROUNDUP(B17/'Premissas'!$B$14,0) -> 110000 | D17: ='Base'!D17 -> 2 | E17: =D17*'Premissas'!$B$16 -> 160 | F17: =ROUND(B17*'Premissas'!$B$5,2) -> 63800 | G17: =ROUND(F17*'Premissas'!$B$6,2) -> 319000 | H17: =ROUND(G17*'Premissas'!$B$7,2) -> 25520 | I17: =ROUND(G17-H17,2) -> 293480 | J17: =ROUND(I17*'Premissas'!$B$8+B17*(1-'Premissas'!$B$7)*'Premissas'!$B$9*'Premissas'!$B$6,2) -> 39174.52 | K17: =ROUND(I17-J17,2) -> 254305.48 | L17: =IF(A17>'Premissas'!$B$20,INDEX($K$5:$K$28,MAX(1,A17-'Premissas'!$B$20)),0) -> 231186.8 | M17: =ROUND(I17*'Premissas'!$B$10,2) -> 44022 | N17: =ROUND(I17*'Premissas'!$B$11,2) -> 8804.4 | O17: =ROUND(B17*'Premissas'!$B$29*'Premissas'!$B$6,2) -> 165000 | P17: =ROUND(B17*'Premissas'!$B$13*'Premissas'!$B$6,2) -> 11000 | Q17: =ROUND(D17*'Premissas'!$B$15,2) -> 60000 | R17: =ROUND(Q17*'Premissas'!$B$19+Q16*(1-'Premissas'!$B$19),2) -> 45000 | S17: =ROUND(E17*'Premissas'!$B$17,2) -> 28800 | T17: =ROUND(Q17*'Premissas'!$B$10,2) -> 9000 | U17: =ROUND(R17*'Premissas'!$B$18,2) -> 2250 | V17: =IF(A17<=12,'Premissas'!$B$24,'Premissas'!$B$25) -> 42000 | W17: =ROUND(G17+Q17,2) -> 379000 | X17: =ROUND(I17+Q17,2) -> 353480 | Y17: =ROUND(L17+R17,2) -> 276186.8 | Z17: =ROUND(SUM(M17:P17)+SUM(S17:V17),2) -> 310876.4 | AA17: =ROUND(Y17-Z17,2) -> -34689.6 | AB17: =ROUND(AB16+AA17,2) -> -640198.45 | AC17: =ROUND(X17-J17-SUM(M17:P17)-S17-T17-ROUND(Q17*'Premissas'!$B$18,2)-V17,2) -> 2679.08 | AD17: =ROUND(SUM($K$5:K17)-SUM($L$5:L17)+SUM($Q$5:Q17)-SUM($R$5:R17),2) -> 284305.48 | AE17: =MAX(0,AB17)*'Premissas'!$B$28 -> 0 | AF17: =IF(AB17>=0,A17,999) -> 999 | AG17: =IF(AE17>=Resumo!$E$8,A17,999) -> 999 | AH17: =AB17+Capital!$A$5 -> -540198.45 | AI17: =AB17+Capital!$A$6 -> -490198.45 | AJ17: =AB17+Capital!$A$7 -> -440198.45
... A28: 24 | B28: ='Base'!B28 -> 3000 | C28: =ROUNDUP(B28/'Premissas'!$B$14,0) -> 150000 | D28: ='Base'!D28 -> 2 | E28: =D28*'Premissas'!$B$16 -> 160 | F28: =ROUND(B28*'Premissas'!$B$5,2) -> 87000 | G28: =ROUND(F28*'Premissas'!$B$6,2) -> 435000 | H28: =ROUND(G28*'Premissas'!$B$7,2) -> 34800 | I28: =ROUND(G28-H28,2) -> 400200 | J28: =ROUND(I28*'Premissas'!$B$8+B28*(1-'Premissas'!$B$7)*'Premissas'!$B$9*'Premissas'!$B$6,2) -> 53419.8 | K28: =ROUND(I28-J28,2) -> 346780.2 | L28: =IF(A28>'Premissas'!$B$20,INDEX($K$5:$K$28,MAX(1,A28-'Premissas'!$B$20)),0) -> 346780.2 | M28: =ROUND(I28*'Premissas'!$B$10,2) -> 60030 | N28: =ROUND(I28*'Premissas'!$B$11,2) -> 12006 | O28: =ROUND(B28*'Premissas'!$B$29*'Premissas'!$B$6,2) -> 225000 | P28: =ROUND(B28*'Premissas'!$B$13*'Premissas'!$B$6,2) -> 15000 | Q28: =ROUND(D28*'Premissas'!$B$15,2) -> 60000 | R28: =ROUND(Q28*'Premissas'!$B$19+Q27*(1-'Premissas'!$B$19),2) -> 60000 | S28: =ROUND(E28*'Premissas'!$B$17,2) -> 28800 | T28: =ROUND(Q28*'Premissas'!$B$10,2) -> 9000 | U28: =ROUND(R28*'Premissas'!$B$18,2) -> 3000 | V28: =IF(A28<=12,'Premissas'!$B$24,'Premissas'!$B$25) -> 42000 | W28: =ROUND(G28+Q28,2) -> 495000 | X28: =ROUND(I28+Q28,2) -> 460200 | Y28: =ROUND(L28+R28,2) -> 406780.2 | Z28: =ROUND(SUM(M28:P28)+SUM(S28:V28),2) -> 394836 | AA28: =ROUND(Y28-Z28,2) -> 11944.2 | AB28: =ROUND(AB27+AA28,2) -> -615184.65 | AC28: =ROUND(X28-J28-SUM(M28:P28)-S28-T28-ROUND(Q28*'Premissas'!$B$18,2)-V28,2) -> 11944.2 | AD28: =ROUND(SUM($K$5:K28)-SUM($L$5:L28)+SUM($Q$5:Q28)-SUM($R$5:R28),2) -> 376780.2 | AE28: =MAX(0,AB28)*'Premissas'!$B$28 -> 0 | AF28: =IF(AB28>=0,A28,999) -> 999 | AG28: =IF(AE28>=Resumo!$E$8,A28,999) -> 999 | AH28: =AB28+Capital!$A$5 -> -515184.65 | AI28: =AB28+Capital!$A$6 -> -465184.65 | AJ28: =AB28+Capital!$A$7 -> -415184.65

Sheet FX4,5
A1: FX4,5 | fluxo mensal em BRL, salvo indicação
A2: Agenda vinculada à Base; nenhum aumento de vendas. Câmbio de R$5 para R$4,50 por USD, demais premissas iguais | M0 separado: -R$100 mil nas premissas. Acumulado exclui aportes/distribuição.
A4: Mês | B4: Pedidos aprovados | C4: Visitas qualificadas | D4: Mapas faturados | E4: Horas diretas TI | F4: Loja bruta USD | G4: Loja bruta BRL | H4: Estornos BRL | I4: Loja após estornos BRL | J4: Taxa plataforma BRL | K4: Liquidação gerada BRL | L4: Loja recebida BRL | M4: Tributos loja BRL | N4: Reserva meios/FX BRL | O4: Aquisição / mídia BRL | P4: Suporte loja BRL | Q4: Fatura TI BRL | R4: Recebimentos TI BRL | S4: Entrega TI BRL | T4: Tributos TI BRL | U4: Comercial TI caixa BRL | V4: Fixo BRL | W4: Vendas brutas BRL | X4: Receita após estornos BRL | Y4: Recebimentos BRL | Z4: Saídas caixa BRL | AA4: Fluxo líquido BRL | AB4: Acumulado sem aporte BRL | AC4: Resultado competência BRL | AD4: A receber BRL | AE4: 50% excedente positivo BRL | AF4: Mês elegível payback projeto | AG4: Mês elegível Dani hipotético | AH4: Saldo com 100k | AI4: Saldo com 150k | AJ4: Saldo com 200k
A5: 1 | B5: ='Base'!B5 -> 0 | C5: =ROUNDUP(B5/'Premissas'!$B$14,0) -> 0 | D5: ='Base'!D5 -> 0 | E5: =D5*'Premissas'!$B$16 -> 0 | F5: =ROUND(B5*'Premissas'!$B$5,2) -> 0 | G5: =ROUND(F5*'Premissas'!$B$30,2) -> 0 | H5: =ROUND(G5*'Premissas'!$B$7,2) -> 0 | I5: =ROUND(G5-H5,2) -> 0 | J5: =ROUND(I5*'Premissas'!$B$8+B5*(1-'Premissas'!$B$7)*'Premissas'!$B$9*'Premissas'!$B$30,2) -> 0 | K5: =ROUND(I5-J5,2) -> 0 | L5: =IF(A5>'Premissas'!$B$20,INDEX($K$5:$K$28,MAX(1,A5-'Premissas'!$B$20)),0) -> 0 | M5: =ROUND(I5*'Premissas'!$B$10,2) -> 0 | N5: =ROUND(I5*'Premissas'!$B$11,2) -> 0 | O5: =ROUND(B5*'Premissas'!$B$12*'Premissas'!$B$30,2) -> 0 | P5: =ROUND(B5*'Premissas'!$B$13*'Premissas'!$B$30,2) -> 0 | Q5: =ROUND(D5*'Premissas'!$B$15,2) -> 0 | R5: =ROUND(Q5*'Premissas'!$B$19+0*(1-'Premissas'!$B$19),2) -> 0 | S5: =ROUND(E5*'Premissas'!$B$17,2) -> 0 | T5: =ROUND(Q5*'Premissas'!$B$10,2) -> 0 | U5: =ROUND(R5*'Premissas'!$B$18,2) -> 0 | V5: =IF(A5<=12,'Premissas'!$B$24,'Premissas'!$B$25) -> 37000 | W5: =ROUND(G5+Q5,2) -> 0 | X5: =ROUND(I5+Q5,2) -> 0 | Y5: =ROUND(L5+R5,2) -> 0 | Z5: =ROUND(SUM(M5:P5)+SUM(S5:V5),2) -> 37000 | AA5: =ROUND(Y5-Z5,2) -> -37000 | AB5: =ROUND(-'Premissas'!$B$23+AA5,2) -> -137000 | AC5: =ROUND(X5-J5-SUM(M5:P5)-S5-T5-ROUND(Q5*'Premissas'!$B$18,2)-V5,2) -> -37000 | AD5: =ROUND(SUM($K$5:K5)-SUM($L$5:L5)+SUM($Q$5:Q5)-SUM($R$5:R5),2) -> 0 | AE5: =MAX(0,AB5)*'Premissas'!$B$28 -> 0 | AF5: =IF(AB5>=0,A5,999) -> 999 | AG5: =IF(AE5>=Resumo!$E$9,A5,999) -> 999 | AH5: =AB5+Capital!$A$5 -> -37000 | AI5: =AB5+Capital!$A$6 -> 13000 | AJ5: =AB5+Capital!$A$7 -> 63000
A6: 2 | B6: ='Base'!B6 -> 0 | C6: =ROUNDUP(B6/'Premissas'!$B$14,0) -> 0 | D6: ='Base'!D6 -> 0 | E6: =D6*'Premissas'!$B$16 -> 0 | F6: =ROUND(B6*'Premissas'!$B$5,2) -> 0 | G6: =ROUND(F6*'Premissas'!$B$30,2) -> 0 | H6: =ROUND(G6*'Premissas'!$B$7,2) -> 0 | I6: =ROUND(G6-H6,2) -> 0 | J6: =ROUND(I6*'Premissas'!$B$8+B6*(1-'Premissas'!$B$7)*'Premissas'!$B$9*'Premissas'!$B$30,2) -> 0 | K6: =ROUND(I6-J6,2) -> 0 | L6: =IF(A6>'Premissas'!$B$20,INDEX($K$5:$K$28,MAX(1,A6-'Premissas'!$B$20)),0) -> 0 | M6: =ROUND(I6*'Premissas'!$B$10,2) -> 0 | N6: =ROUND(I6*'Premissas'!$B$11,2) -> 0 | O6: =ROUND(B6*'Premissas'!$B$12*'Premissas'!$B$30,2) -> 0 | P6: =ROUND(B6*'Premissas'!$B$13*'Premissas'!$B$30,2) -> 0 | Q6: =ROUND(D6*'Premissas'!$B$15,2) -> 0 | R6: =ROUND(Q6*'Premissas'!$B$19+Q5*(1-'Premissas'!$B$19),2) -> 0 | S6: =ROUND(E6*'Premissas'!$B$17,2) -> 0 | T6: =ROUND(Q6*'Premissas'!$B$10,2) -> 0 | U6: =ROUND(R6*'Premissas'!$B$18,2) -> 0 | V6: =IF(A6<=12,'Premissas'!$B$24,'Premissas'!$B$25) -> 37000 | W6: =ROUND(G6+Q6,2) -> 0 | X6: =ROUND(I6+Q6,2) -> 0 | Y6: =ROUND(L6+R6,2) -> 0 | Z6: =ROUND(SUM(M6:P6)+SUM(S6:V6),2) -> 37000 | AA6: =ROUND(Y6-Z6,2) -> -37000 | AB6: =ROUND(AB5+AA6,2) -> -174000 | AC6: =ROUND(X6-J6-SUM(M6:P6)-S6-T6-ROUND(Q6*'Premissas'!$B$18,2)-V6,2) -> -37000 | AD6: =ROUND(SUM($K$5:K6)-SUM($L$5:L6)+SUM($Q$5:Q6)-SUM($R$5:R6),2) -> 0 | AE6: =MAX(0,AB6)*'Premissas'!$B$28 -> 0 | AF6: =IF(AB6>=0,A6,999) -> 999 | AG6: =IF(AE6>=Resumo!$E$9,A6,999) -> 999 | AH6: =AB6+Capital!$A$5 -> -74000 | AI6: =AB6+Capital!$A$6 -> -24000 | AJ6: =AB6+Capital!$A$7 -> 26000
A7: 3 | B7: ='Base'!B7 -> 50 | C7: =ROUNDUP(B7/'Premissas'!$B$14,0) -> 2500 | D7: ='Base'!D7 -> 1 | E7: =D7*'Premissas'!$B$16 -> 80 | F7: =ROUND(B7*'Premissas'!$B$5,2) -> 1450 | G7: =ROUND(F7*'Premissas'!$B$30,2) -> 6525 | H7: =ROUND(G7*'Premissas'!$B$7,2) -> 522 | I7: =ROUND(G7-H7,2) -> 6003 | J7: =ROUND(I7*'Premissas'!$B$8+B7*(1-'Premissas'!$B$7)*'Premissas'!$B$9*'Premissas'!$B$30,2) -> 801.3 | K7: =ROUND(I7-J7,2) -> 5201.7 | L7: =IF(A7>'Premissas'!$B$20,INDEX($K$5:$K$28,MAX(1,A7-'Premissas'!$B$20)),0) -> 0 | M7: =ROUND(I7*'Premissas'!$B$10,2) -> 900.45 | N7: =ROUND(I7*'Premissas'!$B$11,2) -> 180.09 | O7: =ROUND(B7*'Premissas'!$B$12*'Premissas'!$B$30,2) -> 2250 | P7: =ROUND(B7*'Premissas'!$B$13*'Premissas'!$B$30,2) -> 225 | Q7: =ROUND(D7*'Premissas'!$B$15,2) -> 30000 | R7: =ROUND(Q7*'Premissas'!$B$19+Q6*(1-'Premissas'!$B$19),2) -> 15000 | S7: =ROUND(E7*'Premissas'!$B$17,2) -> 14400 | T7: =ROUND(Q7*'Premissas'!$B$10,2) -> 4500 | U7: =ROUND(R7*'Premissas'!$B$18,2) -> 750 | V7: =IF(A7<=12,'Premissas'!$B$24,'Premissas'!$B$25) -> 37000 | W7: =ROUND(G7+Q7,2) -> 36525 | X7: =ROUND(I7+Q7,2) -> 36003 | Y7: =ROUND(L7+R7,2) -> 15000 | Z7: =ROUND(SUM(M7:P7)+SUM(S7:V7),2) -> 60205.54 | AA7: =ROUND(Y7-Z7,2) -> -45205.54 | AB7: =ROUND(AB6+AA7,2) -> -219205.54 | AC7: =ROUND(X7-J7-SUM(M7:P7)-S7-T7-ROUND(Q7*'Premissas'!$B$18,2)-V7,2) -> -25753.84 | AD7: =ROUND(SUM($K$5:K7)-SUM($L$5:L7)+SUM($Q$5:Q7)-SUM($R$5:R7),2) -> 20201.7 | AE7: =MAX(0,AB7)*'Premissas'!$B$28 -> 0 | AF7: =IF(AB7>=0,A7,999) -> 999 | AG7: =IF(AE7>=Resumo!$E$9,A7,999) -> 999 | AH7: =AB7+Capital!$A$5 -> -119205.54 | AI7: =AB7+Capital!$A$6 -> -69205.54 | AJ7: =AB7+Capital!$A$7 -> -19205.54
A8: 4 | B8: ='Base'!B8 -> 150 | C8: =ROUNDUP(B8/'Premissas'!$B$14,0) -> 7500 | D8: ='Base'!D8 -> 0 | E8: =D8*'Premissas'!$B$16 -> 0 | F8: =ROUND(B8*'Premissas'!$B$5,2) -> 4350 | G8: =ROUND(F8*'Premissas'!$B$30,2) -> 19575 | H8: =ROUND(G8*'Premissas'!$B$7,2) -> 1566 | I8: =ROUND(G8-H8,2) -> 18009 | J8: =ROUND(I8*'Premissas'!$B$8+B8*(1-'Premissas'!$B$7)*'Premissas'!$B$9*'Premissas'!$B$30,2) -> 2403.89 | K8: =ROUND(I8-J8,2) -> 15605.11 | L8: =IF(A8>'Premissas'!$B$20,INDEX($K$5:$K$28,MAX(1,A8-'Premissas'!$B$20)),0) -> 5201.7 | M8: =ROUND(I8*'Premissas'!$B$10,2) -> 2701.35 | N8: =ROUND(I8*'Premissas'!$B$11,2) -> 540.27 | O8: =ROUND(B8*'Premissas'!$B$12*'Premissas'!$B$30,2) -> 6750 | P8: =ROUND(B8*'Premissas'!$B$13*'Premissas'!$B$30,2) -> 675 | Q8: =ROUND(D8*'Premissas'!$B$15,2) -> 0 | R8: =ROUND(Q8*'Premissas'!$B$19+Q7*(1-'Premissas'!$B$19),2) -> 15000 | S8: =ROUND(E8*'Premissas'!$B$17,2) -> 0 | T8: =ROUND(Q8*'Premissas'!$B$10,2) -> 0 | U8: =ROUND(R8*'Premissas'!$B$18,2) -> 750 | V8: =IF(A8<=12,'Premissas'!$B$24,'Premissas'!$B$25) -> 37000 | W8: =ROUND(G8+Q8,2) -> 19575 | X8: =ROUND(I8+Q8,2) -> 18009 | Y8: =ROUND(L8+R8,2) -> 20201.7 | Z8: =ROUND(SUM(M8:P8)+SUM(S8:V8),2) -> 48416.62 | AA8: =ROUND(Y8-Z8,2) -> -28214.92 | AB8: =ROUND(AB7+AA8,2) -> -247420.46 | AC8: =ROUND(X8-J8-SUM(M8:P8)-S8-T8-ROUND(Q8*'Premissas'!$B$18,2)-V8,2) -> -32061.51 | AD8: =ROUND(SUM($K$5:K8)-SUM($L$5:L8)+SUM($Q$5:Q8)-SUM($R$5:R8),2) -> 15605.11 | AE8: =MAX(0,AB8)*'Premissas'!$B$28 -> 0 | AF8: =IF(AB8>=0,A8,999) -> 999 | AG8: =IF(AE8>=Resumo!$E$9,A8,999) -> 999 | AH8: =AB8+Capital!$A$5 -> -147420.46 | AI8: =AB8+Capital!$A$6 -> -97420.46 | AJ8: =AB8+Capital!$A$7 -> -47420.46
A9: 5 | B9: ='Base'!B9 -> 300 | C9: =ROUNDUP(B9/'Premissas'!$B$14,0) -> 15000 | D9: ='Base'!D9 -> 1 | E9: =D9*'Premissas'!$B$16 -> 80 | F9: =ROUND(B9*'Premissas'!$B$5,2) -> 8700 | G9: =ROUND(F9*'Premissas'!$B$30,2) -> 39150 | H9: =ROUND(G9*'Premissas'!$B$7,2) -> 3132 | I9: =ROUND(G9-H9,2) -> 36018 | J9: =ROUND(I9*'Premissas'!$B$8+B9*(1-'Premissas'!$B$7)*'Premissas'!$B$9*'Premissas'!$B$30,2) -> 4807.78 | K9: =ROUND(I9-J9,2) -> 31210.22 | L9: =IF(A9>'Premissas'!$B$20,INDEX($K$5:$K$28,MAX(1,A9-'Premissas'!$B$20)),0) -> 15605.11 | M9: =ROUND(I9*'Premissas'!$B$10,2) -> 5402.7 | N9: =ROUND(I9*'Premissas'!$B$11,2) -> 1080.54 | O9: =ROUND(B9*'Premissas'!$B$12*'Premissas'!$B$30,2) -> 13500 | P9: =ROUND(B9*'Premissas'!$B$13*'Premissas'!$B$30,2) -> 1350 | Q9: =ROUND(D9*'Premissas'!$B$15,2) -> 30000 | R9: =ROUND(Q9*'Premissas'!$B$19+Q8*(1-'Premissas'!$B$19),2) -> 15000 | S9: =ROUND(E9*'Premissas'!$B$17,2) -> 14400 | T9: =ROUND(Q9*'Premissas'!$B$10,2) -> 4500 | U9: =ROUND(R9*'Premissas'!$B$18,2) -> 750 | V9: =IF(A9<=12,'Premissas'!$B$24,'Premissas'!$B$25) -> 37000 | W9: =ROUND(G9+Q9,2) -> 69150 | X9: =ROUND(I9+Q9,2) -> 66018 | Y9: =ROUND(L9+R9,2) -> 30605.11 | Z9: =ROUND(SUM(M9:P9)+SUM(S9:V9),2) -> 77983.24 | AA9: =ROUND(Y9-Z9,2) -> -47378.13 | AB9: =ROUND(AB8+AA9,2) -> -294798.59 | AC9: =ROUND(X9-J9-SUM(M9:P9)-S9-T9-ROUND(Q9*'Premissas'!$B$18,2)-V9,2) -> -17523.02 | AD9: =ROUND(SUM($K$5:K9)-SUM($L$5:L9)+SUM($Q$5:Q9)-SUM($R$5:R9),2) -> 46210.22 | AE9: =MAX(0,AB9)*'Premissas'!$B$28 -> 0 | AF9: =IF(AB9>=0,A9,999) -> 999 | AG9: =IF(AE9>=Resumo!$E$9,A9,999) -> 999 | AH9: =AB9+Capital!$A$5 -> -194798.59 | AI9: =AB9+Capital!$A$6 -> -144798.59 | AJ9: =AB9+Capital!$A$7 -> -94798.59
A10: 6 | B10: ='Base'!B10 -> 500 | C10: =ROUNDUP(B10/'Premissas'!$B$14,0) -> 25000 | D10: ='Base'!D10 -> 0 | E10: =D10*'Premissas'!$B$16 -> 0 | F10: =ROUND(B10*'Premissas'!$B$5,2) -> 14500 | G10: =ROUND(F10*'Premissas'!$B$30,2) -> 65250 | H10: =ROUND(G10*'Premissas'!$B$7,2) -> 5220 | I10: =ROUND(G10-H10,2) -> 60030 | J10: =ROUND(I10*'Premissas'!$B$8+B10*(1-'Premissas'!$B$7)*'Premissas'!$B$9*'Premissas'!$B$30,2) -> 8012.97 | K10: =ROUND(I10-J10,2) -> 52017.03 | L10: =IF(A10>'Premissas'!$B$20,INDEX($K$5:$K$28,MAX(1,A10-'Premissas'!$B$20)),0) -> 31210.22 | M10: =ROUND(I10*'Premissas'!$B$10,2) -> 9004.5 | N10: =ROUND(I10*'Premissas'!$B$11,2) -> 1800.9 | O10: =ROUND(B10*'Premissas'!$B$12*'Premissas'!$B$30,2) -> 22500 | P10: =ROUND(B10*'Premissas'!$B$13*'Premissas'!$B$30,2) -> 2250 | Q10: =ROUND(D10*'Premissas'!$B$15,2) -> 0 | R10: =ROUND(Q10*'Premissas'!$B$19+Q9*(1-'Premissas'!$B$19),2) -> 15000 | S10: =ROUND(E10*'Premissas'!$B$17,2) -> 0 | T10: =ROUND(Q10*'Premissas'!$B$10,2) -> 0 | U10: =ROUND(R10*'Premissas'!$B$18,2) -> 750 | V10: =IF(A10<=12,'Premissas'!$B$24,'Premissas'!$B$25) -> 37000 | W10: =ROUND(G10+Q10,2) -> 65250 | X10: =ROUND(I10+Q10,2) -> 60030 | Y10: =ROUND(L10+R10,2) -> 46210.22 | Z10: =ROUND(SUM(M10:P10)+SUM(S10:V10),2) -> 73305.4 | AA10: =ROUND(Y10-Z10,2) -> -27095.18 | AB10: =ROUND(AB9+AA10,2) -> -321893.77 | AC10: =ROUND(X10-J10-SUM(M10:P10)-S10-T10-ROUND(Q10*'Premissas'!$B$18,2)-V10,2) -> -20538.37 | AD10: =ROUND(SUM($K$5:K10)-SUM($L$5:L10)+SUM($Q$5:Q10)-SUM($R$5:R10),2) -> 52017.03 | AE10: =MAX(0,AB10)*'Premissas'!$B$28 -> 0 | AF10: =IF(AB10>=0,A10,999) -> 999 | AG10: =IF(AE10>=Resumo!$E$9,A10,999) -> 999 | AH10: =AB10+Capital!$A$5 -> -221893.77 | AI10: =AB10+Capital!$A$6 -> -171893.77 | AJ10: =AB10+Capital!$A$7 -> -121893.77
A11: 7 | B11: ='Base'!B11 -> 750 | C11: =ROUNDUP(B11/'Premissas'!$B$14,0) -> 37500 | D11: ='Base'!D11 -> 1 | E11: =D11*'Premissas'!$B$16 -> 80 | F11: =ROUND(B11*'Premissas'!$B$5,2) -> 21750 | G11: =ROUND(F11*'Premissas'!$B$30,2) -> 97875 | H11: =ROUND(G11*'Premissas'!$B$7,2) -> 7830 | I11: =ROUND(G11-H11,2) -> 90045 | J11: =ROUND(I11*'Premissas'!$B$8+B11*(1-'Premissas'!$B$7)*'Premissas'!$B$9*'Premissas'!$B$30,2) -> 12019.46 | K11: =ROUND(I11-J11,2) -> 78025.54 | L11: =IF(A11>'Premissas'!$B$20,INDEX($K$5:$K$28,MAX(1,A11-'Premissas'!$B$20)),0) -> 52017.03 | M11: =ROUND(I11*'Premissas'!$B$10,2) -> 13506.75 | N11: =ROUND(I11*'Premissas'!$B$11,2) -> 2701.35 | O11: =ROUND(B11*'Premissas'!$B$12*'Premissas'!$B$30,2) -> 33750 | P11: =ROUND(B11*'Premissas'!$B$13*'Premissas'!$B$30,2) -> 3375 | Q11: =ROUND(D11*'Premissas'!$B$15,2) -> 30000 | R11: =ROUND(Q11*'Premissas'!$B$19+Q10*(1-'Premissas'!$B$19),2) -> 15000 | S11: =ROUND(E11*'Premissas'!$B$17,2) -> 14400 | T11: =ROUND(Q11*'Premissas'!$B$10,2) -> 4500 | U11: =ROUND(R11*'Premissas'!$B$18,2) -> 750 | V11: =IF(A11<=12,'Premissas'!$B$24,'Premissas'!$B$25) -> 37000 | W11: =ROUND(G11+Q11,2) -> 127875 | X11: =ROUND(I11+Q11,2) -> 120045 | Y11: =ROUND(L11+R11,2) -> 67017.03 | Z11: =ROUND(SUM(M11:P11)+SUM(S11:V11),2) -> 109983.1 | AA11: =ROUND(Y11-Z11,2) -> -42966.07 | AB11: =ROUND(AB10+AA11,2) -> -364859.84 | AC11: =ROUND(X11-J11-SUM(M11:P11)-S11-T11-ROUND(Q11*'Premissas'!$B$18,2)-V11,2) -> -2707.56 | AD11: =ROUND(SUM($K$5:K11)-SUM($L$5:L11)+SUM($Q$5:Q11)-SUM($R$5:R11),2) -> 93025.54 | AE11: =MAX(0,AB11)*'Premissas'!$B$28 -> 0 | AF11: =IF(AB11>=0,A11,999) -> 999 | AG11: =IF(AE11>=Resumo!$E$9,A11,999) -> 999 | AH11: =AB11+Capital!$A$5 -> -264859.84 | AI11: =AB11+Capital!$A$6 -> -214859.84 | AJ11: =AB11+Capital!$A$7 -> -164859.84
A12: 8 | B12: ='Base'!B12 -> 1000 | C12: =ROUNDUP(B12/'Premissas'!$B$14,0) -> 50000 | D12: ='Base'!D12 -> 1 | E12: =D12*'Premissas'!$B$16 -> 80 | F12: =ROUND(B12*'Premissas'!$B$5,2) -> 29000 | G12: =ROUND(F12*'Premissas'!$B$30,2) -> 130500 | H12: =ROUND(G12*'Premissas'!$B$7,2) -> 10440 | I12: =ROUND(G12-H12,2) -> 120060 | J12: =ROUND(I12*'Premissas'!$B$8+B12*(1-'Premissas'!$B$7)*'Premissas'!$B$9*'Premissas'!$B$30,2) -> 16025.94 | K12: =ROUND(I12-J12,2) -> 104034.06 | L12: =IF(A12>'Premissas'!$B$20,INDEX($K$5:$K$28,MAX(1,A12-'Premissas'!$B$20)),0) -> 78025.54 | M12: =ROUND(I12*'Premissas'!$B$10,2) -> 18009 | N12: =ROUND(I12*'Premissas'!$B$11,2) -> 3601.8 | O12: =ROUND(B12*'Premissas'!$B$12*'Premissas'!$B$30,2) -> 45000 | P12: =ROUND(B12*'Premissas'!$B$13*'Premissas'!$B$30,2) -> 4500 | Q12: =ROUND(D12*'Premissas'!$B$15,2) -> 30000 | R12: =ROUND(Q12*'Premissas'!$B$19+Q11*(1-'Premissas'!$B$19),2) -> 30000 | S12: =ROUND(E12*'Premissas'!$B$17,2) -> 14400 | T12: =ROUND(Q12*'Premissas'!$B$10,2) -> 4500 | U12: =ROUND(R12*'Premissas'!$B$18,2) -> 1500 | V12: =IF(A12<=12,'Premissas'!$B$24,'Premissas'!$B$25) -> 37000 | W12: =ROUND(G12+Q12,2) -> 160500 | X12: =ROUND(I12+Q12,2) -> 150060 | Y12: =ROUND(L12+R12,2) -> 108025.54 | Z12: =ROUND(SUM(M12:P12)+SUM(S12:V12),2) -> 128510.8 | AA12: =ROUND(Y12-Z12,2) -> -20485.26 | AB12: =ROUND(AB11+AA12,2) -> -385345.1 | AC12: =ROUND(X12-J12-SUM(M12:P12)-S12-T12-ROUND(Q12*'Premissas'!$B$18,2)-V12,2) -> 5523.26 | AD12: =ROUND(SUM($K$5:K12)-SUM($L$5:L12)+SUM($Q$5:Q12)-SUM($R$5:R12),2) -> 119034.06 | AE12: =MAX(0,AB12)*'Premissas'!$B$28 -> 0 | AF12: =IF(AB12>=0,A12,999) -> 999 | AG12: =IF(AE12>=Resumo!$E$9,A12,999) -> 999 | AH12: =AB12+Capital!$A$5 -> -285345.1 | AI12: =AB12+Capital!$A$6 -> -235345.1 | AJ12: =AB12+Capital!$A$7 -> -185345.1
A13: 9 | B13: ='Base'!B13 -> 1250 | C13: =ROUNDUP(B13/'Premissas'!$B$14,0) -> 62500 | D13: ='Base'!D13 -> 1 | E13: =D13*'Premissas'!$B$16 -> 80 | F13: =ROUND(B13*'Premissas'!$B$5,2) -> 36250 | G13: =ROUND(F13*'Premissas'!$B$30,2) -> 163125 | H13: =ROUND(G13*'Premissas'!$B$7,2) -> 13050 | I13: =ROUND(G13-H13,2) -> 150075 | J13: =ROUND(I13*'Premissas'!$B$8+B13*(1-'Premissas'!$B$7)*'Premissas'!$B$9*'Premissas'!$B$30,2) -> 20032.43 | K13: =ROUND(I13-J13,2) -> 130042.57 | L13: =IF(A13>'Premissas'!$B$20,INDEX($K$5:$K$28,MAX(1,A13-'Premissas'!$B$20)),0) -> 104034.06 | M13: =ROUND(I13*'Premissas'!$B$10,2) -> 22511.25 | N13: =ROUND(I13*'Premissas'!$B$11,2) -> 4502.25 | O13: =ROUND(B13*'Premissas'!$B$12*'Premissas'!$B$30,2) -> 56250 | P13: =ROUND(B13*'Premissas'!$B$13*'Premissas'!$B$30,2) -> 5625 | Q13: =ROUND(D13*'Premissas'!$B$15,2) -> 30000 | R13: =ROUND(Q13*'Premissas'!$B$19+Q12*(1-'Premissas'!$B$19),2) -> 30000 | S13: =ROUND(E13*'Premissas'!$B$17,2) -> 14400 | T13: =ROUND(Q13*'Premissas'!$B$10,2) -> 4500 | U13: =ROUND(R13*'Premissas'!$B$18,2) -> 1500 | V13: =IF(A13<=12,'Premissas'!$B$24,'Premissas'!$B$25) -> 37000 | W13: =ROUND(G13+Q13,2) -> 193125 | X13: =ROUND(I13+Q13,2) -> 180075 | Y13: =ROUND(L13+R13,2) -> 134034.06 | Z13: =ROUND(SUM(M13:P13)+SUM(S13:V13),2) -> 146288.5 | AA13: =ROUND(Y13-Z13,2) -> -12254.44 | AB13: =ROUND(AB12+AA13,2) -> -397599.54 | AC13: =ROUND(X13-J13-SUM(M13:P13)-S13-T13-ROUND(Q13*'Premissas'!$B$18,2)-V13,2) -> 13754.07 | AD13: =ROUND(SUM($K$5:K13)-SUM($L$5:L13)+SUM($Q$5:Q13)-SUM($R$5:R13),2) -> 145042.57 | AE13: =MAX(0,AB13)*'Premissas'!$B$28 -> 0 | AF13: =IF(AB13>=0,A13,999) -> 999 | AG13: =IF(AE13>=Resumo!$E$9,A13,999) -> 999 | AH13: =AB13+Capital!$A$5 -> -297599.54 | AI13: =AB13+Capital!$A$6 -> -247599.54 | AJ13: =AB13+Capital!$A$7 -> -197599.54
A14: 10 | B14: ='Base'!B14 -> 1500 | C14: =ROUNDUP(B14/'Premissas'!$B$14,0) -> 75000 | D14: ='Base'!D14 -> 1 | E14: =D14*'Premissas'!$B$16 -> 80 | F14: =ROUND(B14*'Premissas'!$B$5,2) -> 43500 | G14: =ROUND(F14*'Premissas'!$B$30,2) -> 195750 | H14: =ROUND(G14*'Premissas'!$B$7,2) -> 15660 | I14: =ROUND(G14-H14,2) -> 180090 | J14: =ROUND(I14*'Premissas'!$B$8+B14*(1-'Premissas'!$B$7)*'Premissas'!$B$9*'Premissas'!$B$30,2) -> 24038.91 | K14: =ROUND(I14-J14,2) -> 156051.09 | L14: =IF(A14>'Premissas'!$B$20,INDEX($K$5:$K$28,MAX(1,A14-'Premissas'!$B$20)),0) -> 130042.57 | M14: =ROUND(I14*'Premissas'!$B$10,2) -> 27013.5 | N14: =ROUND(I14*'Premissas'!$B$11,2) -> 5402.7 | O14: =ROUND(B14*'Premissas'!$B$12*'Premissas'!$B$30,2) -> 67500 | P14: =ROUND(B14*'Premissas'!$B$13*'Premissas'!$B$30,2) -> 6750 | Q14: =ROUND(D14*'Premissas'!$B$15,2) -> 30000 | R14: =ROUND(Q14*'Premissas'!$B$19+Q13*(1-'Premissas'!$B$19),2) -> 30000 | S14: =ROUND(E14*'Premissas'!$B$17,2) -> 14400 | T14: =ROUND(Q14*'Premissas'!$B$10,2) -> 4500 | U14: =ROUND(R14*'Premissas'!$B$18,2) -> 1500 | V14: =IF(A14<=12,'Premissas'!$B$24,'Premissas'!$B$25) -> 37000 | W14: =ROUND(G14+Q14,2) -> 225750 | X14: =ROUND(I14+Q14,2) -> 210090 | Y14: =ROUND(L14+R14,2) -> 160042.57 | Z14: =ROUND(SUM(M14:P14)+SUM(S14:V14),2) -> 164066.2 | AA14: =ROUND(Y14-Z14,2) -> -4023.63 | AB14: =ROUND(AB13+AA14,2) -> -401623.17 | AC14: =ROUND(X14-J14-SUM(M14:P14)-S14-T14-ROUND(Q14*'Premissas'!$B$18,2)-V14,2) -> 21984.89 | AD14: =ROUND(SUM($K$5:K14)-SUM($L$5:L14)+SUM($Q$5:Q14)-SUM($R$5:R14),2) -> 171051.09 | AE14: =MAX(0,AB14)*'Premissas'!$B$28 -> 0 | AF14: =IF(AB14>=0,A14,999) -> 999 | AG14: =IF(AE14>=Resumo!$E$9,A14,999) -> 999 | AH14: =AB14+Capital!$A$5 -> -301623.17 | AI14: =AB14+Capital!$A$6 -> -251623.17 | AJ14: =AB14+Capital!$A$7 -> -201623.17
A15: 11 | B15: ='Base'!B15 -> 1750 | C15: =ROUNDUP(B15/'Premissas'!$B$14,0) -> 87500 | D15: ='Base'!D15 -> 1 | E15: =D15*'Premissas'!$B$16 -> 80 | F15: =ROUND(B15*'Premissas'!$B$5,2) -> 50750 | G15: =ROUND(F15*'Premissas'!$B$30,2) -> 228375 | H15: =ROUND(G15*'Premissas'!$B$7,2) -> 18270 | I15: =ROUND(G15-H15,2) -> 210105 | J15: =ROUND(I15*'Premissas'!$B$8+B15*(1-'Premissas'!$B$7)*'Premissas'!$B$9*'Premissas'!$B$30,2) -> 28045.4 | K15: =ROUND(I15-J15,2) -> 182059.6 | L15: =IF(A15>'Premissas'!$B$20,INDEX($K$5:$K$28,MAX(1,A15-'Premissas'!$B$20)),0) -> 156051.09 | M15: =ROUND(I15*'Premissas'!$B$10,2) -> 31515.75 | N15: =ROUND(I15*'Premissas'!$B$11,2) -> 6303.15 | O15: =ROUND(B15*'Premissas'!$B$12*'Premissas'!$B$30,2) -> 78750 | P15: =ROUND(B15*'Premissas'!$B$13*'Premissas'!$B$30,2) -> 7875 | Q15: =ROUND(D15*'Premissas'!$B$15,2) -> 30000 | R15: =ROUND(Q15*'Premissas'!$B$19+Q14*(1-'Premissas'!$B$19),2) -> 30000 | S15: =ROUND(E15*'Premissas'!$B$17,2) -> 14400 | T15: =ROUND(Q15*'Premissas'!$B$10,2) -> 4500 | U15: =ROUND(R15*'Premissas'!$B$18,2) -> 1500 | V15: =IF(A15<=12,'Premissas'!$B$24,'Premissas'!$B$25) -> 37000 | W15: =ROUND(G15+Q15,2) -> 258375 | X15: =ROUND(I15+Q15,2) -> 240105 | Y15: =ROUND(L15+R15,2) -> 186051.09 | Z15: =ROUND(SUM(M15:P15)+SUM(S15:V15),2) -> 181843.9 | AA15: =ROUND(Y15-Z15,2) -> 4207.19 | AB15: =ROUND(AB14+AA15,2) -> -397415.98 | AC15: =ROUND(X15-J15-SUM(M15:P15)-S15-T15-ROUND(Q15*'Premissas'!$B$18,2)-V15,2) -> 30215.7 | AD15: =ROUND(SUM($K$5:K15)-SUM($L$5:L15)+SUM($Q$5:Q15)-SUM($R$5:R15),2) -> 197059.6 | AE15: =MAX(0,AB15)*'Premissas'!$B$28 -> 0 | AF15: =IF(AB15>=0,A15,999) -> 999 | AG15: =IF(AE15>=Resumo!$E$9,A15,999) -> 999 | AH15: =AB15+Capital!$A$5 -> -297415.98 | AI15: =AB15+Capital!$A$6 -> -247415.98 | AJ15: =AB15+Capital!$A$7 -> -197415.98
A16: 12 | B16: ='Base'!B16 -> 2000 | C16: =ROUNDUP(B16/'Premissas'!$B$14,0) -> 100000 | D16: ='Base'!D16 -> 1 | E16: =D16*'Premissas'!$B$16 -> 80 | F16: =ROUND(B16*'Premissas'!$B$5,2) -> 58000 | G16: =ROUND(F16*'Premissas'!$B$30,2) -> 261000 | H16: =ROUND(G16*'Premissas'!$B$7,2) -> 20880 | I16: =ROUND(G16-H16,2) -> 240120 | J16: =ROUND(I16*'Premissas'!$B$8+B16*(1-'Premissas'!$B$7)*'Premissas'!$B$9*'Premissas'!$B$30,2) -> 32051.88 | K16: =ROUND(I16-J16,2) -> 208068.12 | L16: =IF(A16>'Premissas'!$B$20,INDEX($K$5:$K$28,MAX(1,A16-'Premissas'!$B$20)),0) -> 182059.6 | M16: =ROUND(I16*'Premissas'!$B$10,2) -> 36018 | N16: =ROUND(I16*'Premissas'!$B$11,2) -> 7203.6 | O16: =ROUND(B16*'Premissas'!$B$12*'Premissas'!$B$30,2) -> 90000 | P16: =ROUND(B16*'Premissas'!$B$13*'Premissas'!$B$30,2) -> 9000 | Q16: =ROUND(D16*'Premissas'!$B$15,2) -> 30000 | R16: =ROUND(Q16*'Premissas'!$B$19+Q15*(1-'Premissas'!$B$19),2) -> 30000 | S16: =ROUND(E16*'Premissas'!$B$17,2) -> 14400 | T16: =ROUND(Q16*'Premissas'!$B$10,2) -> 4500 | U16: =ROUND(R16*'Premissas'!$B$18,2) -> 1500 | V16: =IF(A16<=12,'Premissas'!$B$24,'Premissas'!$B$25) -> 37000 | W16: =ROUND(G16+Q16,2) -> 291000 | X16: =ROUND(I16+Q16,2) -> 270120 | Y16: =ROUND(L16+R16,2) -> 212059.6 | Z16: =ROUND(SUM(M16:P16)+SUM(S16:V16),2) -> 199621.6 | AA16: =ROUND(Y16-Z16,2) -> 12438 | AB16: =ROUND(AB15+AA16,2) -> -384977.98 | AC16: =ROUND(X16-J16-SUM(M16:P16)-S16-T16-ROUND(Q16*'Premissas'!$B$18,2)-V16,2) -> 38446.52 | AD16: =ROUND(SUM($K$5:K16)-SUM($L$5:L16)+SUM($Q$5:Q16)-SUM($R$5:R16),2) -> 223068.12 | AE16: =MAX(0,AB16)*'Premissas'!$B$28 -> 0 | AF16: =IF(AB16>=0,A16,999) -> 999 | AG16: =IF(AE16>=Resumo!$E$9,A16,999) -> 999 | AH16: =AB16+Capital!$A$5 -> -284977.98 | AI16: =AB16+Capital!$A$6 -> -234977.98 | AJ16: =AB16+Capital!$A$7 -> -184977.98
A17: 13 | B17: ='Base'!B17 -> 2200 | C17: =ROUNDUP(B17/'Premissas'!$B$14,0) -> 110000 | D17: ='Base'!D17 -> 2 | E17: =D17*'Premissas'!$B$16 -> 160 | F17: =ROUND(B17*'Premissas'!$B$5,2) -> 63800 | G17: =ROUND(F17*'Premissas'!$B$30,2) -> 287100 | H17: =ROUND(G17*'Premissas'!$B$7,2) -> 22968 | I17: =ROUND(G17-H17,2) -> 264132 | J17: =ROUND(I17*'Premissas'!$B$8+B17*(1-'Premissas'!$B$7)*'Premissas'!$B$9*'Premissas'!$B$30,2) -> 35257.07 | K17: =ROUND(I17-J17,2) -> 228874.93 | L17: =IF(A17>'Premissas'!$B$20,INDEX($K$5:$K$28,MAX(1,A17-'Premissas'!$B$20)),0) -> 208068.12 | M17: =ROUND(I17*'Premissas'!$B$10,2) -> 39619.8 | N17: =ROUND(I17*'Premissas'!$B$11,2) -> 7923.96 | O17: =ROUND(B17*'Premissas'!$B$12*'Premissas'!$B$30,2) -> 99000 | P17: =ROUND(B17*'Premissas'!$B$13*'Premissas'!$B$30,2) -> 9900 | Q17: =ROUND(D17*'Premissas'!$B$15,2) -> 60000 | R17: =ROUND(Q17*'Premissas'!$B$19+Q16*(1-'Premissas'!$B$19),2) -> 45000 | S17: =ROUND(E17*'Premissas'!$B$17,2) -> 28800 | T17: =ROUND(Q17*'Premissas'!$B$10,2) -> 9000 | U17: =ROUND(R17*'Premissas'!$B$18,2) -> 2250 | V17: =IF(A17<=12,'Premissas'!$B$24,'Premissas'!$B$25) -> 42000 | W17: =ROUND(G17+Q17,2) -> 347100 | X17: =ROUND(I17+Q17,2) -> 324132 | Y17: =ROUND(L17+R17,2) -> 253068.12 | Z17: =ROUND(SUM(M17:P17)+SUM(S17:V17),2) -> 238493.76 | AA17: =ROUND(Y17-Z17,2) -> 14574.36 | AB17: =ROUND(AB16+AA17,2) -> -370403.62 | AC17: =ROUND(X17-J17-SUM(M17:P17)-S17-T17-ROUND(Q17*'Premissas'!$B$18,2)-V17,2) -> 49631.17 | AD17: =ROUND(SUM($K$5:K17)-SUM($L$5:L17)+SUM($Q$5:Q17)-SUM($R$5:R17),2) -> 258874.93 | AE17: =MAX(0,AB17)*'Premissas'!$B$28 -> 0 | AF17: =IF(AB17>=0,A17,999) -> 999 | AG17: =IF(AE17>=Resumo!$E$9,A17,999) -> 999 | AH17: =AB17+Capital!$A$5 -> -270403.62 | AI17: =AB17+Capital!$A$6 -> -220403.62 | AJ17: =AB17+Capital!$A$7 -> -170403.62
... A28: 24 | B28: ='Base'!B28 -> 3000 | C28: =ROUNDUP(B28/'Premissas'!$B$14,0) -> 150000 | D28: ='Base'!D28 -> 2 | E28: =D28*'Premissas'!$B$16 -> 160 | F28: =ROUND(B28*'Premissas'!$B$5,2) -> 87000 | G28: =ROUND(F28*'Premissas'!$B$30,2) -> 391500 | H28: =ROUND(G28*'Premissas'!$B$7,2) -> 31320 | I28: =ROUND(G28-H28,2) -> 360180 | J28: =ROUND(I28*'Premissas'!$B$8+B28*(1-'Premissas'!$B$7)*'Premissas'!$B$9*'Premissas'!$B$30,2) -> 48077.82 | K28: =ROUND(I28-J28,2) -> 312102.18 | L28: =IF(A28>'Premissas'!$B$20,INDEX($K$5:$K$28,MAX(1,A28-'Premissas'!$B$20)),0) -> 312102.18 | M28: =ROUND(I28*'Premissas'!$B$10,2) -> 54027 | N28: =ROUND(I28*'Premissas'!$B$11,2) -> 10805.4 | O28: =ROUND(B28*'Premissas'!$B$12*'Premissas'!$B$30,2) -> 135000 | P28: =ROUND(B28*'Premissas'!$B$13*'Premissas'!$B$30,2) -> 13500 | Q28: =ROUND(D28*'Premissas'!$B$15,2) -> 60000 | R28: =ROUND(Q28*'Premissas'!$B$19+Q27*(1-'Premissas'!$B$19),2) -> 60000 | S28: =ROUND(E28*'Premissas'!$B$17,2) -> 28800 | T28: =ROUND(Q28*'Premissas'!$B$10,2) -> 9000 | U28: =ROUND(R28*'Premissas'!$B$18,2) -> 3000 | V28: =IF(A28<=12,'Premissas'!$B$24,'Premissas'!$B$25) -> 42000 | W28: =ROUND(G28+Q28,2) -> 451500 | X28: =ROUND(I28+Q28,2) -> 420180 | Y28: =ROUND(L28+R28,2) -> 372102.18 | Z28: =ROUND(SUM(M28:P28)+SUM(S28:V28),2) -> 296132.4 | AA28: =ROUND(Y28-Z28,2) -> 75969.78 | AB28: =ROUND(AB27+AA28,2) -> 342528.8 | AC28: =ROUND(X28-J28-SUM(M28:P28)-S28-T28-ROUND(Q28*'Premissas'!$B$18,2)-V28,2) -> 75969.78 | AD28: =ROUND(SUM($K$5:K28)-SUM($L$5:L28)+SUM($Q$5:Q28)-SUM($R$5:R28),2) -> 342102.18 | AE28: =MAX(0,AB28)*'Premissas'!$B$28 -> 171264.4 | AF28: =IF(AB28>=0,A28,999) -> 24 | AG28: =IF(AE28>=Resumo!$E$9,A28,999) -> 999 | AH28: =AB28+Capital!$A$5 -> 442528.8 | AI28: =AB28+Capital!$A$6 -> 492528.8 | AJ28: =AB28+Capital!$A$7 -> 542528.8

Sheet Resumo
A1: Resumo | financiamento integral condiciona todos os cenários
A4: Cenário | B4: M0 BRL | C4: Pico déficit BRL | D4: Reserva BRL | E4: Capital total BRL | F4: Payback projeto mês | G4: Dani hipotético mês | H4: Vendas brutas ano 1 | I4: Vendas brutas ano 2 | J4: Receita líquida ano 1 | K4: Receita líquida ano 2 | L4: Recebimentos ano 1 | M4: Recebimentos ano 2 | N4: Acumulado M24 BRL | O4: A receber M24 BRL
A5: Conservador | B5: ='Premissas'!$B$23 -> 100000 | C5: =MAX('Premissas'!$B$23,-MIN('Conservador'!AB5:AB28)) -> 737708.49 | D5: ='Premissas'!$B$25*'Premissas'!$B$26 -> 126000 | E5: =ROUNDUP((C5+D5)/'Premissas'!$B$27,0)*'Premissas'!$B$27 -> 870000 | F5: =IF(MIN('Conservador'!AF5:AF28)=999,"Sem retorno em 24m",MIN('Conservador'!AF5:AF28)) -> Sem retorno em 24m | G5: =IF(MIN('Conservador'!AG5:AG28)=999,"Sem retorno em 24m",MIN('Conservador'!AG5:AG28)) -> Sem retorno em 24m | H5: =SUM('Conservador'!W5:W16) -> 377550 | I5: =SUM('Conservador'!W17:W28) -> 1155750 | J5: =SUM('Conservador'!X5:X16) -> 352146 | K5: =SUM('Conservador'!X17:X28) -> 1070490 | L5: =SUM('Conservador'!Y5:Y16) -> 261132.52 | M5: =SUM('Conservador'!Y17:Y28) -> 904933.47 | N5: ='Conservador'!AB28 -> -737708.49 | O5: ='Conservador'!AD28 -> 86695.05
A6: Base | B6: ='Premissas'!$B$23 -> 100000 | C6: =MAX('Premissas'!$B$23,-MIN('Base'!AB5:AB28)) -> 398842.4 | D6: ='Premissas'!$B$25*'Premissas'!$B$26 -> 126000 | E6: =ROUNDUP((C6+D6)/'Premissas'!$B$27,0)*'Premissas'!$B$27 -> 530000 | F6: =IF(MIN('Base'!AF5:AF28)=999,"Sem retorno em 24m",MIN('Base'!AF5:AF28)) -> 19 | G6: =IF(MIN('Base'!AG5:AG28)=999,"Sem retorno em 24m",MIN('Base'!AG5:AG28)) -> Sem retorno em 24m | H6: =SUM('Base'!W5:W16) -> 1581250 | I6: =SUM('Base'!W17:W28) -> 5650000 | J6: =SUM('Base'!X5:X16) -> 1473950 | K6: =SUM('Base'!X17:X28) -> 5255600 | L6: =SUM('Base'!Y5:Y16) -> 1063052.1 | M6: =SUM('Base'!Y17:Y28) -> 4519582.2 | N6: ='Base'!AB28 -> 466065.35 | O6: ='Base'!AD28 -> 376780.2
A7: Escala24 | B7: ='Premissas'!$B$23 -> 100000 | C7: =MAX('Premissas'!$B$23,-MIN('Escala24'!AB5:AB28)) -> 384422.02 | D7: ='Premissas'!$B$25*'Premissas'!$B$26 -> 126000 | E7: =ROUNDUP((C7+D7)/'Premissas'!$B$27,0)*'Premissas'!$B$27 -> 520000 | F7: =IF(MIN('Escala24'!AF5:AF28)=999,"Sem retorno em 24m",MIN('Escala24'!AF5:AF28)) -> 14 | G7: =IF(MIN('Escala24'!AG5:AG28)=999,"Sem retorno em 24m",MIN('Escala24'!AG5:AG28)) -> 20 | H7: =SUM('Escala24'!W5:W16) -> 3601500 | I7: =SUM('Escala24'!W17:W28) -> 9780000 | J7: =SUM('Escala24'!X5:X16) -> 3361380 | K7: =SUM('Escala24'!X17:X28) -> 9084000 | L7: =SUM('Escala24'!Y5:Y16) -> 2427613.1 | M7: =SUM('Escala24'!Y17:Y28) -> 7957807.3 | N7: ='Escala24'!AB28 -> 1821002 | O7: ='Escala24'!AD28 -> 622967
A8: CAC15 | B8: ='Premissas'!$B$23 -> 100000 | C8: =MAX('Premissas'!$B$23,-MIN('CAC15'!AB5:AB28)) -> 698794.05 | D8: ='Premissas'!$B$25*'Premissas'!$B$26 -> 126000 | E8: =ROUNDUP((C8+D8)/'Premissas'!$B$27,0)*'Premissas'!$B$27 -> 830000 | F8: =IF(MIN('CAC15'!AF5:AF28)=999,"Sem retorno em 24m",MIN('CAC15'!AF5:AF28)) -> Sem retorno em 24m | G8: =IF(MIN('CAC15'!AG5:AG28)=999,"Sem retorno em 24m",MIN('CAC15'!AG5:AG28)) -> Sem retorno em 24m | H8: =SUM('CAC15'!W5:W16) -> 1581250 | I8: =SUM('CAC15'!W17:W28) -> 5650000 | J8: =SUM('CAC15'!X5:X16) -> 1473950 | K8: =SUM('CAC15'!X17:X28) -> 5255600 | L8: =SUM('CAC15'!Y5:Y16) -> 1063052.1 | M8: =SUM('CAC15'!Y17:Y28) -> 4519582.2 | N8: ='CAC15'!AB28 -> -615184.65 | O8: ='CAC15'!AD28 -> 376780.2
A9: FX4,5 | B9: ='Premissas'!$B$23 -> 100000 | C9: =MAX('Premissas'!$B$23,-MIN('FX4,5'!AB5:AB28)) -> 401623.17 | D9: ='Premissas'!$B$25*'Premissas'!$B$26 -> 126000 | E9: =ROUNDUP((C9+D9)/'Premissas'!$B$27,0)*'Premissas'!$B$27 -> 530000 | F9: =IF(MIN('FX4,5'!AF5:AF28)=999,"Sem retorno em 24m",MIN('FX4,5'!AF5:AF28)) -> 20 | G9: =IF(MIN('FX4,5'!AG5:AG28)=999,"Sem retorno em 24m",MIN('FX4,5'!AG5:AG28)) -> Sem retorno em 24m | H9: =SUM('FX4,5'!W5:W16) -> 1447125 | I9: =SUM('FX4,5'!W17:W28) -> 5157000 | J9: =SUM('FX4,5'!X5:X16) -> 1350555 | K9: =SUM('FX4,5'!X17:X28) -> 4802040 | L9: =SUM('FX4,5'!Y5:Y16) -> 979246.92 | M9: =SUM('FX4,5'!Y17:Y28) -> 4138124 | N9: ='FX4,5'!AB28 -> 342528.8 | O9: ='FX4,5'!AD28 -> 342102.18
A12: Receita líquida aqui significa após estornos, antes de tributos e demais custos. Recebimentos da loja já vêm líquidos da plataforma. Não somar receita e recebimentos.
A14: ALERTA: CAC USD10 → USD15 eleva capital-base a R$830 mil e elimina retorno em 24 meses. Nenhuma sensibilidade aumenta a agenda de vendas.
A16: Payback do projeto ≠ retorno de Dani. Coluna G: hipótese de Dani aportar SOZINHA todo capital de E e receber 50% do excedente positivo acumulado. Não há aporte/payout acordado nem lucro distribuível garantido.

Sheet Capital
A1: Cheques iniciais | déficits NÃO financiados
A4: Cheque inicial BRL | B4: Após M0 BRL | C4: Meses sem vendas | D4: Falta até capital-base | E4: Primeiro mês negativo Base | F4: Pior saldo Base BRL | G4: Déficit caixa a cobrir BRL | H4: Saldo M24 Base BRL | I4: Status
A5: 100000 | B5: =A5-'Premissas'!$B$23 -> 0 | C5: =B5/'Premissas'!$B$24 -> 0 | D5: =MAX(0,Resumo!E6-A5) -> 430000 | E5: =IF(A5<'Premissas'!$B$23,0,IF(MIN(IF(Base!AH5<0,Base!A5,999),IF(Base!AH6<0,Base!A6,999),IF(Base!AH7<0,Base!A7,999),IF(Base!AH8<0,Base!A8,999),IF(Base!AH9<0,Base!A9,999),IF(Base!AH10<0,Base!A10,999),IF(Base!AH11<0,Base!A11,999),IF(Base!AH12<0,Base!A12,999),IF(Base!AH13<0,Base!A13,999),IF(Base!AH14<0,Base!A14,999),IF(Base!AH15<0,Base!A15,999),IF(Base!AH16<0,Base!A16,999),IF(Base!AH17<0,Base!A17,999),IF(Base!AH18<0,Base!A18,999),IF(Base!AH19<0,Base!A19,999),IF(Base!AH20<0,Base!A20,999),IF(Base!AH21<0,Base!A21,999),IF(Base!AH22<0,Base!A22,999),IF(Base!AH23<0,Base!A23,999),IF(Base!AH24<0,Base!A24,999),IF(Base!AH25<0,Base!A25,999),IF(Base!AH26<0,Base!A26,999),IF(Base!AH27<0,Base!A27,999),IF(Base!AH28<0,Base!A28,999))=999,"Nenhum em 24m",MIN(IF(Base!AH5<0,Base!A5,999),IF(Base!AH6<0,Base!A6,999),IF(Base!AH7<0,Base!A7,999),IF(Base!AH8<0,Base!A8,999),IF(Base!AH9<0,Base!A9,999),IF(Base!AH10<0,Base!A10,999),IF(Base!AH11<0,Base!A11,999),IF(Base!AH12<0,Base!A12,999),IF(Base!AH13<0,Base!A13,999),IF(Base!AH14<0,Base!A14,999),IF(Base!AH15<0,Base!A15,999),IF(Base!AH16<0,Base!A16,999),IF(Base!AH17<0,Base!A17,999),IF(Base!AH18<0,Base!A18,999),IF(Base!AH19<0,Base!A19,999),IF(Base!AH20<0,Base!A20,999),IF(Base!AH21<0,Base!A21,999),IF(Base!AH22<0,Base!A22,999),IF(Base!AH23<0,Base!A23,999),IF(Base!AH24<0,Base!A24,999),IF(Base!AH25<0,Base!A25,999),IF(Base!AH26<0,Base!A26,999),IF(Base!AH27<0,Base!A27,999),IF(Base!AH28<0,Base!A28,999)))) -> 1 | F5: =MIN(B5,MIN(Base!AB5:AB28)+A5) -> -298842.4 | G5: =MAX(0,-F5) -> 298842.4 | H5: =Base!AB28+A5 -> 566065.35 | I5: Insuficiente; não é plano financiável
A6: 150000 | B6: =A6-'Premissas'!$B$23 -> 50000 | C6: =B6/'Premissas'!$B$24 -> 1.3513514 | D6: =MAX(0,Resumo!E6-A6) -> 380000 | E6: =IF(A6<'Premissas'!$B$23,0,IF(MIN(IF(Base!AI5<0,Base!A5,999),IF(Base!AI6<0,Base!A6,999),IF(Base!AI7<0,Base!A7,999),IF(Base!AI8<0,Base!A8,999),IF(Base!AI9<0,Base!A9,999),IF(Base!AI10<0,Base!A10,999),IF(Base!AI11<0,Base!A11,999),IF(Base!AI12<0,Base!A12,999),IF(Base!AI13<0,Base!A13,999),IF(Base!AI14<0,Base!A14,999),IF(Base!AI15<0,Base!A15,999),IF(Base!AI16<0,Base!A16,999),IF(Base!AI17<0,Base!A17,999),IF(Base!AI18<0,Base!A18,999),IF(Base!AI19<0,Base!A19,999),IF(Base!AI20<0,Base!A20,999),IF(Base!AI21<0,Base!A21,999),IF(Base!AI22<0,Base!A22,999),IF(Base!AI23<0,Base!A23,999),IF(Base!AI24<0,Base!A24,999),IF(Base!AI25<0,Base!A25,999),IF(Base!AI26<0,Base!A26,999),IF(Base!AI27<0,Base!A27,999),IF(Base!AI28<0,Base!A28,999))=999,"Nenhum em 24m",MIN(IF(Base!AI5<0,Base!A5,999),IF(Base!AI6<0,Base!A6,999),IF(Base!AI7<0,Base!A7,999),IF(Base!AI8<0,Base!A8,999),IF(Base!AI9<0,Base!A9,999),IF(Base!AI10<0,Base!A10,999),IF(Base!AI11<0,Base!A11,999),IF(Base!AI12<0,Base!A12,999),IF(Base!AI13<0,Base!A13,999),IF(Base!AI14<0,Base!A14,999),IF(Base!AI15<0,Base!A15,999),IF(Base!AI16<0,Base!A16,999),IF(Base!AI17<0,Base!A17,999),IF(Base!AI18<0,Base!A18,999),IF(Base!AI19<0,Base!A19,999),IF(Base!AI20<0,Base!A20,999),IF(Base!AI21<0,Base!A21,999),IF(Base!AI22<0,Base!A22,999),IF(Base!AI23<0,Base!A23,999),IF(Base!AI24<0,Base!A24,999),IF(Base!AI25<0,Base!A25,999),IF(Base!AI26<0,Base!A26,999),IF(Base!AI27<0,Base!A27,999),IF(Base!AI28<0,Base!A28,999)))) -> 2 | F6: =MIN(B6,MIN(Base!AB5:AB28)+A6) -> -248842.4 | G6: =MAX(0,-F6) -> 248842.4 | H6: =Base!AB28+A6 -> 616065.35 | I6: Insuficiente; não é plano financiável
A7: 200000 | B7: =A7-'Premissas'!$B$23 -> 100000 | C7: =B7/'Premissas'!$B$24 -> 2.7027027 | D7: =MAX(0,Resumo!E6-A7) -> 330000 | E7: =IF(A7<'Premissas'!$B$23,0,IF(MIN(IF(Base!AJ5<0,Base!A5,999),IF(Base!AJ6<0,Base!A6,999),IF(Base!AJ7<0,Base!A7,999),IF(Base!AJ8<0,Base!A8,999),IF(Base!AJ9<0,Base!A9,999),IF(Base!AJ10<0,Base!A10,999),IF(Base!AJ11<0,Base!A11,999),IF(Base!AJ12<0,Base!A12,999),IF(Base!AJ13<0,Base!A13,999),IF(Base!AJ14<0,Base!A14,999),IF(Base!AJ15<0,Base!A15,999),IF(Base!AJ16<0,Base!A16,999),IF(Base!AJ17<0,Base!A17,999),IF(Base!AJ18<0,Base!A18,999),IF(Base!AJ19<0,Base!A19,999),IF(Base!AJ20<0,Base!A20,999),IF(Base!AJ21<0,Base!A21,999),IF(Base!AJ22<0,Base!A22,999),IF(Base!AJ23<0,Base!A23,999),IF(Base!AJ24<0,Base!A24,999),IF(Base!AJ25<0,Base!A25,999),IF(Base!AJ26<0,Base!A26,999),IF(Base!AJ27<0,Base!A27,999),IF(Base!AJ28<0,Base!A28,999))=999,"Nenhum em 24m",MIN(IF(Base!AJ5<0,Base!A5,999),IF(Base!AJ6<0,Base!A6,999),IF(Base!AJ7<0,Base!A7,999),IF(Base!AJ8<0,Base!A8,999),IF(Base!AJ9<0,Base!A9,999),IF(Base!AJ10<0,Base!A10,999),IF(Base!AJ11<0,Base!A11,999),IF(Base!AJ12<0,Base!A12,999),IF(Base!AJ13<0,Base!A13,999),IF(Base!AJ14<0,Base!A14,999),IF(Base!AJ15<0,Base!A15,999),IF(Base!AJ16<0,Base!A16,999),IF(Base!AJ17<0,Base!A17,999),IF(Base!AJ18<0,Base!A18,999),IF(Base!AJ19<0,Base!A19,999),IF(Base!AJ20<0,Base!A20,999),IF(Base!AJ21<0,Base!A21,999),IF(Base!AJ22<0,Base!A22,999),IF(Base!AJ23<0,Base!A23,999),IF(Base!AJ24<0,Base!A24,999),IF(Base!AJ25<0,Base!A25,999),IF(Base!AJ26<0,Base!A26,999),IF(Base!AJ27<0,Base!A27,999),IF(Base!AJ28<0,Base!A28,999)))) -> 3 | F7: =MIN(B7,MIN(Base!AB5:AB28)+A7) -> -198842.4 | G7: =MAX(0,-F7) -> 198842.4 | H7: =Base!AB28+A7 -> 666065.35 | I7: Insuficiente; não é plano financiável
A10: As três colunas finais de cada aba mensal mostram saldos com cheques de R$100/150/200 mil. Continuar calculando depois de saldo negativo é apenas diagnóstico do déficit: execução real requer caixa adicional.
A12: Falta até capital-base inclui reserva de segurança e arredondamento; déficit a cobrir não inclui reserva. Meses sem vendas = saldo após M0 / fixo ano 1; não é runway real com vendas e custos variáveis.

Sheet Escala
A1: Escala mensal estabilizada | não inclui rampa nem M0
A4: Pedidos/mês | B4: Mapas/mês | C4: Loja bruta USD | D4: Vendas brutas BRL | E4: Receita após estornos BRL | F4: Mídia BRL | G4: Visitas qualificadas | H4: Horas diretas TI | I4: Fixo BRL | J4: Resultado operacional BRL
A5: 300 | B5: 0 | C5: =A5*'Premissas'!$B$5 -> 8700 | D5: =C5*'Premissas'!$B$6+B5*'Premissas'!$B$15 -> 43500 | E5: =C5*'Premissas'!$B$6*(1-'Premissas'!$B$7)+B5*'Premissas'!$B$15 -> 40020 | F5: =A5*'Premissas'!$B$12*'Premissas'!$B$6 -> 15000 | G5: =ROUNDUP(A5/'Premissas'!$B$14,0) -> 15000 | H5: =B5*'Premissas'!$B$16 -> 0 | I5: ='Premissas'!$B$25 -> 42000 | J5: =ROUND(A5*Economia!C13+B5*Economia!B21-I5,2) -> -31025.58
A6: 1000 | B6: 1 | C6: =A6*'Premissas'!$B$5 -> 29000 | D6: =C6*'Premissas'!$B$6+B6*'Premissas'!$B$15 -> 175000 | E6: =C6*'Premissas'!$B$6*(1-'Premissas'!$B$7)+B6*'Premissas'!$B$15 -> 163400 | F6: =A6*'Premissas'!$B$12*'Premissas'!$B$6 -> 50000 | G6: =ROUNDUP(A6/'Premissas'!$B$14,0) -> 50000 | H6: =B6*'Premissas'!$B$16 -> 80 | I6: ='Premissas'!$B$25 -> 42000 | J6: =ROUND(A6*Economia!C13+B6*Economia!B21-I6,2) -> 4181.4
A7: 3000 | B7: 2 | C7: =A7*'Premissas'!$B$5 -> 87000 | D7: =C7*'Premissas'!$B$6+B7*'Premissas'!$B$15 -> 495000 | E7: =C7*'Premissas'!$B$6*(1-'Premissas'!$B$7)+B7*'Premissas'!$B$15 -> 460200 | F7: =A7*'Premissas'!$B$12*'Premissas'!$B$6 -> 150000 | G7: =ROUNDUP(A7/'Premissas'!$B$14,0) -> 150000 | H7: =B7*'Premissas'!$B$16 -> 160 | I7: ='Premissas'!$B$25 -> 42000 | J7: =ROUND(A7*Economia!C13+B7*Economia!B21-I7,2) -> 86944.2
A8: 5000 | B8: 3 | C8: =A8*'Premissas'!$B$5 -> 145000 | D8: =C8*'Premissas'!$B$6+B8*'Premissas'!$B$15 -> 815000 | E8: =C8*'Premissas'!$B$6*(1-'Premissas'!$B$7)+B8*'Premissas'!$B$15 -> 757000 | F8: =A8*'Premissas'!$B$12*'Premissas'!$B$6 -> 250000 | G8: =ROUNDUP(A8/'Premissas'!$B$14,0) -> 250000 | H8: =B8*'Premissas'!$B$16 -> 240 | I8: ='Premissas'!$B$25 -> 42000 | J8: =ROUND(A8*Economia!C13+B8*Economia!B21-I8,2) -> 169707
A11: Receita loja em USD; total convertido a câmbio hipotético. Resultado usa contribuição de ambas as frentes menos fixo ano 2. Não é caixa de lançamento nem dividendo. Escala exige mídia, visitas, capacidade de entrega e validação fiscal.

Sheet Gates
A1: Financiamento por marcos | decisão humana, não autorização
A4: Marco | B4: Condição / meta proposta
A5: Antes de comprar | B5: Confirmar tese, disponibilidade de financiamento completo, acordo societário, cotação brasileira da DGX e limites de aprovação. Uma DGX desde o início é hipótese, não compra autorizada.
A6: Dias 1–30 | B6: Meta: entrevistar 10 potenciais compradores de nichos e 5 contatos TI. Selecionar até 3 nichos por dor verificável, disposição de pagar, entrega demonstrável e baixo risco regulatório.
A7: Dias 31–60 | B7: Meta: até 3 ofertas testáveis; validar checkout, entrega, idioma, dados, direitos autorais e revisão humana. Não construir marketplace próprio antes de vender.
A8: Dias 61–90 | B8: Alvo condicional: 50 vendas loja e 1 mapa pago. Metas de cenário, não pipeline existente. Liberação por marcos requer critérios formais ainda a acordar.
A9: M6 / M12 Base | B9: M6: 500 vendas/mês e 2 mapas acumulados. M12: 2.000 vendas/mês e 8 mapas acumulados. Acompanhar estornos, CAC, contribuição, horas, caixa e qualidade.
A10: Parar perdas | B10: Se CAC, reembolso ou entrega invalidarem contribuição e caixa, suspender expansão e revisar oferta. Sem limites numéricos de aprovação já acordados; não confundir teto teórico de CAC com meta sustentável.
A11: Gestão e controles | B11: Proposta a implantar: agentes reconciliam checkout, banco, ads, CRM e projetos com autorização. Sócios têm leitura; diário operacional, reunião semanal e prestação mensal. Humanos aprovam pagamentos, contratos, publicação e compras.
A12: Decisão conjunta | B12: AUMI + Dani aprovam orçamento e despesas relevantes, limites a formalizar. Permissões mínimas, logs, fontes e separação de dados. Agentes não têm acesso financeiro irrestrito.
A13: Infraestrutura | B13: M0: DGX65k + proteção4k + rede2k + backup3k + periféricos2k =76k; jurídico12k + segurança12k =24k. Cloud, aplicação, checkout e backup separados. Uma máquina sem redundância.
A14: Fixo ano 1 | B14: Produto8k + engenharia18k + especialistas6k + cloud1k + ferramentas1k + prospecção1,5k + administração1k + energia0,5k =37k. Ano 2:42k. Envelopes, não cargos/salários pesquisados.
A15: Mapa delimitado | B15: R$30 mil propostos; 80h diretas; 2–4 semanas após acesso/contrato; um domínio, até40 componentes e80 relações, duas fontes autorizadas e duas validações. Sem pentest, alteração produtiva ou garantia de economia.
A16: Pendências societárias | B16: Dani50%; AUMI50% conjunto. Divisão Marcos/Luciana/João, aporte individual, cargos, remuneração, veículo jurídico, propriedade intelectual, impasse e saída a formalizar.

Sheet Fontes
A1: Fontes, status e limites de leitura
A4: Fonte | B4: Data informada | C4: URL clicável | D4: O que sustenta | E4: Limite
A5: hotmart-market | B5: 2024-03-21 | C5: https://press.hotmart.com/hotmart-company-announces-record-breaking-10-billion-in-global-creator-earnings | D5: Hotmart/Teachable:21 milhões de consumidores compraram nos12 meses anteriores; global, autorrelatado. GMV de criadores LATAM exceto Brasil cresceu50% entre2022 e2023. Não é nosso TAM nem demanda validada. | E5: Evidência contextual/técnica; não valida nossa demanda, preço, CAC, câmbio ou regime fiscal.
A6: hotmart-fees | B6: 2026-09-18; tarifa efetiva2026-09-21 | C6: https://suportehotmart.zendesk.com/hc/en-us/articles/208298448-What-are-the-fees-charged-by-Hotmart | D6: Tabela USD>15 e FAQ:9,9%+USD1,00 por venda concluída. Um parágrafo antigo ainda cita0,50; adotado1,00 conforme tabela/FAQ atualizados. Tributos/cartão não incluídos; reembolso cancela taxa. | E6: Evidência contextual/técnica; não valida nossa demanda, preço, CAC, câmbio ou regime fiscal.
A7: flexera | B7: 2025-03-19 | C7: https://www.flexera.com/about-us/press-center/new-flexera-report-finds-84-percent-of-organizations-struggle-to-manage-cloud-spend | D7: 84% dos respondentes identificaram gestão do gasto cloud como principal desafio; pesquisa global com mais de750 profissionais. Não demonstra compra do nosso mapa. | E7: Evidência contextual/técnica; não valida nossa demanda, preço, CAC, câmbio ou regime fiscal.
A8: gsma | B8: 2026-05-13 | C8: https://www.gsma.com/about-us/regions/latin-america-and-the-caribbean/gsma_resources/the-mobile-economy-latin-america-2026/ | D8: Contexto regional de expansão digital, cloud,IA e segurança; não usar PIB mobile como TAM de infoprodutos. | E8: Evidência contextual/técnica; não valida nossa demanda, preço, CAC, câmbio ou regime fiscal.
A9: nvidia | B9: 2026-09-10 | C9: https://docs.nvidia.com/dgx/dgx-spark/hardware.html | D9: GB10/Grace Blackwell,20 núcleos ARM,128GB unificados,1TB ou4TB NVMe,10GbE,fonte240W. Escolha4TB no orçamento. R$65k é provisão sem cotação brasileira. | E9: Evidência contextual/técnica; não valida nossa demanda, preço, CAC, câmbio ou regime fiscal.
A12: Todas as vendas, conversões,preços,CAC,reembolsos,câmbio e prazos são hipóteses não validadas.
A14: R$37k/mês no ano1 e42k no ano2; trabalho de entrega TI e suporte da loja estão nos variáveis, sem dupla contagem de P&D.
A16: Simulação exige capital suficiente. Cheques100/150/200k não sustentam o fluxo-base de530k.
A18: Payback do projeto: primeiro mês em que fluxo acumulado sem aportes após M0 deixa de ser negativo; antes de dividendos, juros e tributos pessoais.
A20: Hipótese Dani exclusivamente ilustrativa: ela financia todo o capital requerido e recebe50% do excedente acumulado positivo após recuperação do projeto, sem reinvestimento; aporte/política não definidos e distribuição depende de lucro legalmente disponível.
A22: Tributos15% são provisão gerencial, não enquadramento tributário. Crescimento acima dos limites de regime exige contador; checkout pode cobrar tributos do comprador além do preço.
A24: A DGX é ferramenta de produção/inferência, não gargalo de cada download. Demanda/comercial/suporte exigem validação própria.
A26: Topologic empresarial200k+12k/mês e receitas adjacentes não entram no novo fluxo.
A28: Autoridade numérica: pitch-data.json, revisão 2026-10-02. Séries mensais e caches preservados. As fórmulas referenciam entradas e células; não incorporam projeções da oferta empresarial antiga. Nenhuma pesquisa adicional de taxa ou cotação feita na geração.
